{"title":"Combined feed","url":"https://MOVIECORD.github.io/feeds/all.xml","elements":[{"title":"'모가디슈' 앵콜 무비토크 라이브 (V SCREEN)","contents":"1시간 전","link":"https://www.vlive.tv/post/0-24566854","retrieved":1628598224800,"image":"https://v-phinf.pstatic.net/20210806_243/1628236798492OR6bD_JPEG/upload_44506405556429007d119c893-848b-42de-af50-a3302b3268be.jpg?type=f359x202"},{"title":"(예고) '모가디슈' 앵콜 무비토크 라이브 (V SCREEN)","contents":"8.6.","link":"https://www.vlive.tv/post/1-24570142","retrieved":1628598224800,"image":"https://v-phinf.pstatic.net/20210806_248/1628234934179QHe2E_JPEG/2fc8ab43-f687-11eb-89ce-48df379ccacc_03.jpg?type=f359x202"},{"title":"(FULL) '모가디슈' 무비토크 라이브 (V SCREEN)","contents":"7.9.","link":"https://www.vlive.tv/post/1-23713500","retrieved":1628598224801,"image":"https://v-phinf.pstatic.net/20210625_216/16245987408395Bdg3_JPEG/upload_68678462169962418be50f615-4262-4cb9-b3be-ee92cf41b374.jpg?type=f359x202"},{"title":"(예고) '모가디슈' 무비토크 라이브 (V SCREEN)","contents":"7.6.","link":"https://www.vlive.tv/post/0-23910007","retrieved":1628598224778},{"title":"(FULL) '발신제한' 무비토크 라이브 (V SCREEN)","contents":"6.11.","link":"https://www.vlive.tv/post/0-23275422","retrieved":1628598224779},{"title":"(예고) '발신제한' 무비토크 (V SCREEN)","contents":"6.4.","link":"https://www.vlive.tv/post/1-23301153","retrieved":1628598224780},{"title":"2021 평창국제평화영화제 온라인 기자간담회 라이브 (V SCREEN)","contents":"5.24.","link":"https://www.vlive.tv/post/1-22932838","retrieved":1628598224781},{"title":"(FULL) 카페 사장 최준과 함께하는 '크루즈 패밀리: 뉴 에이지' 무비토크 (V SCREEN)","contents":"5.3.","link":"https://www.vlive.tv/post/0-22513790","retrieved":1628598224781},{"title":"(예고) 카페 사장 최준과 함께하는 '크루즈 패밀리: 뉴 에이지' 무비토크 (V SCREEN)","contents":"4.23.","link":"https://www.vlive.tv/post/0-22513573","retrieved":1628598224782},{"title":"'더 파더' 10분 하이라이트 영상 (V SCREEN)","contents":"4.5.","link":"https://www.vlive.tv/post/1-22126830","retrieved":1628598224782},{"title":"(FULL) 변요한과 함께 하는 '자산어보' 온라인GV (V SCREEN)","contents":"4.2.","link":"https://www.vlive.tv/post/1-21974780","retrieved":1628598224783},{"title":"(예고) '더 파더' 10분 하이라이트 영상 독점공개! (V SCREEN)","contents":"4.1.","link":"https://www.vlive.tv/post/1-22126753","retrieved":1628598224783},{"title":"(예고) '자산어보' 온라인 GV (V SCREEN)","contents":"3.23.","link":"https://www.vlive.tv/post/1-21974684","retrieved":1628598224784},{"title":"(예고) 미국이 숨긴 충격적 진실 '모리타니안' 개봉 전 미리 보는 10분 하이라이트 (V SCREEN)","contents":"3.11.","link":"https://www.vlive.tv/post/1-21758631","retrieved":1628598224785},{"title":"'라야와 마지막 드래곤' V라이브 하이라이트 #3 '라야' OX 퀴즈 (V SCREEN)","contents":"3.4.","link":"https://www.vlive.tv/post/1-21625746","retrieved":1628598224786},{"title":"'라야와 마지막 드래곤' V라이브 하이라이트 #1 정열의 전사 리더 효정 (V SCREEN)","contents":"3.4.","link":"https://www.vlive.tv/post/1-21625553","retrieved":1628598224787},{"title":"'라야와 마지막 드래곤' V라이브 하이라이트 #4 천만 하트 감사 인사 (V SCREEN)","contents":"3.4.","link":"https://www.vlive.tv/post/1-21625817","retrieved":1628598224790},{"title":"21년째 깨지지 않는 기록, 할리우드도 인정한 아우라 (다음영화 뉴스 ─ 인기)","contents":"[양형석 기자] 모든 나라 사람들이 마찬가지지만 미국인들은 자국에 대한 자부심이 굉장히 강하다. 미국 내 야구리그 결승전을 오만하게 '월드시리즈'라고 부를 정도. 미국 남자농구 대표팀은 1992년 바르셀로나 올림픽부터 (올림픽에서) 무패 행진을 이어오다가 2004년 아테네 올림픽에서 아르헨티나에게 덜미를 잡혔다. 당시 르브론 제임스와 앨런 아이버슨을 비롯한","link":"https://movie.v.daum.net/v/20210810110301255","retrieved":1628583604604,"image":"https://img1.daumcdn.net/thumb/S732x228/?fname=https%3A%2F%2Ft1.daumcdn.net%2Fnews%2F202108%2F10%2Fohmynews%2F20210810110306782ufvw.jpg"},{"title":"하정우, '최연소 1억 배우'의 추락 [MD포커스](종합) (다음영화 뉴스 ─ 인기)","contents":"[마이데일리 = 김나라 기자] 하정우(43·본명 김성훈)가 프로포폴 불법 투약 혐의를 인정했다. 믿고 보는 '최연소 1억 배우'로서 쌓아온 대중의 신뢰도를 스스로 추락시켰다. 10일 오전 10시 33분께 서울 서초구 서울중앙지법에선 형사24단독(박설아 판사) 심리로 마약류 관리에 관한 법률 위반(향정) 등 혐의로 기소된 하정우에 대한 첫 공판이 열렸다.","link":"https://movie.v.daum.net/v/20210810162819052","retrieved":1628583604604,"image":"https://img1.daumcdn.net/thumb/S732x228/?fname=https%3A%2F%2Ft1.daumcdn.net%2Fnews%2F202108%2F10%2Fmydaily%2F20210810162819405ayjq.jpg"},{"title":"혐의 인정한 하정우, 영화계도 촉각 [종합] (다음영화 뉴스 ─ 인기)","contents":"[스포츠경향] 프로포폴 불법 투약 혐의를 인정한 배우 하정우의 재판 향방에 영화계 또한 촉각을 곤두세우고 있다.하정우는 10일 오전 서울중앙지법 형사24단독 박설아 판사 심리로 진행된 첫 공판에 출석해 자신의 혐의 대부분을 인정했다.하정우는 2019년 1월부터 9월까지 성형외과에서 프로포폴을 10차례 이상 불법으로 투약한 혐의로 기소됐고 검찰은 벌금 10","link":"https://movie.v.daum.net/v/20210810150658898","retrieved":1628579631139,"image":"https://img1.daumcdn.net/thumb/S384x240/?fname=https%3A%2F%2Ft1.daumcdn.net%2Fnews%2F202108%2F10%2Fsportskhan%2F20210810152856366slgi.jpg"},{"title":"\"뼈저리게 후회\" 울먹인 하정우, '변호인 10명 선임' 입 열었다 \"글쎄요..\" [종합] (다음영화 뉴스 ─ 인기)","contents":"[마이데일리 = 김나라 기자] \"프로포폴 불법 투약, 뼈저리게 후회하고 있다.\" (하정우(43·본명 김성훈)) 10일 오전 10시 33분께 서울 서초구 서울중앙지법에선 형사24단독(박설아 판사) 심리로 마약류 관리에 관한 법률 위반(향정) 등 혐의로 기소된 배우 하정우에 대한 첫 공판이 열렸다. 앞서 지난 2019년 1월부터 9월까지 하정우는 성형외과에서","link":"https://movie.v.daum.net/v/20210810124454490","retrieved":1628568378448,"image":"https://img1.daumcdn.net/thumb/S384x240/?fname=https%3A%2F%2Ft1.daumcdn.net%2Fnews%2F202108%2F10%2Fmydaily%2F20210810124455025ypmu.jpg"},{"title":"[단독] 전종서, 할리우드 첫 주연작 베니스영화제 초청에도 불참 까닭은(종합) (다음영화 뉴스 ─ 인기)","contents":"(서울=뉴스1) 정유진 기자 = 배우 전종서의 할리우드 진출작 '모나 리자 앤드 블러드 문'(감독 애나 릴리 아미푸르)이 제78회 베니스 국제영화제(베니스 영화제) 경쟁 부문에 초청된 가운데, 전종서의 영화제 참석이 최종 불발됐다. 넷플릭스 드라마 '종이의 집' 촬영에 집중하기 위해서다. 10일 뉴스1 취재 결과, 전종서는 고심 끝에 베니스 영화제에","link":"https://movie.v.daum.net/v/20210810145423347","retrieved":1628586908574,"image":"https://img1.daumcdn.net/thumb/S384x240/?fname=https%3A%2F%2Ft1.daumcdn.net%2Fnews%2F202108%2F10%2FNEWS1%2F20210810145423262mxbe.jpg"},{"title":"[D:영화 뷰] 코로나19가 만들어낸 충무로의 새 얼굴 (다음영화 뉴스 ─ 인기)","contents":"코로나19로 인해 올해 극장가는 한 치 앞을 알 수 없는 안갯속을 걸어왔다. 많은 사람들이 극장가에 발길을 끊었고 개봉 예정이었던 신작들도 피해를 최소화하고자 개봉을 수차례 연기하며 진퇴양난의 상황에 놓였다. 그럼에도 수확이 있다면 미래가 기대되는 신인 배우들의 활약이 충무로의 미래를 다시 한번 밝혔다는 점이다.매년 충무로는 연기력과 티켓 파워가 보장된 4","link":"https://movie.v.daum.net/v/20210810140256400","retrieved":1628583604672,"image":"https://img1.daumcdn.net/thumb/S384x240/?fname=https%3A%2F%2Ft1.daumcdn.net%2Fnews%2F202108%2F10%2Fdailian%2F20210810140302249rwoh.jpg"},{"title":"태국 무당 이어 인도네시아 주술사, 글로벌로 가는 K호러 (다음영화 뉴스 ─ 인기)","contents":"나홍진 감독이 제작한 한국산 태국 공포영화 ‘랑종’(7월 14일 개봉, 감독 반종 피산다나쿤)이 개봉 한 달 만에 82만 관객을 동원하며 올해 한국영화 흥행 3위에 올랐다. ‘모가디슈’ ‘발신제한’에 이어서다. ‘랑종’은 태국말로 무당(ร่างทรง)이라는 뜻. 신내림이 대물림되는 태국 무당 가문의 비극을 그렸다. 이어 ‘부산행’ 감독 연상호가 각본을","link":"https://movie.v.daum.net/v/20210810000551902","retrieved":1628556611572,"image":"https://img1.daumcdn.net/thumb/S384x240/?fname=https%3A%2F%2Ft1.daumcdn.net%2Fnews%2F202108%2F10%2Fjoongang%2F20210810000551755ggzf.jpg"},{"title":"\"'헐크' 어보미네이션→'닥스' 웡 등장\"..'샹치'로 보여줄 MCU 페이즈4의 확장 (다음영화 뉴스 ─ 인기)","contents":"[스포츠조선 이승미 기자]마블의 강력한 새 슈퍼 히어로 샹치의 이야기를 그린 '샹치와 텐 링즈의 전설'이 마블 페이즈 4의 확장된 세계관을 암시하는 단서들을 영화 속에 숨겨 놓은 것으로 전해져 예비 관객들의 가슴을 뛰게 만들고 있다. '샹치와 텐 링즈의 전설'에서 마블 세계관을 뒤흔들 강력한 힘의 원천인 텐 링즈가 2008년 시작된 '아이언맨","link":"https://movie.v.daum.net/v/20210810083313936","retrieved":1628586908575,"image":"https://img1.daumcdn.net/thumb/S384x240/?fname=https%3A%2F%2Ft1.daumcdn.net%2Fnews%2F202108%2F10%2FSpoChosun%2F20210810083314317yquq.jpg"},{"title":"[인터뷰]류승완 \"'모가디슈' 비싼 값에도 OTT 넘기기 싫었다\" (다음영화 뉴스 ─ 인기)","contents":"[아시아경제 이이슬 기자] “아무리 비싼 돈을 준다 해도 ‘모가디슈’를 스트리밍(OTT)에 넘길 수는 없었다.” 류승완 감독은 코로나19(신종 코로나바이러스감염증) 여파 속 극장에 영화를 공개한 후 이같이 말했다. 영화를 극장에서 체험하길 바란 원칙을 고수했다는 설명이다. 그러면서 “아프리카의 열기를 느낄 수 있는 여름에 선보이고 싶었다”고 했다. 류승완","link":"https://movie.v.daum.net/v/20210810135158022","retrieved":1628586908575,"image":"https://img1.daumcdn.net/thumb/S384x240/?fname=https%3A%2F%2Ft1.daumcdn.net%2Fnews%2F202108%2F10%2Fakn%2F20210810135200118nind.jpg"},{"title":"교사 투신 사건 뒤, 새로 부임한 선생이 목격한 충격적 풍경 (다음영화 뉴스 ─ 인기)","contents":"'안방극장'에선 처음 또는 다시 볼 만한 영화, 드라마, 애니메이션을 소개하고자 합니다. 세월의 흔적이 묻은 작품부터 아직 국내에 정식으로 소개되지 않은 작품까지 다양하게 다루려고 합니다. &lt;편집자말&gt; [이학후 기자] ▲ &nbsp;영화 &lt;학교는 끝났다&gt; 포스터    ⓒ (주)플릭스코  &nbsp;명문 학교 '세인트 요셉'에서 12명의 영재로 구성된 학업성취","link":"https://movie.v.daum.net/v/20210809133900518","retrieved":1628536309011,"image":"https://img1.daumcdn.net/thumb/S384x240/?fname=https%3A%2F%2Ft1.daumcdn.net%2Fnews%2F202108%2F09%2Fohmynews%2F20210809133906453xwzv.jpg"},{"title":"[SC초점]'모가디슈' 올해 韓영화 최초 200만 목전..예매율 1위 '싱크홀', 쌍끌이 흥행 예고 (다음영화 뉴스 ─ 인기)","contents":"[스포츠조선 이승미 기자] 영화 '모가디슈'가 올해 한국 영화 최초 200만 돌파를 목전에 두고 있다. 9일 영화진흥위원회 영화관입장권 통합전산망에 따르면 지난달 28일 개봉한 '모가디슈'는 2주 연속 박스오피스 1위를 차지하며 누적관객수 171만2265명을 기록했다. 현재의 추세라면 이번 주 200만을 가뿐히 넘어설 것으로 보인다. '모가디","link":"https://movie.v.daum.net/v/20210809154217389","retrieved":1628590595317,"image":"https://img1.daumcdn.net/thumb/S384x240/?fname=https%3A%2F%2Ft1.daumcdn.net%2Fnews%2F202108%2F09%2FSpoChosun%2F20210809154218512gcan.jpg"},{"title":"79세 해리슨 포드, ♥22세 연하 부인·입양 딸과 크로아티아서 휴식..'인디아나 존스5' 촬영은 언제?[해외이슈] (다음영화 뉴스 ─ 인기)","contents":"[마이데일리 = 곽명동 기자]할리우드 스타 해리슨 포드(79)이 부인 칼리스타 플록하트(57), 입양한 딸 리암 플록하트(20)와 크로아티아에서 휴식을 취하는 모습이 목격됐다. 연예매체 페이지식스는 9일(현지시간) 해리슨 포트가 크로아티아의 두브로브니크의 빌라 발코니에서 셔츠를 벗은 채 어깨 마사지를 받고 있는 현장을 공개했다. 플록하트와 리암은 근처","link":"https://movie.v.daum.net/v/20210810084210159","retrieved":1628556611565,"image":"https://img1.daumcdn.net/thumb/S384x240/?fname=https%3A%2F%2Ft1.daumcdn.net%2Fnews%2F202108%2F10%2Fmydaily%2F20210810084210696phpd.jpg"},{"title":"200만 고지 다가선 '모가디슈', 손익분기점도 넘길까 (다음영화 뉴스 ─ 인기)","contents":"[성하훈 기자] ▲ &nbsp;&lt;모가디슈&gt;의 한 장면    ⓒ 롯데엔터테인먼트  &nbsp;&lt;모가디슈&gt;는 손익분기점을 넘어설 수 있을까? 2주 연속 박스오피스 1위를 차지하며 모처럼 한국영화의 힘을 보여주고 있는 &lt;모가디슈&gt;가 8일까지 누적 171만을 기록하며 200만 고지에 다가섰다. 주말 이틀간 39만 관객이 찾은 데다. 2주 연속 일요일 관객이 토요일보다","link":"https://movie.v.daum.net/v/20210809093900734","retrieved":1628556611575,"image":"https://img1.daumcdn.net/thumb/S384x240/?fname=https%3A%2F%2Ft1.daumcdn.net%2Fnews%2F202108%2F09%2Fohmynews%2F20210809093905679uaax.jpg"},{"title":"[공식] 변요한X김무열 만난 '보이스', 9월 개봉 확정..韓최초 보이스피싱 범죄물 탄생 (다음영화 뉴스 ─ 인기)","contents":"[스포츠조선 조지영 기자] 국내 최초로 보이스피싱의 모든 것을 파헤치는 보이스피싱 리얼 범죄 액션 영화 '보이스'(김선·김곡 감독, 수필름 제작)가 오는 9월 개봉을 확정하고 1차 포스터 3종을 공개했다. '보이스'의 1차 포스터는 발신자와 수신자의 상반된 입장을 담아 눈길을 사로잡는다. 누구나 한번쯤 받아 봤을법한 금융 1팀에서 온 발신전화","link":"https://movie.v.daum.net/v/20210810083713057","retrieved":1628556611573,"image":"https://img1.daumcdn.net/thumb/S384x240/?fname=https%3A%2F%2Ft1.daumcdn.net%2Fnews%2F202108%2F10%2FSpoChosun%2F20210810083714532bjhh.jpg"},{"title":"잔혹하지만 폭소 터지는 DC 슈퍼 빌런들이 돌아왔다 (다음영화 뉴스 ─ 인기)","contents":"한결 더 화려해진 DC코믹스의 빌런들이 모였다. 할리 퀸(마고 로비), 블러드스포트(이드리스 엘바), 피스메이커(존 시나), 킹 샤크(실베스터 스탤론)…. 2016년 개봉한 데이비드 에이어 감독의 ‘수어사이드 스쿼드’를 생각한다면 오산이다. 혹평받았던 과거를 청산하려는 듯 재미와 액션이 배가 되어 돌아왔다. 4일 개봉한 ‘더 수어사이드 스쿼드’는 제임스 건","link":"https://movie.v.daum.net/v/20210809144550979","retrieved":1628556611577,"image":"https://img1.daumcdn.net/thumb/S384x240/?fname=https%3A%2F%2Ft1.daumcdn.net%2Fnews%2F202108%2F09%2Fdonga%2F20210809144553147jead.jpg"},{"title":"신예 최성은, 영화 '젠틀맨' 주인공 확정..주지훈과 호흡 (다음영화 뉴스 ─ 인기)","contents":"한소희 빈자리 채운다...열혈 여검사 김화진 役 [더팩트｜박지윤 기자] 배우 최성은이 영화 '젠틀맨' 주인공으로 낙점됐다. 온라인 동영상 서비스 웨이브(wavve)는 10일 \"웨이브 오리지널 영화 '젠틀맨'이 배우 주지훈, 박성웅이라는 막강 캐스팅에 신인 최성은이 주인공으로 확정됐다\"고 밝혔다. '젠틀맨'은 흥신소 사장 지현수(주지훈 분)가 살인 누명을","link":"https://movie.v.daum.net/v/20210810114333153","retrieved":1628598219440,"image":"https://img1.daumcdn.net/thumb/S384x240/?fname=https%3A%2F%2Ft1.daumcdn.net%2Fnews%2F202108%2F10%2FTHEFACT%2F20210810114334787zmyw.jpg"},{"title":"다큐영화 '학교 가는 길' 상영중지 소취하 (다음영화 뉴스 ─ 인기)","contents":"장애인 특수학교 개교 과정을 다룬 다큐멘터리 영화 ‘학교 가는 길’ 상영 허가 여부를 두고 벌어진 법적 다툼이 신청인 측의 소송 취하로 마무리됐다. 다만 장면 일부를 삭제해 달라는 가처분 신청 사건의 심문은 예정대로 열린다. 9일 법조계에 따르면 특수학교 설립에 반대했던 주민 A씨는 지난 4일 서울중앙지법에 가처분 신청 취하서를 제출했다. 이로 인해 이날","link":"https://movie.v.daum.net/v/20210810050639255","retrieved":1628556611578,"image":"https://img1.daumcdn.net/thumb/S384x240/?fname=https%3A%2F%2Ft1.daumcdn.net%2Fnews%2F202108%2F10%2Fseoul%2F20210810061601524htwj.jpg"},{"title":"[TEN 리뷰] '인질' 된 황정민, 진짜라 믿게되는 '200% 몰입도' (다음영화 뉴스 ─ 인기)","contents":"[텐아시아=김지원 기자]영화 '인질'은 '연기 베테랑 황정민'이라는 실제를 영화의 설정으로 그대로 가져갔다. 현실성과 허구성이 적절히 버무려져 높은 몰입도를 이끌어낸다.신작 영화 '냉혈한' 개봉을 앞두고 제작보고회를 마친 배우 황정민. 늦은 밤 뒤풀이 자리에서 먼저 나와 집으로 향한다. 평소 자주 가던 집 앞 편의점에 들렀다 나왔더니 괴한들이 자신의 차를","link":"https://movie.v.daum.net/v/20210809214203513","retrieved":1628556611584,"image":"https://img1.daumcdn.net/thumb/S384x240/?fname=https%3A%2F%2Ft1.daumcdn.net%2Fnews%2F202108%2F09%2F10asia%2F20210809214206655qyxl.jpg"},{"title":"美 버라이어티 등 '모가디슈' 호평 \"단연 올해 최고의 한국영화\"[공식] (다음영화 뉴스 ─ 인기)","contents":"[OSEN=김보라 기자]&nbsp;올해 한국영화의 부활을 알린 최고의 화제작 ‘모가디슈’가 북미 개봉하고, 제20회 뉴욕아시안영화제에서 공개한 이후 해외 언론 및 관객들의 찬사를 받고 있다. 200만 돌파를 향해 흥행 질주 중인 영화 ‘모가디슈’(감독 류승완, 제공배급 롯데엔터테인먼트, 제작 덱스터스튜디오 외유내강)가 지난 8월 6일(금) 20회 뉴욕아시안영화제 개","link":"https://movie.v.daum.net/v/20210810083625041","retrieved":1628556611574,"image":"https://img1.daumcdn.net/thumb/S384x240/?fname=https%3A%2F%2Ft1.daumcdn.net%2Fnews%2F202108%2F10%2Fpoctan%2F20210810083625978ofkm.jpg"},{"title":"더 유쾌.. 더 통쾌.. 돌아온 DC 빌런들 (다음영화 뉴스 ─ 인기)","contents":"‘더 수어사이드 스쿼드’는 교도소에 수감된 슈퍼빌런들의 활약을 다룬다. 왼쪽부터 릭 플래그 대령(조엘 킨나만), 피스메이커(존 시나), 할리 퀸(마고 로비), 씽커(피터 카팔디), 블러드스포트(이드리스 엘바) 등 총 16명으로 구성된 ‘태스크포스 X’는 청소년 관람 불가 영화답게 잔인하고도 화려한 액션을 선보인다. 워너브러더스코리아 제공한결 화려해진 DC코","link":"https://movie.v.daum.net/v/20210810030256494","retrieved":1628601713066,"image":"https://img1.daumcdn.net/thumb/S384x240/?fname=https%3A%2F%2Ft1.daumcdn.net%2Fnews%2F202108%2F10%2Fdonga%2F20210810030258780uxyy.jpg"},{"title":"변요한 김무열 '보이스' 9월 개봉 확정, 보이스피싱 리얼범죄액션 온다 (다음영화 뉴스 ─ 최신)","contents":"[뉴스엔 박수인 기자] 변요한, 김무열의 '보이스'가 오는 9월 개봉을 확정지었다. 영화 '보이스'는 보이스피싱 조직의 덫에 걸려 모든 것을 잃게 된 '서준'(변요한)이 빼앗긴 돈을 되찾기 위해 중국에 있는 본거지에 잠입, 보이스피싱 설계자 ‘곽프로’(김무열)를 만나며 벌어지는 리얼범죄액션. '보이스' 1차 포스터는 발신자와 수신자의 상반된 입장을 담았다","link":"https://v.daum.net/v/20210810221903127","retrieved":1628601712906,"image":"https://img1.daumcdn.net/thumb/S384x240/?fname=https%3A%2F%2Ft1.daumcdn.net%2Fnews%2F202108%2F10%2Fnewsen%2F20210810221905567hlif.jpg"},{"title":"'모가디슈' 김윤석, 400만 욕심→허준호 극찬 \"뮤지컬에서 조승우만큼 끝내줘\" [V라이브] (다음영화 뉴스 ─ 최신)","contents":"[TV리포트=김은정 기자] '모가디슈' 팀이 관객들에게 감사 인사를 전했다. 영화 ‘모가디슈’가 관객들의 사랑에 보답하기 위해 10일 오후 앵콜 네이버 무비토크 라이브를 개최했다. 이날 자리에는 배우 김윤석, 조인성, 구교환과 류승완 감독이 자리했다. '모가디슈'는 1991년 소말리아의 수도 모가디슈에서 내전으로 인해 고립된 사람들의 생사를 건 탈출을 그린","link":"https://v.daum.net/v/20210810214530733","retrieved":1628601712906,"image":"https://img1.daumcdn.net/thumb/S384x240/?fname=https%3A%2F%2Ft1.daumcdn.net%2Fnews%2F202108%2F10%2Ftvreport%2F20210810214532854hkls.jpg"},{"title":"드라마→ 영화까지 이어진  '방법' 유니버스 속 숨겨진 이스터에그! (방법: 재차의) (다음영화 뉴스 ─ 최신)","contents":"드라마 '방법'의 세계관을 스크린으로 확장한 영화 '방법: 재차의'가 ‘방법’ 유니버스를 관통하는 흥미진진한 이스터에그를 공개한다. [감독: 김용완 | 각본: 연상호 | 제작: 클라이맥스 스튜디오 | 공동제작: CJ ENM, 스튜디오드래곤, 키이스트 | 원작: 드라마 '방법' | 제공/배급: CJ ENM] #왠지 익숙한 파란색 일회용 라이터 미스터리를","link":"https://v.daum.net/v/20210810181832276","retrieved":1628590595048,"image":"https://img1.daumcdn.net/thumb/S384x240/?fname=https%3A%2F%2Ft1.daumcdn.net%2Fnews%2F202108%2F10%2FiMBC%2F20210810181836724txfc.jpg"},{"title":"제23회 서울국제여성영화제 개최..문가영 홍보대사 \"평소에 관심\" (다음영화 뉴스 ─ 최신)","contents":"[OSEN=최나영 기자]&nbsp;제23회 서울국제여성영화제(2021년 8월 26일~9월 1일/집행위원장 박광수)가 올해 영화제 개최 계획 및 상영작을 발표하며 영화제의 개막을 알리는 온라인 기자회견을 개최했다. 기자회견에서는 영화제 개최 방향 및 섹션 소개, 홍보대사 위촉식, '필름X젠더'&nbsp;시상식을 진행했다. 코로나19 방역수칙을 준수하며 안전하게 비공개로 진행된","link":"https://v.daum.net/v/20210810181733250","retrieved":1628590595048,"image":"https://img1.daumcdn.net/thumb/S384x240/?fname=https%3A%2F%2Ft1.daumcdn.net%2Fnews%2F202108%2F10%2Fpoctan%2F20210810181734122zqvy.png"},{"title":"'보이스' 변요한x김무열, 9월 개봉 확정..3종 포스터 공개[공식] (다음영화 뉴스 ─ 최신)","contents":"[OSEN=김보라 기자] 범죄액션 영화 '보이스' 측이 내달 개봉을 확정하고 1차 포스터 3종을 공개했다.&nbsp; '보이스'(감독 김선 김곡, 제작 수필름, 제공배급 CJ ENM)는 보이스피싱 조직의 덫에 걸려 모든 것을 잃게 된 서준(변요한 분)이 빼앗긴 돈을 되찾기 위해 중국에 있는 본거지에 잠입, 보이스피싱 설계자 곽 프로(김무열 분)를 만나며 벌어지는 리","link":"https://v.daum.net/v/20210810175959782","retrieved":1628586908555,"image":"https://img1.daumcdn.net/thumb/S384x240/?fname=https%3A%2F%2Ft1.daumcdn.net%2Fnews%2F202108%2F10%2Fpoctan%2F20210810175959607ipxx.jpg"},{"title":"김강우 \"데뷔 20주년, 절박함 생겨..멜로 도전하고파\" [인터뷰 종합] (다음영화 뉴스 ─ 최신)","contents":"(엑스포츠뉴스 이창규 기자) '귀문' 김강우가 작품과 자신의 연기관에 대한 이야기를 전했다.  10일 오전 영화 '귀문' 김강우와의 화상 인터뷰가 진행됐다.  '귀문'은&nbsp;1990년 집단 살인 사건이 발생한 이후 폐쇄된 귀사리 수련원에 무당의 피가 흐르는 심령연구소 소장과 호기심 많은 대학생들이 발을 들이며 벌어지는 극강의 공포를 그린 작품이다. 김강우는&nbsp;","link":"https://v.daum.net/v/20210810175002491","retrieved":1628586908569,"image":"https://img1.daumcdn.net/thumb/S384x240/?fname=https%3A%2F%2Ft1.daumcdn.net%2Fnews%2F202108%2F10%2Fxportsnews%2F20210810175003674afyz.jpg"},{"title":"귀신, 공포물 무서워하던 김강우 \"직접 해보니까..\" (다음영화 뉴스 ─ 최신)","contents":"[이선필 기자] ▲ &nbsp;영화 &lt;귀문&gt;에서 심령연구소 소장 도진 역을 맡은 김강우.    ⓒ 이선필  &nbsp;액션이든 로맨틱 코미디든 안정적 연기를 보이며 작품을 쌓아온 김강우는 유독 공포영화와는 거리가 멀어 보였다. 그러던 그가 데뷔 19년 만에 관객에게 정통 공포 장르 영화를 선보인다.&nbsp; 10일 온라인상에서 만난 그는 \"공포영화를 일부러 안 해왔던","link":"https://v.daum.net/v/20210810174200258","retrieved":1628586908574,"image":"https://img1.daumcdn.net/thumb/S384x240/?fname=https%3A%2F%2Ft1.daumcdn.net%2Fnews%2F202108%2F10%2Fohmynews%2F20210810174204649cqvy.jpg"},{"title":"[TEN 인터뷰] '모가디슈' 류승완 감독 \"큰돈 준다 해도 스트리밍으로 넘길 순 없었다\" (다음영화 뉴스 ─ 최신)","contents":"[텐아시아=김지원 기자]\"단 한 사람이라도 이 영화를 온전히 즐기고 싶은 관객이 있다면 이렇게 하는 게 맞지 않을까 싶어 용기 냈어요. 진심입니다.\"코로나19 팬데믹에 제작비 250억 원이 들어간 대작을 여름 텐트폴로 개봉한다는 것은 쉬운 일이 아니다. 류승완 감독은 어려운 시기에 영화 '모가디슈'를 극장 스크린에 내건 소감을 이같이 밝혔다. 그는 \"영화는","link":"https://v.daum.net/v/20210810172602754","retrieved":1628586908574,"image":"https://img1.daumcdn.net/thumb/S384x240/?fname=https%3A%2F%2Ft1.daumcdn.net%2Fnews%2F202108%2F10%2F10asia%2F20210810172603794ozpz.jpg"},{"title":"류승완 역작 '모가디슈' 지금 극장서 만날 수 있는 '명작 극장'[EN:인터뷰] (다음영화 뉴스 ─ 최신)","contents":"[뉴스엔 허민녕 기자] 좋은 영화의 공통점. N차 관람 얘기가 나온다. 자주 보다 보니 ‘뜯어보게’ 된다. 장면, 장면에 대한 궁금증, 해석이 분분해진다. 지금 이 영화 ‘모가디슈’가 그렇다. “얻어걸린 장면이 많았다.” 이 사람 매력은 이 거다. 감독 류승완. “특별한 의도를 숨겨뒀다던 지 나 그렇게 대단한 사람 아니다.” 화상 인터뷰임에도 마스크를","link":"https://v.daum.net/v/20210810171632539","retrieved":1628583604129,"image":"https://img1.daumcdn.net/thumb/S384x240/?fname=https%3A%2F%2Ft1.daumcdn.net%2Fnews%2F202108%2F10%2Fnewsen%2F20210810171632405xphm.jpg"},{"title":"최성은, 한소희 빈자리 메운다..영화 '젠틀맨' 캐스팅[공식] (다음영화 뉴스 ─ 최신)","contents":"[OSEN=김보라 기자]&nbsp;웨이브 오리지널 영화&nbsp;'젠틀맨' 측이 주지훈,&nbsp;박성웅이라는 막강 캐스팅에 신인&nbsp;최성은까지 배우 라인업을 완성했다. ‘젠틀맨’(감독 김경원)에서&nbsp;최성은은 누명을 벗으려는 지현수(주지훈 분)와 공조하며 피해자를 찾아나서는 엘리트 열혈 검사 김화진으로 분해 당찬 모습을 보여줄 예정이다. 앞서 배우 한소희가 김화진 역을 맡은 것으로 알려졌","link":"https://v.daum.net/v/20210810170627202","retrieved":1628583604129,"image":"https://img1.daumcdn.net/thumb/S384x240/?fname=https%3A%2F%2Ft1.daumcdn.net%2Fnews%2F202108%2F10%2Fpoctan%2F20210810170628306aknj.jpg"},{"title":"전종서, 베니스영화제 참석 최종 불발[공식] (다음영화 뉴스 ─ 최신)","contents":"배우 전종서가 베니스국제영화제에 초청받았지만 참석하진 못하게 됐다. 현재 촬영 중인 넷플릭스 드라마 '종이의 집' 촬영에 집중하기 위함이다. 전종서 소속사 관계자는 10일 매일경제 스타투데이에 “전종서가 베니스영화제에 초청받았지만 고심 끝에 참석은 못하게 됐다”며 “현재 '종이의 집' 촬영이 진행 중인 만큼 작품에 집중할 예정\"이라고 밝혔다. 앞서 전종서","link":"https://v.daum.net/v/20210810170300062","retrieved":1628583604129,"image":"https://img1.daumcdn.net/thumb/S384x240/?fname=https%3A%2F%2Ft1.daumcdn.net%2Fnews%2F202108%2F10%2Fstartoday%2F20210810170302620oxvq.jpg"},{"title":"류승완 감독 \"'군함도' 덕에 '모가디슈' 탄생\" #조인성 [인터뷰 종합] (다음영화 뉴스 ─ 최신)","contents":"(엑스포츠뉴스 이창규 기자) '모가디슈' 류승완 감독이 작품에 대한 다양한 이야기를 전했다.  10일 오후 영화 '모가디슈' 류승완 감독과의 화상 인터뷰가 진행됐다.  '모가디슈'는 1991년 소말리아의 수도 모가디슈에서 내전으로 인해 고립된 사람들의 생사를 건 탈출을 그린 영화다.  지난달 28일 개봉한 '모가디슈'는 9일까지 총 171만명의 누적 관객","link":"https://v.daum.net/v/20210810165003656","retrieved":1628583604129,"image":"https://img1.daumcdn.net/thumb/S384x240/?fname=https%3A%2F%2Ft1.daumcdn.net%2Fnews%2F202108%2F10%2Fxportsnews%2F20210810165004652ioma.jpg"},{"title":"'프로포폴 투약' 하정우 \"고개 숙여 사죄\"..檢, 벌금 1천만원 구형(종합) [Oh!쎈 초점] (다음영화 뉴스 ─ 최신)","contents":"[OSEN=김보라 기자]&nbsp;배우 하정우가 프로포폴 투얌 혐의에 대해 “제가 얼마나 주의깊지 못하고 경솔했는지 뼈저리게 후회하고 깊이 반성한다”고 말 했다. 프로포폴을 치료 목적 이외로 투약했다는 혐의로 기소된 하정우가 법정에서 혐의를 모두 인정했다. 검찰은 그에게 벌금 1천만원을 구형했다. 하정우는 10일 서울중앙지법 형사24단독 박설아 판사 심리로 열린 첫","link":"https://v.daum.net/v/20210810162824055","retrieved":1628583604129,"image":"https://img1.daumcdn.net/thumb/S384x240/?fname=https%3A%2F%2Ft1.daumcdn.net%2Fnews%2F202108%2F10%2Fpoctan%2F20210810162824422uccz.jpg"},{"title":"하정우, '최연소 1억 배우'의 추락 [MD포커스](종합) (다음영화 뉴스 ─ 최신)","contents":"[마이데일리 = 김나라 기자] 하정우(43·본명 김성훈)가 프로포폴 불법 투약 혐의를 인정했다. 믿고 보는 '최연소 1억 배우'로서 쌓아온 대중의 신뢰도를 스스로 추락시켰다. 10일 오전 10시 33분께 서울 서초구 서울중앙지법에선 형사24단독(박설아 판사) 심리로 마약류 관리에 관한 법률 위반(향정) 등 혐의로 기소된 하정우에 대한 첫 공판이 열렸다.","link":"https://v.daum.net/v/20210810162819052","retrieved":1628583604133,"image":"https://img1.daumcdn.net/thumb/S384x240/?fname=https%3A%2F%2Ft1.daumcdn.net%2Fnews%2F202108%2F10%2Fmydaily%2F20210810162819405ayjq.jpg"},{"title":"후회한다, 죄송하다는 하정우..대중의 마음 돌릴까 [★FOCUS] (다음영화 뉴스 ─ 최신)","contents":"[스타뉴스 김미화 기자] 프로포폴 불법 투약 혐의를 받고 있는 배우 하정우(본명 김성훈)가 10일 오전 서울중앙지법에서 열린 첫 공판을 마친뒤 법정을 나서고 있다. /2021.08.10 /사진=이동훈 기자 photoguy@수 많은 영화 속에서 활약하던 하정우가 고개를 숙였다. 프로포폴을 불법으로 투약한 혐의로 법정에 선 하정우가 자신의 혐의를 인정한 가운데","link":"https://v.daum.net/v/20210810162425923","retrieved":1628583604228,"image":"https://img1.daumcdn.net/thumb/S384x240/?fname=https%3A%2F%2Ft1.daumcdn.net%2Fnews%2F202108%2F10%2Fstarnews%2F20210810162429030tpgq.jpg"},{"title":"마이크 피기스·김윤아, 제17회 JIMF 심사위원 (다음영화 뉴스 ─ 최신)","contents":"[스포츠경향] 마이크 피기스 감독부터 그룹 자우림 김윤아까지 다채로운 얼굴들이 제17회 제천국제음악영화제 심사를 맡는다.제17회 제천국제음악영화제 측은 10일 총 11인의 심사위원들을 발표했다. 제천국제음악영화제는 부분 경쟁을 도입한 국제 영화제로서, 시상 부문은 전통의 ‘세계 음악영화의 흐름-국제경쟁’ 부문과 올해 첫 선을 보이는 ‘한국 음악영화의 오늘","link":"https://v.daum.net/v/20210810162256870","retrieved":1628583604228,"image":"https://img1.daumcdn.net/thumb/S384x240/?fname=https%3A%2F%2Ft1.daumcdn.net%2Fnews%2F202108%2F10%2Fsportskhan%2F20210810162258140ttgg.jpg"},{"title":"김윤아부터 권해효·달시 파켓, 제천국제음악영화제 심사위원 위촉 (다음영화 뉴스 ─ 최신)","contents":"(서울=뉴스1) 정유진 기자 = 제17회 제천국제음악영화제가 총 11인의 심사위원들을 10일 발표했다. 제천국제음악영화제는 부분 경쟁을 도입한 국제 영화제로서, 시상 부문은 전통의 '세계 음악영화의 흐름 – 국제경쟁' 부문과 올해 첫선을 보이는 '한국 음악영화의 오늘 – 한국경쟁' 부문, 그리고 '2021 제천 음악영화 제작지원 프로젝트'가 있다. '세","link":"https://v.daum.net/v/20210810161317566","retrieved":1628579631459,"image":"https://img1.daumcdn.net/thumb/S384x240/?fname=https%3A%2F%2Ft1.daumcdn.net%2Fnews%2F202108%2F10%2FNEWS1%2F20210810161318425avsc.jpg"},{"title":"정글 크루즈 | 익숙하고 편안한 '디즈니'표 모험 영화 (다음영화 뉴스 ─ 최신)","contents":"디즈니는 오래전부터 하나의 가치를 추구해왔다. 바로 ‘정치적 올바름(PC· Political Correctness)’이다. 백인 여성을 공주로 등장시켜 인종에 대한 편견을 확대 재생산한다는 비판을 받았던 과거의 디즈니는 사라진 지 오래다. 1990년대 이후부터 디즈니는 인종과 여성의 역할 등에 대해 지대한 관심을 쏟았다. 무려 30년 동안 일관되게 이어지","link":"https://v.daum.net/v/20210810161206520","retrieved":1628583604228,"image":"https://img1.daumcdn.net/thumb/S384x240/?fname=https%3A%2F%2Ft1.daumcdn.net%2Fnews%2F202108%2F10%2Fmkeconomy%2F20210810161208020bamv.jpg"},{"title":"'젠틀맨' 한소희 하차→최성은 합류 [공식] (다음영화 뉴스 ─ 최신)","contents":"배우 최성은이 건강상의 이유로 하차한 한소희 역할을 맡았다. 신예 최성은이 영화 '젠틀맨' 주인공 출연을 확정했다. 2022년 개봉 예정인 웨이브 오리지널 영화 '젠틀맨'은 흥신소 사장 지현수(주지훈)가 살인 누명을 벗으려다 거대한 사건에 휘말리는 경쾌한 범죄 오락물이다. 최성은은 극중 누명을 벗으려는 지현수와 공조하며 피해자를 찾아 나서는 엘리트 열혈","link":"https://v.daum.net/v/20210810160330198","retrieved":1628579631459,"image":"https://img1.daumcdn.net/thumb/S384x240/?fname=https%3A%2F%2Ft1.daumcdn.net%2Fnews%2F202108%2F10%2FiMBC%2F20210810160333774naug.jpg"},{"title":"'모가디슈' 류승완 \"해외 로케이션, 이젠 어디서든 가능하다\" [인터뷰M] (다음영화 뉴스 ─ 최신)","contents":"영화 '모가디슈'로 코로나 상황임에도 200만 관객을 목전에 두고 있는 류승완 감독을 만났다. 코로나 19 확산 방지를 위해 화상으로 진행된 인터뷰에서 류승완 감독은 그 어떤 다른 인사보다 \"'모가디슈'를 성원해 주셔서 대단히 감사하다\"는 감사의 인사를 먼저 하였다. 영화 '군함도' 이후 차기작으로 '모가디슈'를 내 놓은 류승완 감독은 \"수년 전에 이 소","link":"https://v.daum.net/v/20210810160231139","retrieved":1628579631459,"image":"https://img1.daumcdn.net/thumb/S384x240/?fname=https%3A%2F%2Ft1.daumcdn.net%2Fnews%2F202108%2F10%2FiMBC%2F20210810160232575rwhk.jpg"},{"title":"<귀문> ScreenX vs 4DX 공포 배틀 영상 (우리 영화 볼래?)","contents":"<em class=\"screen_out\">재생시간 : </em>04:34","link":"https://tv.kakao.com/channel/462787/cliplink/421405423?act=clip","retrieved":1628586910476,"image":"https://t1.daumcdn.net/thumb/C320x180.fjpg.q75/?fname=https%3A%2F%2Fthumb.kakaocdn.net%2Fdna%2Fkamp%2Fsource%2Frvwyx0893999xyyqzql09z540%2Fthumbs%2Fthumb.jpg%3Fcredential%3DTuMuFGKUIcirOSjFzOpncbomGFEIdZWK%26expires%3D33185493439%26signature%3D7w%252FTgRXKZ3rnuIhJGOMNTE89%252BSw%253D%26ts%3D1628584639"},{"title":"<올드> #올드 감독 코멘터리 영상 (우리 영화 볼래?)","contents":"<em class=\"screen_out\">재생시간 : </em>01:39","link":"https://tv.kakao.com/channel/462787/cliplink/421405071?act=clip","retrieved":1628586910477,"image":"https://t1.daumcdn.net/thumb/C320x180.fjpg.q75/?fname=https%3A%2F%2Fthumb.kakaocdn.net%2Fdna%2Fkamp%2Fsource%2Frv83yd4leocd3xpjugs3ogopo%2Fthumbs%2Fthumb.jpg%3Fcredential%3DTuMuFGKUIcirOSjFzOpncbomGFEIdZWK%26expires%3D33185492681%26signature%3DNGrluyaMOGdAQo%252Fh1UEt9mJWTSg%253D%26ts%3D1628583881"},{"title":"<신마영정: 야인시대> 메인 예고편 (우리 영화 볼래?)","contents":"<em class=\"screen_out\">재생시간 : </em>00:59","link":"https://tv.kakao.com/channel/462787/cliplink/421404937?act=clip","retrieved":1628586910479,"image":"https://t1.daumcdn.net/thumb/C320x180.fjpg.q75/?fname=http%3A%2F%2Fthumb.kakaocdn.net%2Fdna%2Fkamp%2Fsource%2Frvgdjnv4nha10k25ul10kq04l%2Fthumbs%2Fthumb.jpg%3Fcredential%3DTuMuFGKUIcirOSjFzOpncbomGFEIdZWK%26expires%3D33185492372%26signature%3DvUDKRF5D4P9S4uAlvVnikKFP31I%253D"},{"title":"<건파우더 밀크셰이크> 30초 예고편 (우리 영화 볼래?)","contents":"<em class=\"screen_out\">재생시간 : </em>00:30","link":"https://tv.kakao.com/channel/462787/cliplink/421402717?act=clip","retrieved":1628579632218,"image":"https://t1.daumcdn.net/thumb/C320x180.fjpg.q75/?fname=http%3A%2F%2Fimg1.daumcdn.net%2Fkakaotv%2FKAKAOACCOUNT%2F1529133806%2Fthumb%2F20210810155654"},{"title":"<마이 네버 리스트> 메인 예고편 (우리 영화 볼래?)","contents":"<em class=\"screen_out\">재생시간 : </em>00:56","link":"https://tv.kakao.com/channel/462787/cliplink/421400028?act=clip","retrieved":1628576327471,"image":"https://t1.daumcdn.net/thumb/C320x180.fjpg.q75/?fname=https%3A%2F%2Fthumb.kakaocdn.net%2Fdna%2Fkamp%2Fsource%2Frvr29xk1r69a93her7acn1vhi%2Fthumbs%2Fthumb.jpg%3Fcredential%3DTuMuFGKUIcirOSjFzOpncbomGFEIdZWK%26expires%3D33185481266%26signature%3DVS5y8erN3AHP12CMiXOsUNuRNUE%253D%26ts%3D1628572466"},{"title":"<슈퍼딥> 예고편 (우리 영화 볼래?)","contents":"<em class=\"screen_out\">재생시간 : </em>01:13","link":"https://tv.kakao.com/channel/462787/cliplink/421399541?act=clip","retrieved":1628572383050,"image":"https://t1.daumcdn.net/thumb/C320x180.fjpg.q75/?fname=https%3A%2F%2Fthumb.kakaocdn.net%2Fdna%2Fkamp%2Fsource%2Frvaostu5euspb8ulrwvuy6g8q%2Fthumbs%2Fthumb.jpg%3Fcredential%3DTuMuFGKUIcirOSjFzOpncbomGFEIdZWK%26expires%3D33185479931%26signature%3Dd6u6fTj0RRO6bMjdj0tyVoc%252Bj7w%253D%26ts%3D1628571131"},{"title":"<리버풀 FC: 엔드 오브 스톰> 예고편 (우리 영화 볼래?)","contents":"<em class=\"screen_out\">재생시간 : </em>01:00","link":"https://tv.kakao.com/channel/462787/cliplink/421399161?act=clip","retrieved":1628571144647,"image":"https://t1.daumcdn.net/thumb/C320x180.fjpg.q75/?fname=http%3A%2F%2Fthumb.kakaocdn.net%2Fdna%2Fkamp%2Fsource%2Frv5yhz0t0ova010gzsluufida%2Fthumbs%2Fthumb.jpg%3Fcredential%3DTuMuFGKUIcirOSjFzOpncbomGFEIdZWK%26expires%3D33185478890%26signature%3Dsf8KQFQZTpsK7bHiHf9fCGAwYp0%253D"},{"title":"<박강아름 결혼하다> 뮤직비디오 (우리 영화 볼래?)","contents":"<em class=\"screen_out\">재생시간 : </em>03:05","link":"https://tv.kakao.com/channel/462787/cliplink/421396220?act=clip","retrieved":1628568380002,"image":"https://t1.daumcdn.net/thumb/C320x180.fjpg.q75/?fname=http%3A%2F%2Fimg1.daumcdn.net%2Fkakaotv%2FKAKAOACCOUNT%2F2127401120%2Fthumb%2F20210810110444"},{"title":"<코다> 파이널 예고편 (우리 영화 볼래?)","contents":"<em class=\"screen_out\">재생시간 : </em>01:58","link":"https://tv.kakao.com/channel/462787/cliplink/421396072?act=clip","retrieved":1628568380007,"image":"https://t1.daumcdn.net/thumb/C320x180.fjpg.q75/?fname=https%3A%2F%2Fthumb.kakaocdn.net%2Fdna%2Fkamp%2Fsource%2Frvt2cr58fp9om7b0tqgo564ne%2Fthumbs%2Fthumb.jpg%3Fcredential%3DTuMuFGKUIcirOSjFzOpncbomGFEIdZWK%26expires%3D33185469561%26signature%3DcdqqzVUNFwKOqAI964W76GnijyI%253D%26ts%3D1628560761"},{"title":"<코다> 메인 예고편 (우리 영화 볼래?)","contents":"<em class=\"screen_out\">재생시간 : </em>02:07","link":"https://tv.kakao.com/channel/462787/cliplink/421395899?act=clip","retrieved":1628568380009,"image":"https://t1.daumcdn.net/thumb/C320x180.fjpg.q75/?fname=https%3A%2F%2Fthumb.kakaocdn.net%2Fdna%2Fkamp%2Fsource%2Frvaug1jnnbue5v5zmy63axth6%2Fthumbs%2Fthumb.jpg%3Fcredential%3DTuMuFGKUIcirOSjFzOpncbomGFEIdZWK%26expires%3D33185469079%26signature%3D1ov4wjckEdDXUufu2zAWsi3W2yc%253D%26ts%3D1628560279"},{"title":"<원티드 킬러> 메인 예고편 (우리 영화 볼래?)","contents":"<em class=\"screen_out\">재생시간 : </em>01:41","link":"https://tv.kakao.com/channel/462787/cliplink/421394959?act=clip","retrieved":1628568380011,"image":"https://t1.daumcdn.net/thumb/C320x180.fjpg.q75/?fname=https%3A%2F%2Fthumb.kakaocdn.net%2Fdna%2Fkamp%2Fsource%2Frv5qcpnhaoeq48c4eqjf6hdgi%2Fthumbs%2Fthumb.jpg%3Fcredential%3DTuMuFGKUIcirOSjFzOpncbomGFEIdZWK%26expires%3D33185466651%26signature%3D%252FYbRRwYvcapI%252B1emRIFj84fw7Xw%253D%26ts%3D1628557851"},{"title":"<사보타지 1941> 메인 예고편 (우리 영화 볼래?)","contents":"<em class=\"screen_out\">재생시간 : </em>01:17","link":"https://tv.kakao.com/channel/462787/cliplink/421378193?act=clip","retrieved":1628568380018,"image":"https://t1.daumcdn.net/thumb/C320x180.fjpg.q75/?fname=http%3A%2F%2Fthumb.kakaocdn.net%2Fdna%2Fkamp%2Fsource%2Frvudiwnjebbk1uubk7247xls9%2Fthumbs%2Fthumb.jpg%3Fcredential%3DTuMuFGKUIcirOSjFzOpncbomGFEIdZWK%26expires%3D33185405718%26signature%3Dl6aRKyJu37XtqJ7VRuydLO2Fw%252Fw%253D"},{"title":"<숏버스 감성행> 감성행 김시선투어 예고편 30초버전 (우리 영화 볼래?)","contents":"<em class=\"screen_out\">재생시간 : </em>00:30","link":"https://tv.kakao.com/channel/462787/cliplink/421375872?act=clip","retrieved":1628568380020,"image":"https://t1.daumcdn.net/thumb/C320x180.fjpg.q75/?fname=http%3A%2F%2Fthumb.kakaocdn.net%2Fdna%2Fkamp%2Fsource%2Frvvdthrnpqtexm8ecj5702lb0%2Fthumbs%2Fthumb.jpg%3Fcredential%3DTuMuFGKUIcirOSjFzOpncbomGFEIdZWK%26expires%3D33185400310%26signature%3D50iFRW66xjL7OFpuMPTAxvqxi%252FA%253D"},{"title":"<숏버스 감성행> 감성행 김시선투어 예고편 (우리 영화 볼래?)","contents":"<em class=\"screen_out\">재생시간 : </em>01:00","link":"https://tv.kakao.com/channel/462787/cliplink/421375800?act=clip","retrieved":1628568380021,"image":"https://t1.daumcdn.net/thumb/C320x180.fjpg.q75/?fname=https%3A%2F%2Fthumb.kakaocdn.net%2Fdna%2Fkamp%2Fsource%2Frvylxhtlvgn9es7keybmo3nj3%2Fthumbs%2Fthumb.jpg%3Fcredential%3DTuMuFGKUIcirOSjFzOpncbomGFEIdZWK%26expires%3D33185400169%26signature%3DjQO6gWgg%252BqUsGZKbnTQnWfBjHWU%253D%26ts%3D1628491369"},{"title":"<숏버스 감성행>  감성행 메인 예고편 30초버전 (우리 영화 볼래?)","contents":"<em class=\"screen_out\">재생시간 : </em>00:30","link":"https://tv.kakao.com/channel/462787/cliplink/421375705?act=clip","retrieved":1628568380024,"image":"https://t1.daumcdn.net/thumb/C320x180.fjpg.q75/?fname=https%3A%2F%2Fthumb.kakaocdn.net%2Fdna%2Fkamp%2Fsource%2Frvmhg8dasftdqp690vhvesaqi%2Fthumbs%2Fthumb.jpg%3Fcredential%3DTuMuFGKUIcirOSjFzOpncbomGFEIdZWK%26expires%3D33185399960%26signature%3D1bxcbDe3J7Y2ko8fN58E5z4t2to%253D%26ts%3D1628491160"},{"title":"<숏버스 감성행> 감성행 메인 예고편 (우리 영화 볼래?)","contents":"<em class=\"screen_out\">재생시간 : </em>01:35","link":"https://tv.kakao.com/channel/462787/cliplink/421375632?act=clip","retrieved":1628568380025,"image":"https://t1.daumcdn.net/thumb/C320x180.fjpg.q75/?fname=https%3A%2F%2Fthumb.kakaocdn.net%2Fdna%2Fkamp%2Fsource%2Frvfwhgc92e8gftk267iadug4n%2Fthumbs%2Fthumb.jpg%3Fcredential%3DTuMuFGKUIcirOSjFzOpncbomGFEIdZWK%26expires%3D33185399738%26signature%3DsVCL26bUIU3lf0C4ao11enyvQ6Q%253D%26ts%3D1628490938"},{"title":"<윙즈 오버 에베레스트> 메인 예고편 (우리 영화 볼래?)","contents":"<em class=\"screen_out\">재생시간 : </em>01:13","link":"https://tv.kakao.com/channel/462787/cliplink/421373196?act=clip","retrieved":1628568380026,"image":"https://t1.daumcdn.net/thumb/C320x180.fjpg.q75/?fname=http%3A%2F%2Fthumb.kakaocdn.net%2Fdna%2Fkamp%2Fsource%2Frvyipfehk9igsebzg12za0guq%2Fthumbs%2Fthumb.jpg%3Fcredential%3DTuMuFGKUIcirOSjFzOpncbomGFEIdZWK%26expires%3D33185393431%26signature%3D8H0S%252FSNNPPuJZL1MNC25OPW7P50%253D"},{"title":"<남색대문> 계륜미의 여름 시(時) 예고편 (우리 영화 볼래?)","contents":"<em class=\"screen_out\">재생시간 : </em>00:30","link":"https://tv.kakao.com/channel/462787/cliplink/421373107?act=clip","retrieved":1628568380027,"image":"https://t1.daumcdn.net/thumb/C320x180.fjpg.q75/?fname=http%3A%2F%2Fthumb.kakaocdn.net%2Fdna%2Fkamp%2Fsource%2Frvk1l2gjdte3as9tozqhkbzo3%2Fthumbs%2Fthumb.jpg%3Fcredential%3DTuMuFGKUIcirOSjFzOpncbomGFEIdZWK%26expires%3D33185393183%26signature%3DQbc2F3UQ%252Fnn1n0qyhbpW9nrD7U0%253D"},{"title":"<남색대문> 메인 예고편 (우리 영화 볼래?)","contents":"<em class=\"screen_out\">재생시간 : </em>01:03","link":"https://tv.kakao.com/channel/462787/cliplink/421373023?act=clip","retrieved":1628568380029,"image":"https://t1.daumcdn.net/thumb/C320x180.fjpg.q75/?fname=https%3A%2F%2Fthumb.kakaocdn.net%2Fdna%2Fkamp%2Fsource%2Frv45fayw9qpz06irjx2f0a4qy%2Fthumbs%2Fthumb.jpg%3Fcredential%3DTuMuFGKUIcirOSjFzOpncbomGFEIdZWK%26expires%3D33185393004%26signature%3D%252FGkvxOV4WfLWNPnZQhqx6M8qLBw%253D%26ts%3D1628484204"},{"title":"<신적인걸: 통천교주> 메인 예고편 (우리 영화 볼래?)","contents":"<em class=\"screen_out\">재생시간 : </em>01:04","link":"https://tv.kakao.com/channel/462787/cliplink/421372380?act=clip","retrieved":1628568380044,"image":"https://t1.daumcdn.net/thumb/C320x180.fjpg.q75/?fname=http%3A%2F%2Fthumb.kakaocdn.net%2Fdna%2Fkamp%2Fsource%2Frv3wit90y2sudh4hl62im9k8l%2Fthumbs%2Fthumb.jpg%3Fcredential%3DTuMuFGKUIcirOSjFzOpncbomGFEIdZWK%26expires%3D33185391304%26signature%3DHrX40HHwb7MPH7sek61qjC3XKq0%253D"},{"title":"<브레이브 하트2> 메인 예고편 (우리 영화 볼래?)","contents":"<em class=\"screen_out\">재생시간 : </em>01:58","link":"https://tv.kakao.com/channel/462787/cliplink/421371436?act=clip","retrieved":1628568380045,"image":"https://t1.daumcdn.net/thumb/C240x140.fjpg.q75/?fname=https%3A%2F%2Fthumb.kakaocdn.net%2Fdna%2Fkamp%2Fsource%2Frvjgz95h88prynus2ltoh3b8c%2Fthumbs%2Fthumb.jpg%3Fcredential%3DTuMuFGKUIcirOSjFzOpncbomGFEIdZWK%26expires%3D33185388740%26signature%3DGL3eAWEBgHnIPz7TAcVdvEwykl0%253D%26ts%3D1628479940"},{"title":"<다이노 월드: 배틀어택> 예고편 (우리 영화 볼래?)","contents":"<em class=\"screen_out\">재생시간 : </em>01:09","link":"https://tv.kakao.com/channel/462787/cliplink/421370035?act=clip","retrieved":1628568380049,"image":"https://t1.daumcdn.net/thumb/C240x140.fjpg.q75/?fname=https%3A%2F%2Fthumb.kakaocdn.net%2Fdna%2Fkamp%2Fsource%2Frvqsddkmozx5nzuyaspojbn1g%2Fthumbs%2Fthumb.jpg%3Fcredential%3DTuMuFGKUIcirOSjFzOpncbomGFEIdZWK%26expires%3D33185384674%26signature%3DQGFQAd0puYUbVRgsfJdIgMDqITQ%253D%26ts%3D1628475874"},{"title":"<귀문> 제작기 영상 (우리 영화 볼래?)","contents":"<em class=\"screen_out\">재생시간 : </em>04:11","link":"https://tv.kakao.com/channel/462787/cliplink/421369808?act=clip","retrieved":1628568380049,"image":"https://t1.daumcdn.net/thumb/C240x140.fjpg.q75/?fname=https%3A%2F%2Fthumb.kakaocdn.net%2Fdna%2Fkamp%2Fsource%2Frvfeim6dg7da8fmpngw3yf6l7%2Fthumbs%2Fthumb.jpg%3Fcredential%3DTuMuFGKUIcirOSjFzOpncbomGFEIdZWK%26expires%3D33185384174%26signature%3DsY5IudXivj0vIVkv%252FX3hjAyM650%253D%26ts%3D1628475374"},{"title":"<바쿠라우> 티저 예고편 (우리 영화 볼래?)","contents":"<em class=\"screen_out\">재생시간 : </em>00:59","link":"https://tv.kakao.com/channel/462787/cliplink/421369559?act=clip","retrieved":1628568380050,"image":"https://t1.daumcdn.net/thumb/C240x140.fjpg.q75/?fname=http%3A%2F%2Fthumb.kakaocdn.net%2Fdna%2Fkamp%2Fsource%2Frv41wk1bzcsnh878llv5sucqq%2Fthumbs%2Fthumb.jpg%3Fcredential%3DTuMuFGKUIcirOSjFzOpncbomGFEIdZWK%26expires%3D33185383465%26signature%3DHi4BdJyYOC5BVlRiaeH2RC%252FyCp8%253D"},{"title":"<박강아름 결혼하다> 30초 예고편 (우리 영화 볼래?)","contents":"<em class=\"screen_out\">재생시간 : </em>00:30","link":"https://tv.kakao.com/channel/462787/cliplink/421369443?act=clip","retrieved":1628568380052,"image":"https://t1.daumcdn.net/thumb/C240x140.fjpg.q75/?fname=https%3A%2F%2Fthumb.kakaocdn.net%2Fdna%2Fkamp%2Fsource%2Frvxb4whlp93cbxam6perpgxm3%2Fthumbs%2Fthumb.jpg%3Fcredential%3DTuMuFGKUIcirOSjFzOpncbomGFEIdZWK%26expires%3D33185383259%26signature%3DKhtKm%252BZrDR9HvR%252BnNRje8arjO%252B4%253D%26ts%3D1628474459"},{"title":"<레미니센스> 액션 추적 영상 (우리 영화 볼래?)","contents":"<em class=\"screen_out\">재생시간 : </em>00:30","link":"https://tv.kakao.com/channel/462787/cliplink/421369387?act=clip","retrieved":1628568380056,"image":"https://t1.daumcdn.net/thumb/C240x140.fjpg.q75/?fname=https%3A%2F%2Fthumb.kakaocdn.net%2Fdna%2Fkamp%2Fsource%2Frvrymibz38qorh81rs652judg%2Fthumbs%2Fthumb.jpg%3Fcredential%3DTuMuFGKUIcirOSjFzOpncbomGFEIdZWK%26expires%3D33185383093%26signature%3DWoiEyuZw9uwUHn5IVz8IsD97IwE%253D%26ts%3D1628474293"},{"title":"<여름날 우리> 메인 예고편 (우리 영화 볼래?)","contents":"<em class=\"screen_out\">재생시간 : </em>01:34","link":"https://tv.kakao.com/channel/462787/cliplink/421369307?act=clip","retrieved":1628568380057,"image":"https://t1.daumcdn.net/thumb/C240x140.fjpg.q75/?fname=https%3A%2F%2Fthumb.kakaocdn.net%2Fdna%2Fkamp%2Fsource%2Frvwv6s2opzusxpzas36f7pu07%2Fthumbs%2Fthumb.jpg%3Fcredential%3DTuMuFGKUIcirOSjFzOpncbomGFEIdZWK%26expires%3D33185382832%26signature%3D%252Ft0pSv6U4VBgQ4FLMoyN81gkJMs%253D%26ts%3D1628474032"},{"title":"<아담> 메인 예고편 (우리 영화 볼래?)","contents":"<em class=\"screen_out\">재생시간 : </em>02:01","link":"https://tv.kakao.com/channel/462787/cliplink/421369133?act=clip","retrieved":1628569964745,"image":"https://t1.daumcdn.net/thumb/C240x140.fjpg.q75/?fname=https%3A%2F%2Fthumb.kakaocdn.net%2Fdna%2Fkamp%2Fsource%2Frv33cl9r9tsadtyvgg4tkrhss%2Fthumbs%2Fthumb.jpg%3Fcredential%3DTuMuFGKUIcirOSjFzOpncbomGFEIdZWK%26expires%3D33185382230%26signature%3DWtsxjgApxi9Z22tZJ5MGYp8yMM8%253D%26ts%3D1628473430"},{"title":"<귀신> 티저 예고편 (우리 영화 볼래?)","contents":"<em class=\"screen_out\">재생시간 : </em>01:10","link":"https://tv.kakao.com/channel/462787/cliplink/421369041?act=clip","retrieved":1628569964746,"image":"https://t1.daumcdn.net/thumb/C240x140.fjpg.q75/?fname=https%3A%2F%2Fthumb.kakaocdn.net%2Fdna%2Fkamp%2Fsource%2Frvhlf64xo64la8x497g9wslkx%2Fthumbs%2Fthumb.jpg%3Fcredential%3DTuMuFGKUIcirOSjFzOpncbomGFEIdZWK%26expires%3D33185381981%26signature%3DXdkiozNNE%252FbeONMpycWmgPGjhvc%253D%26ts%3D1628473181"},{"title":"<더 테러 라이브: 스쿨 어택> 메인 예고편 (우리 영화 볼래?)","contents":"<em class=\"screen_out\">재생시간 : </em>02:32","link":"https://tv.kakao.com/channel/462787/cliplink/421312602?act=clip","retrieved":1628569964747,"image":"https://t1.daumcdn.net/thumb/C240x140.fjpg.q75/?fname=https%3A%2F%2Fthumb.kakaocdn.net%2Fdna%2Fkamp%2Fsource%2Frvd2wo1lq79j9cqc86rauwddh%2Fthumbs%2Fthumb.jpg%3Fcredential%3DTuMuFGKUIcirOSjFzOpncbomGFEIdZWK%26expires%3D33185148359%26signature%3DJGY%252BD74b0YGnGypNjygAKE2PeCk%253D%26ts%3D1628239559"},{"title":"<습도 다소 높음> 1차 예고편 (우리 영화 볼래?)","contents":"<em class=\"screen_out\">재생시간 : </em>00:47","link":"https://tv.kakao.com/channel/462787/cliplink/421311590?act=clip","retrieved":1628569964748,"image":"https://t1.daumcdn.net/thumb/C240x140.fjpg.q75/?fname=https%3A%2F%2Fthumb.kakaocdn.net%2Fdna%2Fkamp%2Fsource%2Frvwp7h2sb85pjy499imzf6jft%2Fthumbs%2Fthumb.jpg%3Fcredential%3DTuMuFGKUIcirOSjFzOpncbomGFEIdZWK%26expires%3D33185146054%26signature%3DHt8wwp0LXahmsut%252FrUZMQVN%252F2aA%253D%26ts%3D1628237254"},{"title":"<더 그레이트 샤크> 생명 단축 리뷰 영상 (우리 영화 볼래?)","contents":"<em class=\"screen_out\">재생시간 : </em>00:43","link":"https://tv.kakao.com/channel/462787/cliplink/421308842?act=clip","retrieved":1628569964750,"image":"https://t1.daumcdn.net/thumb/C240x140.fjpg.q75/?fname=https%3A%2F%2Fthumb.kakaocdn.net%2Fdna%2Fkamp%2Fsource%2Frvfu9q1carvrasv4alkp3gh6w%2Fthumbs%2Fthumb.jpg%3Fcredential%3DTuMuFGKUIcirOSjFzOpncbomGFEIdZWK%26expires%3D33185139055%26signature%3Db08DGQO3s%252FBWPaF7wDCG%252BW5Iy7M%253D%26ts%3D1628230255"},{"title":"<이도공간> [재개봉] 뮤직비디오 (우리 영화 볼래?)","contents":"<em class=\"screen_out\">재생시간 : </em>03:39","link":"https://tv.kakao.com/channel/462787/cliplink/421308650?act=clip","retrieved":1628569964751,"image":"https://t1.daumcdn.net/thumb/C240x140.fjpg.q75/?fname=https%3A%2F%2Fthumb.kakaocdn.net%2Fdna%2Fkamp%2Fsource%2Frv85exjid7amzqb78cf7mu29t%2Fthumbs%2Fthumb.jpg%3Fcredential%3DTuMuFGKUIcirOSjFzOpncbomGFEIdZWK%26expires%3D33185138609%26signature%3Duq4JL%252F1tLUAfJBWZ62BrGFeUGJU%253D%26ts%3D1628229809"},{"title":"<아담> 30초 예고편 (우리 영화 볼래?)","contents":"<em class=\"screen_out\">재생시간 : </em>00:30","link":"https://tv.kakao.com/channel/462787/cliplink/421307712?act=clip","retrieved":1628569964752,"image":"https://t1.daumcdn.net/thumb/C240x140.fjpg.q75/?fname=http%3A%2F%2Fimg1.daumcdn.net%2Fkakaotv%2FKAKAOACCOUNT%2F2077678470%2Fthumb%2F20210806142129"},{"title":"<로빈의 소원> 감동의 파이널 예고편 (우리 영화 볼래?)","contents":"<em class=\"screen_out\">재생시간 : </em>01:02","link":"https://tv.kakao.com/channel/462787/cliplink/421303767?act=clip","retrieved":1628569964755,"image":"https://t1.daumcdn.net/thumb/C240x140.fjpg.q75/?fname=http%3A%2F%2Fimg1.daumcdn.net%2Fkakaotv%2FKAKAOACCOUNT%2F1273251854%2Fthumb%2F20210806111343"},{"title":"<로빈의 소원> 영원한 로빈 예고편 (우리 영화 볼래?)","contents":"<em class=\"screen_out\">재생시간 : </em>01:00","link":"https://tv.kakao.com/channel/462787/cliplink/421303716?act=clip","retrieved":1628569964756,"image":"https://t1.daumcdn.net/thumb/C240x140.fjpg.q75/?fname=http%3A%2F%2Fimg1.daumcdn.net%2Fkakaotv%2FKAKAOACCOUNT%2F1839910646%2Fthumb%2F20210806111115"},{"title":"<남편이 필요해?> 메인 예고편 (우리 영화 볼래?)","contents":"<em class=\"screen_out\">재생시간 : </em>00:40","link":"https://tv.kakao.com/channel/462787/cliplink/421303612?act=clip","retrieved":1628569964757,"image":"https://t1.daumcdn.net/thumb/C240x140.fjpg.q75/?fname=https%3A%2F%2Fthumb.kakaocdn.net%2Fdna%2Fkamp%2Fsource%2Frv3sxm2wtwnqhscmwx64g03ng%2Fthumbs%2Fthumb.jpg%3Fcredential%3DTuMuFGKUIcirOSjFzOpncbomGFEIdZWK%26expires%3D33185124464%26signature%3Dc1wrB943TP3qCC7mmlhAzsbQwTo%253D%26ts%3D1628215664"},{"title":"<남편이 필요해?> 2차 티저 예고편 (우리 영화 볼래?)","contents":"<em class=\"screen_out\">재생시간 : </em>00:41","link":"https://tv.kakao.com/channel/462787/cliplink/421303538?act=clip","retrieved":1628569964758,"image":"https://t1.daumcdn.net/thumb/C240x140.fjpg.q75/?fname=https%3A%2F%2Fthumb.kakaocdn.net%2Fdna%2Fkamp%2Fsource%2Frvz0w5spahryw9vmjicziapbq%2Fthumbs%2Fthumb.jpg%3Fcredential%3DTuMuFGKUIcirOSjFzOpncbomGFEIdZWK%26expires%3D33185124291%26signature%3DIMSEH55ea1j0iotJkgbAAMcHPvo%253D%26ts%3D1628215491"},{"title":"<남편이 필요해?> 1차 티저 예고편 (우리 영화 볼래?)","contents":"<em class=\"screen_out\">재생시간 : </em>00:14","link":"https://tv.kakao.com/channel/462787/cliplink/421303484?act=clip","retrieved":1628569964761,"image":"https://t1.daumcdn.net/thumb/C240x140.fjpg.q75/?fname=https%3A%2F%2Fthumb.kakaocdn.net%2Fdna%2Fkamp%2Fsource%2Frvlqp9oqofca3c5o7as9qo8ku%2Fthumbs%2Fthumb.jpg%3Fcredential%3DTuMuFGKUIcirOSjFzOpncbomGFEIdZWK%26expires%3D33185124200%26signature%3DlRL7JS2WaAcYWGbAVdxOB1jaOgo%253D%26ts%3D1628215400"},{"title":"<올드> 극찬 리뷰 영상 (우리 영화 볼래?)","contents":"<em class=\"screen_out\">재생시간 : </em>00:15","link":"https://tv.kakao.com/channel/462787/cliplink/421303030?act=clip","retrieved":1628569964762,"image":"https://t1.daumcdn.net/thumb/C240x140.fjpg.q75/?fname=https%3A%2F%2Fthumb.kakaocdn.net%2Fdna%2Fkamp%2Fsource%2Frvbmpl63da4zlet48qecmcuwh%2Fthumbs%2Fthumb.jpg%3Fcredential%3DTuMuFGKUIcirOSjFzOpncbomGFEIdZWK%26expires%3D33185122911%26signature%3DZMZtaQkrFHF7jkUspZRRhus7y94%253D%26ts%3D1628214111"},{"title":"'다이노 월드: 배틀어택' 예고편 (네이버 영화 예고편 저장소)","contents":"3시간 전","link":"https://tv.naver.com/v/21790713","retrieved":1628590591704,"image":"https://phinf.pstatic.net/tvcast/20210810_177/Vkrny_1628587371252tki0P_JPEG/41b7463a-f9bc-11eb-86ec-48df37ae3fca_08.jpg?type=f194_109_blend"},{"title":"'여배우의 스와핑' 예고편 (네이버 영화 예고편 저장소)","contents":"4시간 전","link":"https://tv.naver.com/v/21790604","retrieved":1628590591708,"image":"https://phinf.pstatic.net/tvcast/20210810_160/8rbx6_1628587016105UsWX9_JPEG/643e0a11-f9bb-11eb-82ff-505dac8c385b_01.jpg?type=f194_109_blend"},{"title":"'새아빠와 모녀' 예고편 (네이버 영화 예고편 저장소)","contents":"4시간 전","link":"https://tv.naver.com/v/21790484","retrieved":1628586904622,"image":"https://phinf.pstatic.net/tvcast/20210810_228/y9v8I_1628586639617FtEnH_JPEG/88976b79-f9ba-11eb-a9f1-505dac8c3639_03.jpg?type=f194_109_blend"},{"title":"'올드' #올드 감독 코멘터리 영상 (네이버 영화 예고편 저장소)","contents":"4시간 전","link":"https://tv.naver.com/v/21790338","retrieved":1628586904629,"image":"https://phinf.pstatic.net/tvcast/20210810_171/2uIXF_1628586245014SRg37_JPEG/91ac0dbf-f9b9-11eb-8e61-a0369ff94f34_08.jpg?type=f194_109_blend"},{"title":"'건파우더 밀크셰이크' 30초 예고편 (네이버 영화 예고편 저장소)","contents":"5시간 전","link":"https://tv.naver.com/v/21788132","retrieved":1628583601692,"image":"https://phinf.pstatic.net/tvcast/20210810_102/KnZ25_1628581372820fH3IF_JPEG/4d9bbdf5-f9ae-11eb-b778-a0369ff963bc_07.jpg?type=f194_109_blend"},{"title":"'슈퍼딥' 예고편 (네이버 영화 예고편 저장소)","contents":"6시간 전","link":"https://tv.naver.com/v/21786208","retrieved":1628579627977,"image":"https://phinf.pstatic.net/tvcast/20210810_266/wqSqm_1628577742725XjOGD_JPEG/9c43c850-f9a5-11eb-8111-505dac8c381b_03.jpg?type=f194_109_blend"},{"title":"'리버풀 FC: 엔드 오브 스톰' 예고편 (네이버 영화 예고편 저장소)","contents":"7시간 전","link":"https://tv.naver.com/v/21784107","retrieved":1628576324905,"image":"https://phinf.pstatic.net/tvcast/20210810_227/oCtHU_1628573354922s3P4i_JPEG/8dc7076e-f99b-11eb-882d-48df37ae3dc4_10.jpg?type=f194_109_blend"},{"title":"'박강아름 결혼하다' 뮤직비디오 (네이버 영화 예고편 저장소)","contents":"8시간 전","link":"https://tv.naver.com/v/21783762","retrieved":1628576324905,"image":"https://phinf.pstatic.net/tvcast/20210810_69/mDSze_1628572761873EYuIg_JPEG/1628572759218.jpg?type=f194_109_blend"},{"title":"'코다' 파이널 예고편 (네이버 영화 예고편 저장소)","contents":"10시간 전","link":"https://tv.naver.com/v/21779647","retrieved":1628564465299,"image":"https://phinf.pstatic.net/tvcast/20210810_32/rUOdu_1628563607790XuNRY_JPEG/52648292-f984-11eb-86ec-48df37ae3fca_07.jpg?type=f194_109_blend"},{"title":"'리벤지 오브 인사이트' 예고편 (네이버 영화 예고편 저장소)","contents":"11시간 전","link":"https://tv.naver.com/v/21778304","retrieved":1628563553959,"image":"https://phinf.pstatic.net/tvcast/20210810_64/F48YP_1628559624872Hcpqc_JPEG/a69db8cb-f97b-11eb-80a9-a0369ff95678_04.jpg?type=f194_109_blend"},{"title":"'윙스 오버 에베레스트' 메인 예고편 (네이버 영화 예고편 저장소)","contents":"11시간 전","link":"https://tv.naver.com/v/21778061","retrieved":1628563553966,"image":"https://phinf.pstatic.net/tvcast/20210810_279/6Zi7Y_1628558808319cHY5L_JPEG/a1682d34-f979-11eb-9d7e-a0369ff952f4_01.jpg?type=f194_109_blend"},{"title":"'한 침대 두 커플' 예고편 (네이버 영화 예고편 저장소)","contents":"1일 전","link":"https://tv.naver.com/v/21769505","retrieved":1628500564302,"image":"https://phinf.pstatic.net/tvcast/20210809_253/McnlH_1628497950838O40BM_JPEG/420312e8-f8ec-11eb-8c9c-505dac8c37f3_09.jpg?type=f194_109_blend"},{"title":"'교회누나랑 첫 여자' 예고편 (네이버 영화 예고편 저장소)","contents":"1일 전","link":"https://tv.naver.com/v/21769312","retrieved":1628500564302,"image":"https://phinf.pstatic.net/tvcast/20210809_274/SBv36_1628497575821jeaG3_JPEG/64d1dc08-f8eb-11eb-809b-a0369ff94ed0_01.jpg?type=f194_109_blend"},{"title":"'캐논볼' 메인 예고편 (네이버 영화 예고편 저장소)","contents":"1일 전","link":"https://tv.naver.com/v/21767125","retrieved":1628493229709,"image":"https://phinf.pstatic.net/tvcast/20210809_160/pt60t_1628492582780dB3JF_JPEG/aea53554-f8df-11eb-882d-48df37ae3dc4_06.jpg?type=f194_109_blend"},{"title":"'신적인걸: 통천교주' 메인 예고편 (네이버 영화 예고편 저장소)","contents":"1일 전","link":"https://tv.naver.com/v/21766954","retrieved":1628493229712,"image":"https://phinf.pstatic.net/tvcast/20210809_76/96d9k_1628492244879x1628_JPEG/db8de6c8-f8de-11eb-89ce-48df379ccacc_03.jpg?type=f194_109_blend"},{"title":"'브레이브 하트2' 메인 예고편 (네이버 영화 예고편 저장소)","contents":"1일 전","link":"https://tv.naver.com/v/21765571","retrieved":1628489932985,"image":"https://phinf.pstatic.net/tvcast/20210809_140/znLel_1628488644408aLFr6_JPEG/f163bcfc-f8d5-11eb-a8ac-505dac8c35ff_03.jpg?type=f194_109_blend"},{"title":"'귀문' 제작기 영상 (네이버 영화 예고편 저장소)","contents":"1일 전","link":"https://tv.naver.com/v/21765318","retrieved":1628489933006,"image":"https://phinf.pstatic.net/tvcast/20210809_280/Dr84g_1628487805227M31zm_JPEG/4dcb8258-f8d4-11eb-8e61-a0369ff94f34_02.jpg?type=f194_109_blend"},{"title":"'여름날 우리' 메인 예고편 (네이버 영화 예고편 저장소)","contents":"1일 전","link":"https://tv.naver.com/v/21764333","retrieved":1628489933009,"image":"https://phinf.pstatic.net/tvcast/20210809_60/2210S_1628484907361nN6CQ_JPEG/cc8b7e5a-f8cd-11eb-8f8d-505dac8c3721_02.jpg?type=f194_109_blend"},{"title":"'바쿠라우' 티저 예고편 (네이버 영화 예고편 저장소)","contents":"1일 전","link":"https://tv.naver.com/v/21762667","retrieved":1628482761601,"image":"https://phinf.pstatic.net/tvcast/20210809_234/Lfuq5_1628477591139vbMHX_JPEG/b77f5f6e-f8bc-11eb-882d-48df37ae3dc4_03.jpg?type=f194_109_blend"},{"title":"'신마영정: 야인시대' 메인 예고편 (네이버 영화 예고편 저장소)","contents":"1일 전","link":"https://tv.naver.com/v/21761787","retrieved":1628476034164,"image":"https://phinf.pstatic.net/tvcast/20210809_88/yuws9_1628474208847Vw1GA_JPEG/c4c1aa4c-f8b4-11eb-882d-48df37ae3dc4_03.jpg?type=f194_109_blend"},{"title":"'귀신' 티저 예고편 (네이버 영화 예고편 저장소)","contents":"1일 전","link":"https://tv.naver.com/v/21761648","retrieved":1628476034165,"image":"https://phinf.pstatic.net/tvcast/20210809_14/LVtMb_1628473721183eiyHU_JPEG/a54a5abc-f8b3-11eb-86ec-48df37ae3fca_03.jpg?type=f194_109_blend"},{"title":"'모가디슈' 명장면 무삭제 클립 영상 (네이버 영화 예고편 저장소)","contents":"1일 전","link":"https://tv.naver.com/v/21735909","retrieved":1628476034185,"image":"https://phinf.pstatic.net/tvcast/20210806_286/Up0e3_1628240341327vA3CG_JPEG/39a8fa2d-f694-11eb-8111-505dac8c381b_10.jpg?type=f194_109_blend"},{"title":"'습도 다소 높음' 1차 예고편 (네이버 영화 예고편 저장소)","contents":"4일 전","link":"https://tv.naver.com/v/21735229","retrieved":1628375753403,"image":"https://phinf.pstatic.net/tvcast/20210806_73/UdJx6_1628238805366MosfU_JPEG/57b400c0-f690-11eb-8e61-a0369ff94f34_02.jpg?type=f194_109_blend"},{"title":"'더 테러 라이브: 스쿨 어택' 메인 예고편 (네이버 영화 예고편 저장소)","contents":"4일 전","link":"https://tv.naver.com/v/21734149","retrieved":1628375753415,"image":"https://phinf.pstatic.net/tvcast/20210806_13/mB2eV_16282363716348RJmj_JPEG/d1b1eb2f-f68a-11eb-bf57-246e963a4708_06.jpg?type=f194_109_blend"},{"title":"'더 그레이트 샤크' 생명 단축 리뷰 영상 (네이버 영화 예고편 저장소)","contents":"4일 전","link":"https://tv.naver.com/v/21732422","retrieved":1628375753417,"image":"https://phinf.pstatic.net/tvcast/20210806_190/XRCxw_1628232377370xawRQ_JPEG/bb054191-f681-11eb-86ec-48df37ae3fca_01.jpg?type=f194_109_blend"},{"title":"'레미니센스' 액션 추적 영상 (네이버 영화 예고편 저장소)","contents":"4일 전","link":"https://tv.naver.com/v/21731993","retrieved":1628375753417,"image":"https://phinf.pstatic.net/tvcast/20210806_67/yudEx_1628231508938beQup_JPEG/c7e4763b-f67f-11eb-a613-505dac8c38f5_07.jpg?type=f194_109_blend"},{"title":"'이도공간' 뮤직비디오 (네이버 영화 예고편 저장소)","contents":"4일 전","link":"https://tv.naver.com/v/21731759","retrieved":1628375753418,"image":"https://phinf.pstatic.net/tvcast/20210806_157/d4LrM_1628230960260jvo81_JPEG/79339dd9-f67e-11eb-8111-505dac8c381b_03.jpg?type=f194_109_blend"},{"title":"'아담' 30초 예고편 (네이버 영화 예고편 저장소)","contents":"4일 전","link":"https://tv.naver.com/v/21731478","retrieved":1628375753419,"image":"https://phinf.pstatic.net/tvcast/20210806_100/CiRFm_1628230226950xrONV_JPEG/b6783253-f67c-11eb-9b63-505dacfba98a_01.jpg?type=f194_109_blend"},{"title":"'귀문' ScreenX vs 4DX 공포 배틀 영상 (네이버 영화 예고편 저장소)","contents":"4일 전","link":"https://tv.naver.com/v/21730247","retrieved":1628375753419,"image":"https://phinf.pstatic.net/tvcast/20210806_178/MIBIH_16282270780093t26P_JPEG/fd3b8ed1-f674-11eb-9d74-a0369ff9545c_01.jpg?type=f194_109_blend"},{"title":"'건담 G의 레콘기스타 2: 벨리 격진' 메인 예고편 (네이버 영화 예고편 저장소)","contents":"4일 전","link":"https://tv.naver.com/v/21729726","retrieved":1628375753420,"image":"https://phinf.pstatic.net/tvcast/20210806_107/RVyzK_1628225749309AStWC_JPEG/71612ae4-f672-11eb-b835-505dac8c3607_04.jpg?type=f194_109_blend"}]}