{"title":"Combined feed","url":"https://MOVIECORD.github.io/feeds/all.xml","elements":[{"title":"'D.P.' 정해인·구교환 \"군대 아닌 우리 주변의 이야기…공감할 것\"(종합) (네이버TV연예 ─ 영화)","contents":"기사내용 요약 넷플릭스 시리즈 'D.P.' 온라인 제작발표회 정해인·구교환 탈영병 잡는 체포조로 '콤비' 호흡 [서울=뉴시스] 김지은 기자 = 군대에서 도망친 탈영병과 그들을 뒤쫓는 군인의 이야기를 담은 'D.P.'","link":"https://entertain.naver.com/movie/now/read?oid=003&aid=0010682442","retrieved":1629865161864},{"title":"'D.P.' 軍서 뭉친 정해인X구교환, 탈영병 잡으러 출동 [종합] (네이버TV연예 ─ 영화)","contents":"배우 정해인과 구교환 김성균, 손석구 등이 군대에서 뭉쳤다. 25일 오전 넷플릭스 시리즈 'D.P.' 제작보고회가 열렸다. 이날 행사에는 정해인 구교환 김성균 손석구 한준희 감독이 참석했다. 'D.P.'는 탈영병들을","link":"https://entertain.naver.com/movie/now/read?oid=108&aid=0002983423","retrieved":1629865161864},{"title":"“탈영병 잡는 군인”…‘D.P.’ 정해인·구교환이 출격한다 [스경X현장] (네이버TV연예 ─ 영화)","contents":"[스포츠경향] “‘D.P.’는 사복헌병입니다. 부대 밖에서 생활하는 D.P.조가 탈영병을 잡기 위해 활동하는 모습을 담는데요. 탈영병들의 사연, 그 사연들을 쫓으면서 무언가를 깨닫고 성장해나가는 두 인물을 그린 이야","link":"https://entertain.naver.com/movie/now/read?oid=144&aid=0000757737","retrieved":1629865161864},{"title":"‘D.P.’ 구교환 “정해인에 1일 데이트권 주고 싶다” (네이버TV연예 ─ 영화)","contents":"[스포츠경향] 배우 구교환이 정해인에 대한 애정을 표현했다. 구교환은 25일 오전 온라인생중계된 넷플릭스 새 시리즈 ‘D.P.’ 제작발표회에서 “정해인에게 나와 1일 데이트권을 주고 싶다”고 밝혀 웃음을 자아냈다.","link":"https://entertain.naver.com/movie/now/read?oid=144&aid=0000757734","retrieved":1629861346203},{"title":"넷플릭스 영화 <사냥의 시간> <콜> <승리호> <낙원의 밤>, CGV에서 본다 (네이버TV연예 ─ 영화)","contents":"넷플릭스 영화가 극장에서 상영된다. 넷플릭스와 CJ CGV가 특별전 ‘NETFLIX IN CGV’(넷픽)를 연다. 9월1일부터 12일까지 진행되는 이번 특별전에서 &lt;사냥의 시간&gt; &lt;콜&gt; &lt;차인표&gt; &lt;승리호&gt; &lt;낙원의","link":"https://entertain.naver.com/movie/now/read?oid=140&aid=0000045208","retrieved":1629861346206},{"title":"'D.P.' 정해인 \"구교환 애드리브, 행복한 고통이었다\" (네이버TV연예 ─ 영화)","contents":"배우 정해인이 구교환의 애드리브로 인해 많이 웃었다고 털어놨다. 25일 오전 넷플릭스 시리즈 'D.P.' 제작보고회가 열렸다. 이날 행사에는 정해인 구교환 김성균 손석구 한준희 감독이 참석했다. 'D.P.'는 탈영병","link":"https://entertain.naver.com/movie/now/read?oid=108&aid=0002983417","retrieved":1629861346227},{"title":"‘D.P.’ 정해인 “세트장, 실제 군대 같아서 소름” (네이버TV연예 ─ 영화)","contents":"[스포츠경향] 배우 정해인이 넷플릭스 새 시리즈 ‘D.P.’의 리얼리티를 보장했다. 정해인은 25일 오전 온라인생중계된 ‘D.P.’ 제작발표회에서 “제작진이 세트장을 정말 군대처럼 극사실주의로 만들어서 소름이 돋았다","link":"https://entertain.naver.com/movie/now/read?oid=144&aid=0000757731","retrieved":1629861346233},{"title":"CGV, 송중기 ‘승리호’→‘낙원의 밤’ 등 한국 넷플릭스 영화 7편 상영 (네이버TV연예 ─ 영화)","contents":"넷플릭스 영화로 공개되었던 한국영화를 극장에서도 볼 수 있는 길이 열렸다. CGV가 넷플릭스 영화로 공개되었던 한국영화들을 모아 ‘NETFIC(넷픽, NETFLIX IN CGV)’ 특별전을 개최한다고 25일 밝혔다.","link":"https://entertain.naver.com/movie/now/read?oid=410&aid=0000811516","retrieved":1629861346234},{"title":"배우 구교환, 넷플릭스 한국 드라마 'D.P.' 제작발표회 (네이버TV연예 ─ 영화)","contents":"[서울=뉴시스] 박진희 기자 = 배우 구교환이 25일 넷플릭스 한국드라마 'D.P.' 온라인 제작발표회를 하고 있다. (사진=넷플릭스 제공) 2021.08.25. photo@newsis.com *재판매 및 DB 금지","link":"https://entertain.naver.com/movie/now/read?oid=003&aid=0010682313","retrieved":1629861346243},{"title":"배우 손석구, 넷플릭스 한국 드라마 'D.P.' 제작발표회 (네이버TV연예 ─ 영화)","contents":"[서울=뉴시스] 박진희 기자 = 배우 손석구가 25일 넷플릭스 한국드라마 'D.P.' 온라인 제작발표회를 하고 있다. (사진=넷플릭스 제공) 2021.08.25. photo@newsis.com *재판매 및 DB 금지","link":"https://entertain.naver.com/movie/now/read?oid=003&aid=0010682312","retrieved":1629861346248},{"title":"배우 손석구, 넷플릭스 한국 드라마 'D.P.' 제작발표회 (네이버TV연예 ─ 영화)","contents":"[서울=뉴시스] 박진희 기자 = 배우 손석구가 25일 넷플릭스 한국드라마 'D.P.' 온라인 제작발표회를 하고 있다. (사진=넷플릭스 제공) 2021.08.25. photo@newsis.com *재판매 및 DB 금지","link":"https://entertain.naver.com/movie/now/read?oid=003&aid=0010682311","retrieved":1629861346250},{"title":"배우 김성균, 넷플릭스 한국 드라마 'D.P.' 제작발표회 (네이버TV연예 ─ 영화)","contents":"[서울=뉴시스] 박진희 기자 = 배우 김성균이 25일 넷플릭스 한국드라마 'D.P.' 온라인 제작발표회를 하고 있다. (사진=넷플릭스 제공) 2021.08.25. photo@newsis.com *재판매 및 DB 금지","link":"https://entertain.naver.com/movie/now/read?oid=003&aid=0010682310","retrieved":1629861346251},{"title":"배우 정해인, 넷플릭스 한국 드라마 'D.P.' 제작발표회 (네이버TV연예 ─ 영화)","contents":"[서울=뉴시스] 박진희 기자 = 배우 정해인이 25일 넷플릭스 한국드라마 'D.P.' 온라인 제작발표회를 하고 있다. (사진=넷플릭스 제공) 2021.08.25. photo@newsis.com *재판매 및 DB 금지","link":"https://entertain.naver.com/movie/now/read?oid=003&aid=0010682309","retrieved":1629861346253},{"title":"배우 정해인, 넷플릭스 한국 드라마 'D.P.' 제작발표회 (네이버TV연예 ─ 영화)","contents":"[서울=뉴시스] 박진희 기자 = 배우 정해인이 25일 넷플릭스 한국드라마 'D.P.' 온라인 제작발표회를 하고 있다. (사진=넷플릭스 제공) 2021.08.25. photo@newsis.com *재판매 및 DB 금지","link":"https://entertain.naver.com/movie/now/read?oid=003&aid=0010682308","retrieved":1629861346254},{"title":"넷플릭스 한국 드라마 'D.P.' 제작발표회 (네이버TV연예 ─ 영화)","contents":"[서울=뉴시스] 박진희 기자 = 배우 정해인, 구교환, 김성균, 손석구가 25일 넷플릭스 한국드라마 'D.P.' 온라인 제작발표회를 하고 있다. (사진=넷플릭스 제공) 2021.08.25. photo@newsis.c","link":"https://entertain.naver.com/movie/now/read?oid=003&aid=0010682307","retrieved":1629861346256},{"title":"정해인-구교환, 넷플릭스 한국 드라마 'D.P.' 제작발표회 (네이버TV연예 ─ 영화)","contents":"[서울=뉴시스] 박진희 기자 = 배우 정해인과 구교환이 25일 넷플릭스 한국드라마 'D.P.' 온라인 제작발표회를 하고 있다. (사진=넷플릭스 제공) 2021.08.25. photo@newsis.com *재판매 및","link":"https://entertain.naver.com/movie/now/read?oid=003&aid=0010682306","retrieved":1629861346258},{"title":"넷플릭스 한국 드라마 'D.P.' 제작발표회 (네이버TV연예 ─ 영화)","contents":"[서울=뉴시스] 박진희 기자 = 배우 구교환, 김성균, 손석구, 한준희 감독, 정해인이 25일 넷플릭스 한국드라마 'D.P.' 온라인 제작발표회를 하고 있다. (사진=넷플릭스 제공) 2021.08.25. photo@","link":"https://entertain.naver.com/movie/now/read?oid=003&aid=0010682305","retrieved":1629861346263},{"title":"넷플릭스 한국 드라마 'D.P.' 제작발표회 (네이버TV연예 ─ 영화)","contents":"[서울=뉴시스] 박진희 기자 = 배우 정해인, 구교환, 김성균, 손석구가 25일 넷플릭스 한국드라마 'D.P.' 온라인 제작발표회를 하고 있다. (사진=넷플릭스 제공) 2021.08.25. photo@newsis.c","link":"https://entertain.naver.com/movie/now/read?oid=003&aid=0010682304","retrieved":1629861346270},{"title":"‘기적’ 박정민X임윤아 “따뜻함이야말로 사람들 마음 움직여”[스타화보] (네이버TV연예 ─ 영화)","contents":"[뉴스엔 배효주 기자] '기적' 박정민과 임윤아가 함께한 화보와 인터뷰가 공개됐다. 9월 개봉하는 영화 '기적'은 오갈 수 있는 길은 기찻길밖에 없지만 정작 기차역은 없는 마을에 간이역 하나 생기는 게 유일한 인생","link":"https://entertain.naver.com/movie/now/read?oid=609&aid=0000482653","retrieved":1629861346271},{"title":"티아라 지연, 영화 '화녀' 주인공…오랜만에 스크린 복귀 [공식] (네이버TV연예 ─ 영화)","contents":"[마이데일리 = 양유진 기자] 그룹 티아라 멤버 겸 배우 지연이 영화 '화녀' 주인공으로 발탁되며 오랜만에 스크린으로 복귀한다. 영화 '화녀'는 스릴러물의 장편 상업영화로, 지연은 극중 유명 배우의 삶을 살다 한 순","link":"https://entertain.naver.com/movie/now/read?oid=117&aid=0003530293","retrieved":1629861346272},{"title":"정해인X구교환 찐 브로의 뜨거운 ‘D.P.’[종합] (네이버TV연예 ─ 영화)","contents":"리얼하고도 신선한 청춘 이야기가 온다. 김성균 정해인 구교환 손석구가 뭉친 영화 'D.P'(감독 한준희)다. 25일 오전 온라인으로 넷플릭스 오리지널 시리즈 'D.P.' 제작발표회가 열렸다. 먼저 메가폰을 잡은 한준","link":"https://entertain.naver.com/movie/now/read?oid=009&aid=0004842961","retrieved":1629861346273},{"title":"드디어 오픈…'인질' 대장 빌런 김재범 \"황정민에 꿇리지 않으려 최선\" (네이버TV연예 ─ 영화)","contents":"[스포티비뉴스=김현록 기자]박스오피스 1위 자리를 굳건히 지키며 흥행 중인 영화 '인질'이 김재범의 캐릭터 스틸을 전격 공개했다. NEW는 '인질'(감독 필감성, 제작 (주)외유내강) 속 빌런들의 리더, ‘최기완’ 역의","link":"https://entertain.naver.com/movie/now/read?oid=477&aid=0000315776","retrieved":1629861346274},{"title":"'인질' 이유미, 첫 번째 '인질'로 변신..황정민과 탈출 감행 (네이버TV연예 ─ 영화)","contents":"[헤럴드POP=박서현기자] '인질' 이유미가 밀도 높은 열연을 선사, 다시 한번 믿고 보는 배우의 진가를 입증했다. 지난 18일 베일을 벗은 영화 '인질'이 손에 땀을 쥐게 만드는 휘몰아치는 전개와 빈틈없는 열연 퍼","link":"https://entertain.naver.com/movie/now/read?oid=112&aid=0003469985","retrieved":1629861346275},{"title":"'D.P.' 정해인 \"작품 위해 3개월 복싱 연습..대역 없이 촬영\" (네이버TV연예 ─ 영화)","contents":"배우 정해인이 작품을 위해 3개월 간 복싱 연습을 했다고 말했다. 25일 오전 넷플릭스 시리즈 'D.P.' 제작보고회가 열렸다. 이날 행사에는 정해인 구교환 김성균 손석구 한준희 감독이 참석했다. 'D.P.'는 탈영","link":"https://entertain.naver.com/movie/now/read?oid=108&aid=0002983401","retrieved":1629861346277},{"title":"홍콩 영화 검열 본격화…\"주성치 영화도 허가취소 가능\" (네이버TV연예 ─ 영화)","contents":"불법상영 징역형 강화…\"레드라인 더 넓게 확대\" (홍콩=연합뉴스) 윤고은 특파원 = 홍콩 정부가 옛 영화에 대한 상영 허가를 취소할 수 있는 내용이 포함된 법률 개정을 추진하며 영화에 대한 검열을 본격화하고 있다.","link":"https://entertain.naver.com/movie/now/read?oid=001&aid=0012619769","retrieved":1629861346278},{"title":"인질 (다음영화 영화관 ─ 현재상영)","contents":"21.08.18","link":"https://movie.daum.net/moviedb/main?movieId=127738","retrieved":1629042859643,"image":"https://img1.daumcdn.net/thumb/C408x596/?fname=https%3A%2F%2Ft1.daumcdn.net%2Fmovie%2Fe1285fe4d39de150ca497edf0d91d8b4ad8d8e39"},{"title":"싱크홀 (다음영화 영화관 ─ 현재상영)","contents":"21.08.11","link":"https://movie.daum.net/moviedb/main?movieId=134290","retrieved":1629043175260,"image":"https://img1.daumcdn.net/thumb/C408x596/?fname=https%3A%2F%2Ft1.daumcdn.net%2Fmovie%2F446090579974d44551356ce961743e57eaa41bd6"},{"title":"귀문 (다음영화 영화관 ─ 현재상영)","contents":"21.08.25","link":"https://movie.daum.net/moviedb/main?movieId=151323","retrieved":1629852411001,"image":"https://img1.daumcdn.net/thumb/C408x596/?fname=https%3A%2F%2Ft1.daumcdn.net%2Fmovie%2F159c36be955bf23df2dab2b17953595b2f8e5f15"},{"title":"모가디슈 (다음영화 영화관 ─ 현재상영)","contents":"21.07.28","link":"https://movie.daum.net/moviedb/main?movieId=132564","retrieved":1629043175260,"image":"https://img1.daumcdn.net/thumb/C408x596/?fname=https%3A%2F%2Ft1.daumcdn.net%2Fmovie%2F8606d47d1447d6c8f77e9dfe91aba7ce53c09488"},{"title":"레미니센스 (다음영화 영화관 ─ 현재상영)","contents":"21.08.25","link":"https://movie.daum.net/moviedb/main?movieId=151315","retrieved":1629852411001,"image":"https://img1.daumcdn.net/thumb/C408x596/?fname=https%3A%2F%2Ft1.daumcdn.net%2Fmovie%2F3b72c91d5a32de281ff8224830482a733df9cd68"},{"title":"여름날 우리 (다음영화 영화관 ─ 현재상영)","contents":"21.08.25","link":"https://movie.daum.net/moviedb/main?movieId=151333","retrieved":1629852411002,"image":"https://img1.daumcdn.net/thumb/C408x596/?fname=https%3A%2F%2Ft1.daumcdn.net%2Fmovie%2F1ad067800d4d9fa50c4626c017a0f831e31e27a3"},{"title":"프리 가이 (다음영화 영화관 ─ 현재상영)","contents":"21.08.11","link":"https://movie.daum.net/moviedb/main?movieId=131277","retrieved":1629043175266,"image":"https://img1.daumcdn.net/thumb/C408x596/?fname=https%3A%2F%2Ft1.daumcdn.net%2Fmovie%2Fb83ce3cb29a492a800a4c18c0c168987ecc21e43"},{"title":"귀신 (다음영화 영화관 ─ 현재상영)","contents":"21.08.25","link":"https://movie.daum.net/moviedb/main?movieId=142522","retrieved":1629852411003,"image":"https://img1.daumcdn.net/thumb/C408x596/?fname=https%3A%2F%2Ft1.daumcdn.net%2Fmovie%2F9ea87dc38b521afffb78d3ede90c8f080e413108"},{"title":"올드 (다음영화 영화관 ─ 현재상영)","contents":"21.08.18","link":"https://movie.daum.net/moviedb/main?movieId=145174","retrieved":1629042859654,"image":"https://img1.daumcdn.net/thumb/C408x596/?fname=https%3A%2F%2Ft1.daumcdn.net%2Fmovie%2F2771975974a5ea16126c86bd0bb19fb57f8cc0c2"},{"title":"퍼피 구조대 더 무비 (다음영화 영화관 ─ 현재상영)","contents":"21.08.18","link":"https://movie.daum.net/moviedb/main?movieId=151320","retrieved":1629042859656,"image":"https://img1.daumcdn.net/thumb/C408x596/?fname=https%3A%2F%2Ft1.daumcdn.net%2Fmovie%2Fcddfc4c347466a3f1960fb480cdfa1a57d1835ff"},{"title":"남색대문 (다음영화 영화관 ─ 현재상영)","contents":"21.08.18","link":"https://movie.daum.net/moviedb/main?movieId=44893","retrieved":1629042859657,"image":"https://img1.daumcdn.net/thumb/C408x596/?fname=https%3A%2F%2Ft1.daumcdn.net%2Fmovie%2F17149b5f9a248e4e6e0fe88b5cd2fe99ecc8e2a1"},{"title":"더 수어사이드 스쿼드 (다음영화 영화관 ─ 현재상영)","contents":"21.08.04","link":"https://movie.daum.net/moviedb/main?movieId=122276","retrieved":1629043175266,"image":"https://img1.daumcdn.net/thumb/C408x596/?fname=https%3A%2F%2Ft1.daumcdn.net%2Fmovie%2F8c183d3a3ac7d926c9aac443a650211a7e5494f4"},{"title":"하이큐!! 땅 VS 하늘 (다음영화 영화관 ─ 현재상영)","contents":"21.08.12","link":"https://movie.daum.net/moviedb/main?movieId=137824","retrieved":1629043175275,"image":"https://img1.daumcdn.net/thumb/C408x596/?fname=https%3A%2F%2Ft1.daumcdn.net%2Fmovie%2F96dd30921f935279b8fa9f5d013d0b831be01410"},{"title":"아이스 로드 (다음영화 영화관 ─ 현재상영)","contents":"21.07.21","link":"https://movie.daum.net/moviedb/main?movieId=150693","retrieved":1629043175278,"image":"https://img1.daumcdn.net/thumb/C408x596/?fname=https%3A%2F%2Ft1.daumcdn.net%2Fmovie%2F4f98e5c0d73c95891b49493b7d62ba4480489df6"},{"title":"더 그레이트 샤크 (다음영화 영화관 ─ 현재상영)","contents":"21.08.05","link":"https://movie.daum.net/moviedb/main?movieId=150566","retrieved":1629420375936,"image":"https://img1.daumcdn.net/thumb/C408x596/?fname=https%3A%2F%2Ft1.daumcdn.net%2Fmovie%2Fa89dc80a0838884bbe5b7da0240ff9664b789c48"},{"title":"킬러의 보디가드 2: 킬러의 와이프 (다음영화 영화관 ─ 현재상영)","contents":"21.08.04","link":"https://movie.daum.net/moviedb/main?movieId=130061","retrieved":1629043175272,"image":"https://img1.daumcdn.net/thumb/C408x596/?fname=https%3A%2F%2Ft1.daumcdn.net%2Fmovie%2F44cff9be3a13f0cf1746357f7d4dd58f248f5f2c"},{"title":"킬러의 보디가드 2: 킬러의 와이프 (다음영화 영화관 ─ 현재상영)","contents":"21.06.23","link":"https://movie.daum.net/moviedb/main?movieId=130061","retrieved":1629043175272,"image":"https://img1.daumcdn.net/thumb/C408x596/?fname=https%3A%2F%2Ft1.daumcdn.net%2Fmovie%2F44cff9be3a13f0cf1746357f7d4dd58f248f5f2c"},{"title":"블랙 위도우 (다음영화 영화관 ─ 현재상영)","contents":"21.07.07","link":"https://movie.daum.net/moviedb/main?movieId=123215","retrieved":1629043175269,"image":"https://img1.daumcdn.net/thumb/C408x596/?fname=https%3A%2F%2Ft1.daumcdn.net%2Fmovie%2Ff39274b0acd76f7c66f0a5fb9e5b7222ed37b373"},{"title":"팜 스프링스 (다음영화 영화관 ─ 현재상영)","contents":"21.08.19","link":"https://movie.daum.net/moviedb/main?movieId=137848","retrieved":1629333676865,"image":"https://img1.daumcdn.net/thumb/C408x596/?fname=https%3A%2F%2Ft1.daumcdn.net%2Fmovie%2F4c82a5639003742ab571a36d61b6a7092229d9d4"},{"title":"그린 나이트 (다음영화 영화관 ─ 현재상영)","contents":"21.08.05","link":"https://movie.daum.net/moviedb/main?movieId=139183","retrieved":1629043175276,"image":"https://img1.daumcdn.net/thumb/C408x596/?fname=https%3A%2F%2Ft1.daumcdn.net%2Fmovie%2F6dd33309d1b1b3a9e3aa6e65ddf1ebe229433eb3"},{"title":"코드 카림 (다음영화 영화관 ─ 개봉예정)","contents":"21.08.26","link":"https://movie.daum.net/moviedb/main?movieId=151147","retrieved":1629328530344,"image":"https://img1.daumcdn.net/thumb/C408x596/?fname=https%3A%2F%2Ft1.daumcdn.net%2Fmovie%2F7426c08b967d01f615174ddcd4063545ebaa2f31"},{"title":"극장판 페이트/그랜드 오더 신성원탁영역 카멜롯 팔라딘; 아가트람 (다음영화 영화관 ─ 개봉예정)","contents":"21.08.26","link":"https://movie.daum.net/moviedb/main?movieId=150453","retrieved":1629328530357,"image":"https://img1.daumcdn.net/thumb/C408x596/?fname=https%3A%2F%2Ft1.daumcdn.net%2Fmovie%2Fb466e8c626f9f77e033ed7a6023d82568d327ef6"},{"title":"드림걸즈 (다음영화 영화관 ─ 개봉예정)","contents":"21.08.26","link":"https://movie.daum.net/moviedb/main?movieId=42728","retrieved":1629328530346,"image":"https://img1.daumcdn.net/thumb/C408x596/?fname=https%3A%2F%2Ft1.daumcdn.net%2Fmovie%2Fe4f98bccfb72790b319d30d2fa4303cd49eda578"},{"title":"자마 (다음영화 영화관 ─ 개봉예정)","contents":"21.08.26","link":"https://movie.daum.net/moviedb/main?movieId=114771","retrieved":1629328530353,"image":"https://img1.daumcdn.net/thumb/C408x596/?fname=https%3A%2F%2Ft1.daumcdn.net%2Fmovie%2F59dc5878cbd995a1b68d2e175baae4c02ed24f47"},{"title":"다이노 마이 프렌드 (다음영화 영화관 ─ 개봉예정)","contents":"21.08.26","link":"https://movie.daum.net/moviedb/main?movieId=151976","retrieved":1629328530349,"image":"https://img1.daumcdn.net/thumb/C408x596/?fname=https%3A%2F%2Ft1.daumcdn.net%2Fmovie%2F93349a89d113d410c0d3a697da856283e5cbea78"},{"title":"마더스 인스팅트 (다음영화 영화관 ─ 개봉예정)","contents":"21.08.26","link":"https://movie.daum.net/moviedb/main?movieId=124585","retrieved":1629247689657,"image":"https://img1.daumcdn.net/thumb/C408x596/?fname=https%3A%2F%2Ft1.daumcdn.net%2Fmovie%2F505ed2bc353f446fc063ddfa39f1aa91703bcf9d"},{"title":"블룸 업: 스와핑 (다음영화 영화관 ─ 개봉예정)","contents":"21.08.26","link":"https://movie.daum.net/moviedb/main?movieId=150768","retrieved":1629328530350,"image":"https://img1.daumcdn.net/thumb/C408x596/?fname=https%3A%2F%2Ft1.daumcdn.net%2Fmovie%2F40bb31becca612805d5ae2f6f8ef018375a83ccc"},{"title":"블러드 비스트 (다음영화 영화관 ─ 개봉예정)","contents":"21.08.26","link":"https://movie.daum.net/moviedb/main?movieId=152287","retrieved":1629328530352,"image":"https://img1.daumcdn.net/thumb/C408x596/?fname=https%3A%2F%2Ft1.daumcdn.net%2Fmovie%2F1e39f9c2d1758887cf346968162dac42c85d2844"},{"title":"올리버 색스: 그의 생애 (다음영화 영화관 ─ 개봉예정)","contents":"21.08.26","link":"https://movie.daum.net/moviedb/main?movieId=135758","retrieved":1629328530355,"image":"https://img1.daumcdn.net/thumb/C408x596/?fname=https%3A%2F%2Ft1.daumcdn.net%2Fmovie%2F04ab47947966c855f781e9df6ce6876355cda687"},{"title":"숲의 비명 : 사라진 사람들 (다음영화 영화관 ─ 개봉예정)","contents":"21.08.26","link":"https://movie.daum.net/moviedb/main?movieId=152678","retrieved":1629420383519,"image":"https://img1.daumcdn.net/thumb/C408x596/?fname=https%3A%2F%2Ft1.daumcdn.net%2Fmovie%2Fca92cf27755f3d244f7d7a23951e60533416a7f1"},{"title":"카라타이: 태양의 전사 (다음영화 영화관 ─ 개봉예정)","contents":"21.08.26","link":"https://movie.daum.net/moviedb/main?movieId=152727","retrieved":1629537292925,"image":"https://img1.daumcdn.net/thumb/C408x596/?fname=https%3A%2F%2Ft1.daumcdn.net%2Fmovie%2F1bab9942f0a56ef45283fe7c6f1bc9175eb089fa"},{"title":"데미지 (다음영화 영화관 ─ 개봉예정)","contents":"21.08.26","link":"https://movie.daum.net/moviedb/main?movieId=1785","retrieved":1629695608073,"image":"https://img1.daumcdn.net/thumb/C408x596/?fname=https%3A%2F%2Ft1.daumcdn.net%2Fmovie%2F047da9511aa35e5892f2ad983473b03710c24516"},{"title":"코다 (다음영화 영화관 ─ 개봉예정)","contents":"21.08.31","link":"https://movie.daum.net/moviedb/main?movieId=147452","retrieved":1629829064757,"image":"https://img1.daumcdn.net/thumb/C408x596/?fname=https%3A%2F%2Ft1.daumcdn.net%2Fmovie%2F9db1b2ab48843490fa9705cbae8389e6c3bd9876"},{"title":"켈리 갱 (다음영화 영화관 ─ 개봉예정)","contents":"21.08.31","link":"https://movie.daum.net/moviedb/main?movieId=134961","retrieved":1629846914598,"image":"https://img1.daumcdn.net/thumb/C408x596/?fname=https%3A%2F%2Ft1.daumcdn.net%2Fmovie%2F72e9fb6eb7fbc2597815fd1551e30576a385d658"},{"title":"상견니 (다음영화 영화관 ─ 개봉예정)","contents":"21.08.31","link":"https://movie.daum.net/moviedb/main?movieId=153046","retrieved":1629846914601,"image":"https://img1.daumcdn.net/thumb/C408x596/?fname=https%3A%2F%2Ft1.daumcdn.net%2Fmovie%2F66c754624aca8e6f9ae303ffe4216bbf59ac31a0"},{"title":"데이 앤 나잇 (다음영화 영화관 ─ 개봉예정)","contents":"21.08","link":"https://movie.daum.net/moviedb/main?movieId=131065","retrieved":1629846914601,"image":"https://img1.daumcdn.net/thumb/C408x596/?fname=https%3A%2F%2Ft1.daumcdn.net%2Fmovie%2F04a99481b4858518caf28b4c570ff364ef111d32"},{"title":"브레이브 하트2 (다음영화 영화관 ─ 개봉예정)","contents":"21.08","link":"https://movie.daum.net/moviedb/main?movieId=132821","retrieved":1629846914602,"image":"https://img1.daumcdn.net/thumb/C408x596/?fname=https%3A%2F%2Ft1.daumcdn.net%2Fmovie%2Ff8e88784cdb4aae6db9df532f9b98cdcca89c12b"},{"title":"언노운 아이덴티티 (다음영화 영화관 ─ 개봉예정)","contents":"21.08","link":"https://movie.daum.net/moviedb/main?movieId=150450","retrieved":1629846914603,"image":"https://img1.daumcdn.net/thumb/C408x596/?fname=https%3A%2F%2Ft1.daumcdn.net%2Fmovie%2Fb0f819f22cc53bba3aa41ad353d46ef5510986ae"},{"title":"노바디 다이 (다음영화 영화관 ─ 개봉예정)","contents":"21.08","link":"https://movie.daum.net/moviedb/main?movieId=151631","retrieved":1629846914605,"image":"https://img1.daumcdn.net/thumb/C408x596/?fname=https%3A%2F%2Ft1.daumcdn.net%2Fmovie%2Fb06f7722510ddaec82eff5f556e9889f92946c2e"},{"title":"스네이크 아이즈: 지.아이.조 (다음영화 영화관 ─ 개봉예정)","contents":"21.08","link":"https://movie.daum.net/moviedb/main?movieId=137243","retrieved":1629846914606,"image":"https://img1.daumcdn.net/thumb/C408x596/?fname=https%3A%2F%2Ft1.daumcdn.net%2Fmovie%2F7e3c07f14911dd107fa48930131b0eb3b7696b60"},{"title":"티아라 지연 '화녀' 주인공 발탁..스릴러물 도전 (다음영화 뉴스 ─ 인기)","contents":"(서울=뉴스1) 고승아 기자 = 그룹 티아라 겸 배우 박지연이 영화 '화녀' 주인공으로 발탁되며 오랜만에 스크린으로 복귀한다. 영화 '화녀'는 스릴러물의 장편 상업영화로, 박지연은 극중 유명 배우의 삶을 살다 한 순간의 실수로 위기를 겪고 난 후 다시 배우로서의 재기를 꿈꾸는 주인공 '이수연' 역을 맡았다. '화녀'는 촉망받던 배우와 그녀의 팬, 그리","link":"https://movie.v.daum.net/v/20210825083438536","retrieved":1629852425894,"image":"https://img1.daumcdn.net/thumb/S732x228/?fname=https%3A%2F%2Ft1.daumcdn.net%2Fnews%2F202108%2F25%2FNEWS1%2F20210825083439662cjgt.jpg"},{"title":"송중기 '승리호'→전여빈 '낙원의 밤' 등 넷플릭스 7편, 극장서 상영한다 [공식] (다음영화 뉴스 ─ 인기)","contents":"[마이데일리 = 김나라 기자] 송중기 '승리호', 전여빈 '낙원의 밤' 등 넷플릭스 작품들이 CGV에서 상영된다. 세계적인 엔터테인먼트 스트리밍 서비스 넷플릭스는 25일 오전, \"CGV와 함께 'NETFLIX IN CGV(넷픽)'를 개최한다\"라며 \"이는 한국 창작자들이 만들고 전 세계가 사랑한 넷플릭스 영화를 위한 특별전\"이라고 밝혔다. 오는 9월 1일부","link":"https://movie.v.daum.net/v/20210825085240974","retrieved":1629852425893,"image":"https://img1.daumcdn.net/thumb/S732x228/?fname=https%3A%2F%2Ft1.daumcdn.net%2Fnews%2F202108%2F25%2Fmydaily%2F20210825085240874oult.jpg"},{"title":"[노규민의 영화인싸] \"MCU 얘기 좀 합시다\"..마블 첫 아시안 히어로 '샹치' 따낸 시무 리우 (다음영화 뉴스 ─ 인기)","contents":"[텐아시아=노규민 기자]≪노규민의 영화人싸≫노규민 텐아시아 영화팀장이 매주 수요일 오전 영화계 인물에 대한 이야기를 전합니다. 배우, 감독, 작가, 번역가, 제작사 등 영화 생태계 구성원들 가운데 오늘뿐 아니라 미래의 '인싸'들을 집중 탐구합니다.상상을 초월하는 '텐 링즈'의 힘으로 오랜 세월 동안 어둠이 빗발치는 세상을 지배해 온 웬우. 샹치는 이런 아버","link":"https://movie.v.daum.net/v/20210825070101897","retrieved":1629852425907,"image":"https://img1.daumcdn.net/thumb/S384x240/?fname=https%3A%2F%2Ft1.daumcdn.net%2Fnews%2F202108%2F25%2F10asia%2F20210825070105371dztk.jpg"},{"title":"'듄' 영화 '아바타' 이후 가장 혁명적 프로젝트, 초호화 캐스팅으로 기대작으로 등극! (다음영화 뉴스 ─ 인기)","contents":"화제작 ‘듄’이 10월 개봉을 확정했다. ‘아바타’ 이후 가장 혁명적인 프로젝트이자 경이로움과 아름다움을 선사하는 역사적인 블록버스터의 탄생을 예고한다. 영화 ‘듄’은 생명 유지 자원인 스파이스를 두고 아라키스 모래 행성 ‘듄’에서 악의 세력과 전쟁을 앞둔, 전 우주의 왕좌에 오를 운명으로 태어난 전설의 메시아 폴의 위대한 여정을 그린 작품이다. 프랭크","link":"https://movie.v.daum.net/v/20210825084208715","retrieved":1629852425907,"image":"https://img1.daumcdn.net/thumb/S384x240/?fname=https%3A%2F%2Ft1.daumcdn.net%2Fnews%2F202108%2F25%2FiMBC%2F20210825084214472bhka.jpg"},{"title":"'아시안 히어로' 할리우드를 접수하다 (다음영화 뉴스 ─ 인기)","contents":"■ 美 영화에 부는 ‘아시안 파워’마블 새 히어로 무비 ‘샹치와…’주연 중국계 시무 리우 호평 11월 개봉하는 ‘이터널스’엔 제마 챈 · 마동석 큰 비중 맡아 박서준도 ‘캡틴마블 속편’ 캐스팅…‘아마데우스 조’役 예상 ‘화이트 워싱’ 잇단 비판 · ‘크레이지 리치 아시안’ 성공 힘입어 아시안계 배우, 비호감 이웃·빌런 등 변방서 중심으로 이동 미국 할리우드","link":"https://movie.v.daum.net/v/20210824101023732","retrieved":1629793086381,"image":"https://img1.daumcdn.net/thumb/S384x240/?fname=https%3A%2F%2Ft1.daumcdn.net%2Fnews%2F202108%2F24%2Fmunhwa%2F20210824101025575uxuc.jpg"},{"title":"디즈니 코로나 굴욕? 고질라에게도 밀린 '블랙 위도우' 어쩌다[무비와치] (다음영화 뉴스 ─ 인기)","contents":"[뉴스엔 허민녕 기자] 디즈니니까 ‘굴욕’이란 표현도 가능한 거다. 전세계가 코로나로 혼미한 틈을 타 중국이 지난 해에 이어 올해도 글로벌 박스오피스 1위를 ‘수성’할 기세다. 박스오피스 모조 기준 현재까지 전세계 관객동원 1위는 지난 설 연휴 중국에서 개봉됐던 영화 ‘니하오, 리환잉’(你好, 李焕英). 8억2,200만 달러 한화로 무려 9,588억원을","link":"https://movie.v.daum.net/v/20210824164425536","retrieved":1629852425913,"image":"https://img1.daumcdn.net/thumb/S384x240/?fname=https%3A%2F%2Ft1.daumcdn.net%2Fnews%2F202108%2F24%2Fnewsen%2F20210824164427057heil.jpg"},{"title":"'인질' 이유미, 황정민과 아슬아슬한 탈주..고밀도 열연 (다음영화 뉴스 ─ 인기)","contents":"[스타뉴스 김미화 기자] /사진=NEW'인질' 이유미가 밀도 높은 열연으로 관객을 사로잡았다. 지난 18일 베일을 벗은 영화 '인질'이 손에 땀을 쥐게 만드는 휘몰아치는 전개와 빈틈없는 열연 퍼레이드로 순항하고 있는 가운데, 황정민 보다 먼저 잡힌 첫번재 인질 역을 맡은 이유미가 고밀도의 현실감 넘치는 연기로 호평을 받고 있다. 이유미는 영화 '박화영',","link":"https://movie.v.daum.net/v/20210825080430881","retrieved":1629852425910,"image":"https://img1.daumcdn.net/thumb/S384x240/?fname=https%3A%2F%2Ft1.daumcdn.net%2Fnews%2F202108%2F25%2Fstarnews%2F20210825080432023xtmz.jpg"},{"title":"\"제작비 50% 먼저 지급\"..극장가 아름다운 '통 큰 양보' (다음영화 뉴스 ─ 인기)","contents":"영화 ‘모가디슈’ 한 장면. 사진제공｜롯데엔터테인먼트“백신의 빠른 보급과 맞물려 한국영화 개봉이 늘어나고 있는 만큼 관객의 더 큰 성원과 사랑을 기대한다.” 올해 6월 CJ CGV·롯데시네마·메가박스 등이 소속된 한국상영관협회가 내놓은 바람이다. 당시 한국상영관협회는 투자배급사와 극장 티켓 매출의 절반씩 나눠온 종전의 ‘부율’과 상관없이 ‘모가디슈’와 ‘","link":"https://movie.v.daum.net/v/20210825065720811","retrieved":1629852425912,"image":"https://img1.daumcdn.net/thumb/S384x240/?fname=https%3A%2F%2Ft1.daumcdn.net%2Fnews%2F202108%2F25%2Fsportsdonga%2F20210825065723051qnhu.jpg"},{"title":"히가시노 게이고 원작 '인어가 잠든 집', 10월7일 韓개봉..포스터 공개 [Oh!쎈 컷] (다음영화 뉴스 ─ 인기)","contents":"[OSEN=김보라 기자]&nbsp;히가시노 게이고 데뷔 30주년 기념 소설을 원작으로 한 영화 '인어가 잠든 집'이 오는 10월 개봉을 확정 짓고 메인 포스터를 전격 공개했다. 삶과 죽음에 관한 가장 뜨거운 물음을 던지는 영화 '인어가 잠든 집'이 10월 7일 국내 개봉을 전격 확정 짓고, 스토리를 향한 궁금증을 자극하는 메인 포스터를 공개했다. '인어가 잠든 집'","link":"https://movie.v.daum.net/v/20210825083823635","retrieved":1629856507514,"image":"https://img1.daumcdn.net/thumb/S384x240/?fname=https%3A%2F%2Ft1.daumcdn.net%2Fnews%2F202108%2F25%2Fpoctan%2F20210825083823099uyhc.jpg"},{"title":"'보이스' 이주영, '독전'·'삼진그룹 영어토익반' 이을 新 팔색조 매력 (다음영화 뉴스 ─ 인기)","contents":"(엑스포츠뉴스 김유진 기자) 배우 이주영이 영화 '보이스'(감독 김곡, 김선)의 깡칠 역으로 새로운 매력을 보여줄 예정이다. '보이스'는 보이스피싱 조직의 덫에 걸려 모든 것을 잃게 된 서준(변요한 분)이 빼앗긴 돈을 되찾기 위해 중국에 있는 본거지에 잠입, 보이스피싱 설계자 곽프로(김무열)를 만나며 벌어지는 이야기를 담은 영화다. 등장하는 작품마다 같은","link":"https://movie.v.daum.net/v/20210824173505375","retrieved":1629852425914,"image":"https://img1.daumcdn.net/thumb/S384x240/?fname=https%3A%2F%2Ft1.daumcdn.net%2Fnews%2F202108%2F24%2Fxportsnews%2F20210824173507329nlqe.jpg"},{"title":"호소다 마모루 신작 '용과 주근깨 공주', '겨울왕국' 韓애니메이터 김상진 참여 (다음영화 뉴스 ─ 인기)","contents":"[스포츠조선 이승미 기자]'시간을 달리는소녀' '늑대아이'등 전세계 영화 팬들의 마음을 사로잡아온 일본 애니메이션계 거장 호소다 마모루 감독의 신작 '용과 주근깨공주'에 김상진 애니메이터를 비롯해, 유명 글로벌 창작진이 '엘사 아빠'로 잘 알려진 김상진은 디즈니 최초의 한국인 애니메이터로 '겨울왕국' '모아나' '라푼젤' 등의 작품에서 캐릭터","link":"https://movie.v.daum.net/v/20210825084507794","retrieved":1629852425915,"image":"https://img1.daumcdn.net/thumb/S384x240/?fname=https%3A%2F%2Ft1.daumcdn.net%2Fnews%2F202108%2F25%2FSpoChosun%2F20210825084507619jlxj.jpg"},{"title":"스칼렛 요한슨, 디즈니 중재 요청 거절..법적 공방 본격 시작 (다음영화 뉴스 ─ 인기)","contents":"[스타뉴스 김미화 기자] 스칼렛 요한슨 /사진=/AFPBBNews=뉴스1 '블랙 위도우' 정산 문제로 디즈니와 소송을 진행 중인 스칼렛 요한슨이 디즈니 측의 중재 요청을 거절한 것으로 전해졌다. 21일(현지시간) 미국 데드라인은 스칼렛 요한슨이 디즈니 측의 중재안을 거절했다고 보도했다. 스칼렛 요한슨이 디즈니의 중재 요청을 거절하며 이 문제는 본격적인 법적","link":"https://movie.v.daum.net/v/20210824141539391","retrieved":1629793086394,"image":"https://img1.daumcdn.net/thumb/S384x240/?fname=https%3A%2F%2Ft1.daumcdn.net%2Fnews%2F202108%2F24%2Fstarnews%2F20210824141540670bhwh.jpg"},{"title":"[단독]주지훈 '킹덤: 세자전' 제작 보류..강윤성 감독 '카지노'로 선회 (다음영화 뉴스 ─ 인기)","contents":"[스타뉴스 전형화 기자] 주지훈 '킹덤' 스틸. 넷플릭스 '킹덤' 시리즈 외전으로 기획됐던 '킹덤: 세자전' 제작이 잠정 보류됐다. 25일 영화계에 따르면 올 하반기 촬영을 논의 중이었던 '킹덤: 세자전' 제작이 여러 이유로 잠정 보류됐다. '킹덤: 세자전'은 2019년 1월 시즌1이, 2020년 3월 시즌2가 공개돼 세계적으로 화제를 모았던 넷플릭스 오리","link":"https://movie.v.daum.net/v/20210825100337824","retrieved":1629856507521,"image":"https://img1.daumcdn.net/thumb/S384x240/?fname=https%3A%2F%2Ft1.daumcdn.net%2Fnews%2F202108%2F25%2Fstarnews%2F20210825100339125spbb.jpg"},{"title":"[영화 리뷰-올드] 30분에 1년씩 늙는다면 (다음영화 뉴스 ─ 인기)","contents":"[서울경제] 사람들에게 잘 알려지지 않은 고급 리조트가 있다. 느긋한 음악, 맛있는 음식, 친절한 직원. 모든 게 완벽하다. 엄마, 아빠와 함께 휴가 여행을 온 아이들의 마음에도 쏙 드는 곳이다. 하지만 이들 가족은 겉보기와 달리 위태롭다. 부부는 이혼을 앞두고 있다. 애써 숨기려는 긴장된 분위기를 리조트 지배인이 눈치챈 걸까. 이들 가족에게 특별한 액티","link":"https://movie.v.daum.net/v/20210824123940991","retrieved":1629856507522,"image":"https://img1.daumcdn.net/thumb/S384x240/?fname=https%3A%2F%2Ft1.daumcdn.net%2Fnews%2F202108%2F24%2Fseouleconomy%2F20210824123945073hhzf.jpg"},{"title":"휴 잭맨 끄는 '화차', 왜 약하지? [편파적인 씨네리뷰] (다음영화 뉴스 ─ 인기)","contents":"[스포츠경향] ■편파적인 한줄평 : 힘 없는 캐릭터, 화력 센 세계관도 못 살리네할리우드판 ‘화차’인데 화력이 좀처럼 거세지질 않는다. 휴 잭맨과 디스토피아, 팜므파탈 등 에너지 강한 ‘요소’들이 결합했지만 어쩐지 그 여운은 얕다. 독특한 세계관에 묻힌 영화 ‘레미니센스’(감독 리사 조이)다.‘레미니센스’는 바다에 절반이 잠긴 미래도시에서 기억을 보여주는","link":"https://movie.v.daum.net/v/20210824072201611","retrieved":1629796552070,"image":"https://img1.daumcdn.net/thumb/S384x240/?fname=https%3A%2F%2Ft1.daumcdn.net%2Fnews%2F202108%2F24%2Fsportskhan%2F20210824072203280irbt.jpg"},{"title":"얼굴 천재에 연기 천재까지.. '여심 방화범'의 원조 (다음영화 뉴스 ─ 인기)","contents":"[양형석 기자] 방한할 때마다 팬서비스가 워낙 좋아 한국팬들에게 '친절한 톰 아저씨'로 불리는 배우 톰 크루즈는 &lt;7월 4일생&gt;과 &lt;제리 맥과이어&gt;로 두 번이나 아카데미 시상식 남우주연상 후보에 오른 배우다. 만약 톰 크루즈가 젊은 시절처럼 아카데미 수상을 노리는 영화를 위주로 활동을 이어갔다면 커리어에서 한두 번 정도는 아카데미 남우주연상이라는 타이틀을","link":"https://movie.v.daum.net/v/20210824101202808","retrieved":1629793086401,"image":"https://img1.daumcdn.net/thumb/S384x240/?fname=https%3A%2F%2Ft1.daumcdn.net%2Fnews%2F202108%2F24%2Fohmynews%2F20210824101203363gcza.jpg"},{"title":"'습도 다소 높음' 이희준, 단발머리로 시선 강탈 (다음영화 뉴스 ─ 인기)","contents":"(엑스포츠뉴스 이서은 인턴기자) '습도 다소 높음'의 이희준이 '시동' 마동석을 이을 단발머리를 선보인다. '습도 다소 높음'은 극한의 습도가 엄습해온 어느 여름날, 에어컨을 꺼버린 극장에서 벌어지는 현실공감 땀생개방 코미디.&nbsp; 극 중 이희준은 자아도취에 빠진 나르시시스트 C급 영화감독으로 분해 코믹 연기를 선보인다. 무엇보다 그는 '시동' 마동석과 '인","link":"https://movie.v.daum.net/v/20210824121539518","retrieved":1629793086399,"image":"https://img1.daumcdn.net/thumb/S384x240/?fname=https%3A%2F%2Ft1.daumcdn.net%2Fnews%2F202108%2F24%2Fxportsnews%2F20210824121541126bexi.jpg"},{"title":"'말리그넌트' 제임스 완 감독 \"'겨울왕국' 공포 버전\"..多장르 호러 9월 개봉[공식] (다음영화 뉴스 ─ 인기)","contents":"[OSEN=김보라 기자]&nbsp;제임스 완 감독이 9월 개봉을 앞둔 영화 ‘말리그넌트’로 자신만의 새로운 비전을 제시한다. ‘말리그넌트’(감독 제임스 완, 수입배급 워너브러더스 코리아)는 폭력 남편의 죽음 이후, 연쇄 살인 현장에 초대된 매디슨 앞에 어릴 적 상상 속의 친구 가브리엘이 진짜로 나타나면서 벌어지는 의문의 사건을 다룬다. 제임스 완 감독은 ‘말리그넌트","link":"https://movie.v.daum.net/v/20210825085719150","retrieved":1629861370247,"image":"https://img1.daumcdn.net/thumb/S384x240/?fname=https%3A%2F%2Ft1.daumcdn.net%2Fnews%2F202108%2F25%2Fpoctan%2F20210825085720647vajw.jpg"},{"title":"[박스오피스IS] 황정민 '인질', 일주일째 굳건한 1위..74만 관객 돌파 (다음영화 뉴스 ─ 인기)","contents":"영화 '인질(필감성 감독)'이 일주일 연속 박스오피스 1위에 올랐다. 영화진흥위원회 영화관입장권통합전산망에 따르면, '인질'은 지난 24일 4만 9965명의 관객을 동원했다. 누적 관객수는 74만 1624명이다. 지난 18일 개봉해 7일 연속 박스오피스 1위 자리를 놓치지 않고 있다. 개봉 2주차에도 흥행세를 이어갈 것으로 보인다. '인질'은 어","link":"https://movie.v.daum.net/v/20210825071333070","retrieved":1629865186671,"image":"https://img1.daumcdn.net/thumb/S384x240/?fname=https%3A%2F%2Ft1.daumcdn.net%2Fnews%2F202108%2F25%2Filgansports%2F20210825071334998omzd.jpg"},{"title":"넷플릭스 \"주지훈 '킹덤:세자전' 제작 보류? 애초에 정해진 바 없어\"[공식] (다음영화 뉴스 ─ 인기)","contents":"넷플릭스 '킹덤' 시리즈 외전으로 논의 중이던 '킹덤: 세자전'의 제작이 잠정 보류됐다는 보도가 나온 가운데 넷플릭스 측이 “애초에 구체적으로 정해진 바가 없었다”고 일축했다. 25일 한 매체는 올 하반기 촬영을 논의 중이었던 '킹덤: 세자전' 제작이 다양한 이유로 잠정 보류됐다고 보도했다. 앞서 '킹덤' 시리즈 주인공인 세자 이창(주지훈)를 주인공으로","link":"https://movie.v.daum.net/v/20210825104514742","retrieved":1629858316441,"image":"https://img1.daumcdn.net/thumb/S384x240/?fname=https%3A%2F%2Ft1.daumcdn.net%2Fnews%2F202108%2F25%2Fstartoday%2F20210825104515288mjks.png"},{"title":"'D.P.' 軍서 뭉친 정해인X구교환, 탈영병 잡으러 출동 [종합] (다음영화 뉴스 ─ 최신)","contents":"[스타뉴스 김미화 기자] 배우 정해인, 구교환, 김성균, 손석구가 25일 오전 온라인으로 진행된 넷플릭스 오리지널 'D.P' 제작발표회에 참석해 포즈를 취하고 있다.  'D.P.'는 탈영병들을 잡는 군무 이탈 체포조(D.P.) 준호(정해인 분)와 호열(구교환 분)이 다양한 사연을 가진 이들을 쫓으며 미처 알지 못했던 현실을 마주하는 이야기를 그린 넷플릭스","link":"https://v.daum.net/v/20210825125502830","retrieved":1629865194150,"image":"https://img1.daumcdn.net/thumb/S384x240/?fname=https%3A%2F%2Ft1.daumcdn.net%2Fnews%2F202108%2F25%2Fstarnews%2F20210825125505458xcha.jpg"},{"title":"넷플릭스 '지옥' 부국제서 본다..亞최초 'OTT 섹션' 신설 (다음영화 뉴스 ─ 최신)","contents":"부산국제영화제가 OTT 작품을 품는다. 제26회 부산국제영화제(BIFF·이하 부국제)가 '온 스크린' 섹션 신설을 공식화 했다. 온 스크린은 온라인 동영상 스트리밍 플랫폼(Over the Top, 이하 OTT)에서 방영될 화제의 드라마 시리즈를 상영하는 섹션으로 '아시아 최초' 신설됐다. 온 스크린 섹션에서는 OTT 드라마 시리즈 화제작을 월드 프","link":"https://v.daum.net/v/20210825124734652","retrieved":1629865194153,"image":"https://img1.daumcdn.net/thumb/S384x240/?fname=https%3A%2F%2Ft1.daumcdn.net%2Fnews%2F202108%2F25%2Filgansports%2F20210825124738208ldlg.jpg"},{"title":"\"탈영병 잡는 군인\"..'D.P.' 정해인·구교환이 출격한다 [스경X현장] (다음영화 뉴스 ─ 최신)","contents":"[스포츠경향] “‘D.P.’는 사복헌병입니다. 부대 밖에서 생활하는 D.P.조가 탈영병을 잡기 위해 활동하는 모습을 담는데요. 탈영병들의 사연, 그 사연들을 쫓으면서 무언가를 깨닫고 성장해나가는 두 인물을 그린 이야기에요.”(한준희 감독)군인 잡는 군인들이 온다. 탈영병들을 잡는 군무 이탈 체포조(D.P.) 준호와 호열이 다양한 사연을 가진 이들을 쫓으며","link":"https://v.daum.net/v/20210825123230461","retrieved":1629865194158,"image":"https://img1.daumcdn.net/thumb/S384x240/?fname=https%3A%2F%2Ft1.daumcdn.net%2Fnews%2F202108%2F25%2Fsportskhan%2F20210825123231998dlmc.jpg"},{"title":"'D.P.' 구교환 \"정해인에 1일 데이트권 주고 싶다\" (다음영화 뉴스 ─ 최신)","contents":"[스포츠경향] 배우 구교환이 정해인에 대한 애정을 표현했다.구교환은 25일 오전 온라인생중계된 넷플릭스 새 시리즈 ‘D.P.’ 제작발표회에서 “정해인에게 나와 1일 데이트권을 주고 싶다”고 밝혀 웃음을 자아냈다.그는 “뭔가 물리적인 것보다 정해인 안으로 들어가고 싶은 마음을 주고 싶었다. 그런데 쑥쓰럽다”며 이번 작품 속 브로맨스를 예고했다.이어 “데이트","link":"https://v.daum.net/v/20210825121406045","retrieved":1629861378642,"image":"https://img1.daumcdn.net/thumb/S384x240/?fname=https%3A%2F%2Ft1.daumcdn.net%2Fnews%2F202108%2F25%2Fsportskhan%2F20210825121407355bhba.jpg"},{"title":"'D.P.' 정해인 \"구교환 애드리브, 행복한 고통이었다\" (다음영화 뉴스 ─ 최신)","contents":"[스타뉴스 김미화 기자] 배우 정해인, 구교환이 25일 오전 온라인으로 진행된 넷플릭스 오리지널 'D.P' 제작발표회에 참석해 포즈를 취하고 있다.  'D.P.'는 탈영병들을 잡는 군무 이탈 체포조(D.P.) 준호(정해인 분)와 호열(구교환 분)이 다양한 사연을 가진 이들을 쫓으며 미처 알지 못했던 현실을 마주하는 이야기를 그린 넷플릭스 시리즈.다. 오는","link":"https://v.daum.net/v/20210825121141989","retrieved":1629861378643,"image":"https://img1.daumcdn.net/thumb/S384x240/?fname=https%3A%2F%2Ft1.daumcdn.net%2Fnews%2F202108%2F25%2Fstarnews%2F20210825121142945lmbo.jpg"},{"title":"'D.P.' 손석구 \"정해인·구교환 호흡 기대돼..조합 궁금\" (다음영화 뉴스 ─ 최신)","contents":"[스포츠조선 문지연 기자] 배우 손석구가 정해인과 구교환의 호흡에 기대감을 전했다. 25일 오전 넷플릭스는 새 오리지널 시리즈 'D.P.'(김보통 한준희 극본, 한준희 연출, 이하 디피)의 제작발표회를 신종 코로나바이러스 감염증(코로나19) 확산 방지를 위한 온라인 생중계로 진행했다. 행사에는 정해인, 구교환, 김성균, 손석구, 한준희 감독","link":"https://v.daum.net/v/20210825120843886","retrieved":1629861378646,"image":"https://img1.daumcdn.net/thumb/S384x240/?fname=https%3A%2F%2Ft1.daumcdn.net%2Fnews%2F202108%2F25%2FSpoChosun%2F20210825120843939yfzg.jpg"},{"title":"'D.P.' 정해인 \"세트장, 실제 군대 같아서 소름\" (다음영화 뉴스 ─ 최신)","contents":"[스포츠경향] 배우 정해인이 넷플릭스 새 시리즈 ‘D.P.’의 리얼리티를 보장했다.정해인은 25일 오전 온라인생중계된 ‘D.P.’ 제작발표회에서 “제작진이 세트장을 정말 군대처럼 극사실주의로 만들어서 소름이 돋았다”고 밝혔다.그는 “그때서야 실감이 났고, 재입대하는 느낌이 들어 아찔했다”며 “너무 긴장돼 실제 이름으로 관등성명을 대는 등 NG가 나기도 했","link":"https://v.daum.net/v/20210825120636835","retrieved":1629861378646,"image":"https://img1.daumcdn.net/thumb/S384x240/?fname=https%3A%2F%2Ft1.daumcdn.net%2Fnews%2F202108%2F25%2Fsportskhan%2F20210825120637233dvbm.jpg"},{"title":"티아라 지연, 영화 '화녀' 주인공..오랜만에 스크린 복귀 [공식] (다음영화 뉴스 ─ 최신)","contents":"[마이데일리 = 양유진 기자] 그룹 티아라 멤버 겸 배우 지연이 영화 '화녀' 주인공으로 발탁되며 오랜만에 스크린으로 복귀한다. 영화 '화녀'는 스릴러물의 장편 상업영화로, 지연은 극중 유명 배우의 삶을 살다 한 순간의 실수로 위기를 겪고 난 후 다시 배우로서의 재기를 꿈꾸는 여주인공 이수연 역을 맡았다. '화녀'는 촉망받던 배우와 그녀의 팬, 그리고","link":"https://v.daum.net/v/20210825120322719","retrieved":1629861378649,"image":"https://img1.daumcdn.net/thumb/S384x240/?fname=https%3A%2F%2Ft1.daumcdn.net%2Fnews%2F202108%2F25%2Fmydaily%2F20210825120322818mndc.jpg"},{"title":"정해인X구교환 찐 브로의 뜨거운 'D.P.'[종합] (다음영화 뉴스 ─ 최신)","contents":"리얼하고도 신선한 청춘 이야기가 온다. 김성균 정해인 구교환 손석구가 뭉친 영화 'D.P'(감독 한준희)다. 25일 오전 온라인으로 넷플릭스 오리지널 시리즈 'D.P.' 제작발표회가 열렸다. 먼저 메가폰을 잡은 한준희 감독은 “첫 작품 만든 뒤 긴 시간 동안 정말 하고 싶었던 이야기였다. 거의 5~6년 동안 이 원작을 맡고 싶었는데 기회가 닿았다\"고 운을","link":"https://v.daum.net/v/20210825115702349","retrieved":1629861378650,"image":"https://img1.daumcdn.net/thumb/S384x240/?fname=https%3A%2F%2Ft1.daumcdn.net%2Fnews%2F202108%2F25%2Fstartoday%2F20210825115707501ovcw.jpg"},{"title":"'D.P.' 구교환 \"대본, 러브레터 같아\"·정해인 \"만화책 보듯 읽었다\" (다음영화 뉴스 ─ 최신)","contents":"[스포츠조선 문지연 기자] 배우 구교환과 정해인이 대본을 읽은 소감을 밝혔다. 25일 오전 넷플릭스는 새 오리지널 시리즈 'D.P.'(김보통 한준희 극본, 한준희 연출, 이하 디피)의 제작발표회를 신종 코로나바이러스 감염증(코로나19) 확산 방지를 위한 온라인 생중계로 진행했다. 행사에는 정해인, 구교환, 김성균, 손석구, 한준희 감독이 참","link":"https://v.daum.net/v/20210825114833129","retrieved":1629861378651,"image":"https://img1.daumcdn.net/thumb/S384x240/?fname=https%3A%2F%2Ft1.daumcdn.net%2Fnews%2F202108%2F25%2FSpoChosun%2F20210825114833954zwkt.jpg"},{"title":"'D.P.' 정해인 \"작품 위해 3개월 복싱 연습..대역 없이 촬영\" (다음영화 뉴스 ─ 최신)","contents":"[스타뉴스 김미화 기자] 배우 정해인이 25일 오전 온라인으로 진행된 넷플릭스 오리지널 'D.P' 제작발표회에 참석해 포즈를 취하고 있다.  'D.P.'는 탈영병들을 잡는 군무 이탈 체포조(D.P.) 준호(정해인 분)와 호열(구교환 분)이 다양한 사연을 가진 이들을 쫓으며 미처 알지 못했던 현실을 마주하는 이야기를 그린 넷플릭스 시리즈.다. 오는 27일 공","link":"https://v.daum.net/v/20210825114801095","retrieved":1629861378653,"image":"https://img1.daumcdn.net/thumb/S384x240/?fname=https%3A%2F%2Ft1.daumcdn.net%2Fnews%2F202108%2F25%2Fstarnews%2F20210825114802744wgls.jpg"},{"title":"'D.P.' 정해인 \"리얼한 내무반 세트..재입대 한 느낌\" (다음영화 뉴스 ─ 최신)","contents":"[스타뉴스 김미화 기자] 배우 정해인이 25일 오전 온라인으로 진행된 넷플릭스 오리지널 'D.P' 제작발표회에 참석해 포즈를 취하고 있다.  'D.P.'는 탈영병들을 잡는 군무 이탈 체포조(D.P.) 준호(정해인 분)와 호열(구교환 분)이 다양한 사연을 가진 이들을 쫓으며 미처 알지 못했던 현실을 마주하는 이야기를 그린 넷플릭스 시리즈.다. 오는 27일 공","link":"https://v.daum.net/v/20210825114718069","retrieved":1629861378654,"image":"https://img1.daumcdn.net/thumb/S384x240/?fname=https%3A%2F%2Ft1.daumcdn.net%2Fnews%2F202108%2F25%2Fstarnews%2F20210825114719853zaqd.jpg"},{"title":"'D.P.' 정해인 \"대역 없이 복싱 장면 소화..3개월간 땀흘리며 연습\" (다음영화 뉴스 ─ 최신)","contents":"[스포츠조선 문지연 기자] 배우 정해인이 복싱 연기를 대역 없이 해냈다고 말했다. 25일 오전 넷플릭스는 새 오리지널 시리즈 'D.P.'(김보통 한준희 극본, 한준희 연출, 이하 디피)의 제작발표회를 신종 코로나바이러스 감염증(코로나19) 확산 방지를 위한 온라인 생중계로 진행했다. 행사에는 정해인, 구교환, 김성균, 손석구, 한준희 감독이","link":"https://v.daum.net/v/20210825114653054","retrieved":1629861378657,"image":"https://img1.daumcdn.net/thumb/S384x240/?fname=https%3A%2F%2Ft1.daumcdn.net%2Fnews%2F202108%2F25%2FSpoChosun%2F20210825114653604ezcb.jpg"},{"title":"'D.P.' 정해인 \"구교환 애드리브 기가 막힐 정도..촬영하기 어려웠다\" (다음영화 뉴스 ─ 최신)","contents":"‘D.P.’ 정해인이 구교환의 애드리브에 대해 언급했다. 25일 오전 넷플릭스 ‘D.P.’ 제작발표회가 코로나19 확산 방지를 위해 온라인으로 생중계됐다. 이날 한준희 감독을 비롯해 배우 정해인, 구교환, 김성균, 손석구 등이 자리에 참석했다. 정해인은 “구교환의 애드리브에 고통 받았다고 하던데”라는 사회자의 질문에 “고통인데 행복한 고통이었다”라고 말했다","link":"https://v.daum.net/v/20210825114506993","retrieved":1629861378657,"image":"https://img1.daumcdn.net/thumb/S384x240/?fname=https%3A%2F%2Ft1.daumcdn.net%2Fnews%2F202108%2F25%2Fmksports%2F20210825114513538gunx.jpg"},{"title":"유아인x박정민 '지옥'-한소희 '마이 네임', 부국제 '온 스크린' 공개[공식] (다음영화 뉴스 ─ 최신)","contents":"[OSEN=김보라 기자] 올 10월 열리는 제26회 부산국제영화제(BIFF)가 '온 스크린' 섹션을 신설한다. 온 스크린은 온라인 동영상 스트리밍 플랫폼(OTT)에서 방송될 드라마 시리즈를 상영하는 섹션으로 아시아 최초로 신설됐다. 부산국제영화제(BIFF) 측은 25일 \"온 스크린 섹션에서는 OTT 드라마 시리즈 화제작을 월드 프리미어 혹은 아시아 프리미어","link":"https://v.daum.net/v/20210825114347933","retrieved":1629861378658,"image":"https://img1.daumcdn.net/thumb/S384x240/?fname=https%3A%2F%2Ft1.daumcdn.net%2Fnews%2F202108%2F25%2Fpoctan%2F20210825114347756ueyp.jpg"},{"title":"'D.P.' 감독 \"6년의 기다림..20대 청년 공감 원했다\" (다음영화 뉴스 ─ 최신)","contents":"한준희 감독이 청춘에 대한 애정을 드러내며 넷플릭스 ‘D.P.’를 시리즈로 연출하게 된 소감을 밝혔다. 한준희 감독은 25일 오전 온라인으로 진행된 넷플릭스 오리지널 시리즈 'D.P.' 제작발표회에서 “첫 작품 만든 뒤 긴 시간 동안 정말 하고 싶었던 이야기였다. 거의 5~6년 동안 이 원작을 맡고 싶었는데 기회가 닿았다\"고 운을 뗐다. 이어 \"가장 중요","link":"https://v.daum.net/v/20210825114215880","retrieved":1629861378660,"image":"https://img1.daumcdn.net/thumb/S384x240/?fname=https%3A%2F%2Ft1.daumcdn.net%2Fnews%2F202108%2F25%2Fstartoday%2F20210825114217080ddkt.jpg"},{"title":"'D.P.' 손석구 \"정해인·구교환의 열혈한 팬\" (다음영화 뉴스 ─ 최신)","contents":"‘D.P.’ 손석구가 정해인, 구교환 팬임을 밝혔다. 25일 오전 넷플릭스 ‘D.P.’ 제작발표회가 코로나19 확산 방지를 위해 온라인으로 생중계됐다. 이날 한준희 감독을 비롯해 배우 정해인, 구교환, 김성균, 손석구 등이 자리에 참석했다. 손석구는 ‘정해인, 구교환 조합 때문에 출연했다는 소문이 있다’라는 말에 “맞다”라고 말문을 열었다. 이어 “저는","link":"https://v.daum.net/v/20210825113909714","retrieved":1629861378661,"image":"https://img1.daumcdn.net/thumb/S384x240/?fname=https%3A%2F%2Ft1.daumcdn.net%2Fnews%2F202108%2F25%2Fmksports%2F20210825113911028bsan.jpg"},{"title":"'매트릭스4' 부제는 '레저렉션(부활)'..키아누 리브스 \"내가 미쳤나?\" [Oh!llywood] (다음영화 뉴스 ─ 최신)","contents":"[OSEN=최나영 기자]&nbsp;18년 만에 돌아오는 '매트릭스4'의 정식 타이틀이 공개됐다. 바로 '레저렉션'(Resurrection, 부활). 워너 브라더스가 24일(현지시간) 진행된&nbsp;시네마 콘퍼런스에서 '매트릭스' 4의 예고편을 대대적으로 공개했다. 더불어 매트릭스: 부활'이라는 공식 타이틀(부제)도&nbsp;선보였다.&nbsp; '매트릭스'는 매 시리즈마다 're'로 시작하","link":"https://v.daum.net/v/20210825112809107","retrieved":1629861378662,"image":"https://img1.daumcdn.net/thumb/S384x240/?fname=https%3A%2F%2Ft1.daumcdn.net%2Fnews%2F202108%2F25%2Fpoctan%2F20210825112809473tbrv.jpg"},{"title":"'D.P.' 정해인 \"너무 리얼한 내무반 세트..재입대한 줄\" (다음영화 뉴스 ─ 최신)","contents":"배우 정해인이 'D.P.'(디피) 촬영 에피소드를 전했다. 정해인은 25일 오전 온라인으로 진행된 넷플릭스 오리지널 시리즈 'D.P.' 제작발표회에서 \"내무반 세트장이 너무 극사실주의여서 깜짝 놀랐다\"고 운을 뗐다. 그는 \"정말 리얼하게 재현해내서 소름 돋았다. 내무반에 들어가니 아찔한 실감이 나더라. 재입대한 듯한 기분이었다\"고 말했다. 이어 \"실제 테","link":"https://v.daum.net/v/20210825112706030","retrieved":1629861378665,"image":"https://img1.daumcdn.net/thumb/S384x240/?fname=https%3A%2F%2Ft1.daumcdn.net%2Fnews%2F202108%2F25%2Fstartoday%2F20210825112709521sywf.jpg"},{"title":"'D.P.' 정해인 \"내무반 세트 리얼해..소름돋고 아찔한 실감\" (다음영화 뉴스 ─ 최신)","contents":"[스포츠조선 문지연 기자] 배우 정해인이 리얼한 세트장에 대해 언급했다. 25일 오전 넷플릭스는 새 오리지널 시리즈 'D.P.'(김보통 한준희 극본, 한준희 연출, 이하 디피)의 제작발표회를 신종 코로나바이러스 감염증(코로나19) 확산 방지를 위한 온라인 생중계로 진행했다. 행사에는 정해인, 구교환, 김성균, 손석구, 한준희 감독이 참석했다","link":"https://v.daum.net/v/20210825111018082","retrieved":1629858323771,"image":"https://img1.daumcdn.net/thumb/S384x240/?fname=https%3A%2F%2Ft1.daumcdn.net%2Fnews%2F202108%2F25%2FSpoChosun%2F20210825111018358yefe.jpg"},{"title":"<듄> 메인 예고편 (우리 영화 볼래?)","contents":"<em class=\"screen_out\">재생시간 : </em>03:27","link":"https://tv.kakao.com/channel/462787/cliplink/421791147?act=clip","retrieved":1629865206773,"image":"https://t1.daumcdn.net/thumb/C320x180.fjpg.q75/?fname=https%3A%2F%2Fthumb.kakaocdn.net%2Fdna%2Fkamp%2Fsource%2Frvuqlyg74iw5808ibhcj0vc1q%2Fthumbs%2Fthumb.jpg%3Fcredential%3DTuMuFGKUIcirOSjFzOpncbomGFEIdZWK%26expires%3D33186771062%26signature%3DLj%252BnoZ5LUYeE7YkUPIofmO%252FlA%252BQ%253D%26ts%3D1629862262"},{"title":"<이터널스> 메인 예고편 (우리 영화 볼래?)","contents":"<em class=\"screen_out\">재생시간 : </em>02:50","link":"https://tv.kakao.com/channel/462787/cliplink/421788141?act=clip","retrieved":1629856524476,"image":"https://t1.daumcdn.net/thumb/C320x180.fjpg.q75/?fname=https%3A%2F%2Fthumb.kakaocdn.net%2Fdna%2Fkamp%2Fsource%2Frv93vri3idsoumr0yow794vrm%2Fthumbs%2Fthumb.jpg%3Fcredential%3DTuMuFGKUIcirOSjFzOpncbomGFEIdZWK%26expires%3D33186763256%26signature%3DHPtVrtTZQMnuvuiq8yrhOLJdYqE%253D%26ts%3D1629854456"},{"title":"<말리그넌트> 30초 예고편 (우리 영화 볼래?)","contents":"<em class=\"screen_out\">재생시간 : </em>00:30","link":"https://tv.kakao.com/channel/462787/cliplink/421788085?act=clip","retrieved":1629856524476,"image":"https://t1.daumcdn.net/thumb/C320x180.fjpg.q75/?fname=http%3A%2F%2Fthumb.kakaocdn.net%2Fdna%2Fkamp%2Fsource%2Frvg3mg2uem6ldj0qp3ycbeazq%2Fthumbs%2Fthumb.jpg%3Fcredential%3DTuMuFGKUIcirOSjFzOpncbomGFEIdZWK%26expires%3D33186763058%26signature%3DAF%252F%252B59anV%252FwW6%252BrUbgWv%252FJoWYko%253D"},{"title":"<캔디맨> 캔디맨 소환영상 1탄 (우리 영화 볼래?)","contents":"<em class=\"screen_out\">재생시간 : </em>00:39","link":"https://tv.kakao.com/channel/462787/cliplink/421788036?act=clip","retrieved":1629856524479,"image":"https://t1.daumcdn.net/thumb/C320x180.fjpg.q75/?fname=http%3A%2F%2Fthumb.kakaocdn.net%2Fdna%2Fkamp%2Fsource%2Frvgde4mt000k9x2w1xfsj2vyc%2Fthumbs%2Fthumb.jpg%3Fcredential%3DTuMuFGKUIcirOSjFzOpncbomGFEIdZWK%26expires%3D33186762912%26signature%3DLygls1YIVx3t5a%252FqE7AeM1w05sc%253D"},{"title":"<타다: 대한민국 스타트업의 초상> 1차 티저 예고편 (우리 영화 볼래?)","contents":"<em class=\"screen_out\">재생시간 : </em>01:00","link":"https://tv.kakao.com/channel/462787/cliplink/421787961?act=clip","retrieved":1629856524483,"image":"https://t1.daumcdn.net/thumb/C320x180.fjpg.q75/?fname=http%3A%2F%2Fimg1.daumcdn.net%2Fkakaotv%2FKAKAOACCOUNT%2F1443873045%2Fthumb%2F20210825101247"},{"title":"<용과 주근깨 공주> 티저 예고편 (우리 영화 볼래?)","contents":"<em class=\"screen_out\">재생시간 : </em>00:48","link":"https://tv.kakao.com/channel/462787/cliplink/421768431?act=clip","retrieved":1629789344738,"image":"https://t1.daumcdn.net/thumb/C320x180.fjpg.q75/?fname=https%3A%2F%2Fthumb.kakaocdn.net%2Fdna%2Fkamp%2Fsource%2Frvee2oh76vkotg77tx8vnp20o%2Fthumbs%2Fthumb.jpg%3Fcredential%3DTuMuFGKUIcirOSjFzOpncbomGFEIdZWK%26expires%3D33186697212%26signature%3Dsn0QzgFIzLuLJfqMGlj2b2CfNJA%253D%26ts%3D1629788412"},{"title":"<극장판 포켓몬스터: 정글의 아이, 코코> 메인 예고편 (우리 영화 볼래?)","contents":"<em class=\"screen_out\">재생시간 : </em>01:30","link":"https://tv.kakao.com/channel/462787/cliplink/421765043?act=clip","retrieved":1629782018701,"image":"https://t1.daumcdn.net/thumb/C320x180.fjpg.q75/?fname=https%3A%2F%2Fthumb.kakaocdn.net%2Fdna%2Fkamp%2Fsource%2Frv7ewzmgf5wrd8oqs6bxanqqf%2Fthumbs%2Fthumb.jpg%3Fcredential%3DTuMuFGKUIcirOSjFzOpncbomGFEIdZWK%26expires%3D33186690171%26signature%3DcwWKqnA23fkCjd6f6mjK%252BJKKw1A%253D%26ts%3D1629781371"},{"title":"<맨 인 더 다크 2> 30초 예고편 (우리 영화 볼래?)","contents":"<em class=\"screen_out\">재생시간 : </em>00:30","link":"https://tv.kakao.com/channel/462787/cliplink/421763130?act=clip","retrieved":1629778813460,"image":"https://t1.daumcdn.net/thumb/C320x180.fjpg.q75/?fname=https%3A%2F%2Fthumb.kakaocdn.net%2Fdna%2Fkamp%2Fsource%2Frvzhiey8558o26d0hp334csfl%2Fthumbs%2Fthumb.jpg%3Fcredential%3DTuMuFGKUIcirOSjFzOpncbomGFEIdZWK%26expires%3D33186685877%26signature%3D3Ur7YEK6NmK4VVTecvZeNQcaVCw%253D%26ts%3D1629777077"},{"title":"<남색대문> 엔딩 명장면 (우리 영화 볼래?)","contents":"<em class=\"screen_out\">재생시간 : </em>01:00","link":"https://tv.kakao.com/channel/462787/cliplink/421762532?act=clip","retrieved":1629778813467,"image":"https://t1.daumcdn.net/thumb/C320x180.fjpg.q75/?fname=https%3A%2F%2Fthumb.kakaocdn.net%2Fdna%2Fkamp%2Fsource%2Frv2ue6g25radm881vpw1mxtnz%2Fthumbs%2Fthumb.jpg%3Fcredential%3DTuMuFGKUIcirOSjFzOpncbomGFEIdZWK%26expires%3D33186684516%26signature%3Dq1lggd5dJmm2BUk4IElgNrxWfVA%253D%26ts%3D1629775716"},{"title":"<좋은 사람> 30초 예고편 (우리 영화 볼래?)","contents":"<em class=\"screen_out\">재생시간 : </em>00:30","link":"https://tv.kakao.com/channel/462787/cliplink/421762465?act=clip","retrieved":1629778813468,"image":"https://t1.daumcdn.net/thumb/C320x180.fjpg.q75/?fname=http%3A%2F%2Fthumb.kakaocdn.net%2Fdna%2Fkamp%2Fsource%2Frvl461pxgxwmze2ul6tcui3l9%2Fthumbs%2Fthumb.jpg%3Fcredential%3DTuMuFGKUIcirOSjFzOpncbomGFEIdZWK%26expires%3D33186684340%26signature%3DRh0VsDb2fiMZ8qWEiKuA6b8c92Q%253D"},{"title":"<꿈꾸는 고양이> 메인 예고편 (우리 영화 볼래?)","contents":"<em class=\"screen_out\">재생시간 : </em>00:56","link":"https://tv.kakao.com/channel/462787/cliplink/421760798?act=clip","retrieved":1629771857101,"image":"https://t1.daumcdn.net/thumb/C320x180.fjpg.q75/?fname=https%3A%2F%2Fthumb.kakaocdn.net%2Fdna%2Fkamp%2Fsource%2Frvzde57lgk8ieb9m1xw70kgsx%2Fthumbs%2Fthumb.jpg%3Fcredential%3DTuMuFGKUIcirOSjFzOpncbomGFEIdZWK%26expires%3D33186679781%26signature%3DPF9JrHvXY5e83E%252By26LhlLxOufU%253D%26ts%3D1629770981"},{"title":"<어시스턴트> 30초 예고편 (우리 영화 볼래?)","contents":"<em class=\"screen_out\">재생시간 : </em>00:30","link":"https://tv.kakao.com/channel/462787/cliplink/421760497?act=clip","retrieved":1629771857103,"image":"https://t1.daumcdn.net/thumb/C320x180.fjpg.q75/?fname=https%3A%2F%2Fthumb.kakaocdn.net%2Fdna%2Fkamp%2Fsource%2Frv5f1qi9lxf5uz8krc4zavmvc%2Fthumbs%2Fthumb.jpg%3Fcredential%3DTuMuFGKUIcirOSjFzOpncbomGFEIdZWK%26expires%3D33186679489%26signature%3DfwgEFTJzWyOD7L1%252FrSJ4ar2Bmz8%253D%26ts%3D1629770689"},{"title":"<내가 날 부를 때> 30초 예고편 (우리 영화 볼래?)","contents":"<em class=\"screen_out\">재생시간 : </em>00:30","link":"https://tv.kakao.com/channel/462787/cliplink/421739628?act=clip","retrieved":1629706677811,"image":"https://t1.daumcdn.net/thumb/C320x180.fjpg.q75/?fname=http%3A%2F%2Fthumb.kakaocdn.net%2Fdna%2Fkamp%2Fsource%2Frvhaa5g9xw6boczntmdj7rxt3%2Fthumbs%2Fthumb.jpg%3Fcredential%3DTuMuFGKUIcirOSjFzOpncbomGFEIdZWK%26expires%3D33186611934%26signature%3D1OiS015dxYmgOOmwnPTg%252B4XPAPs%253D"},{"title":"<내가 날 부를 때> 메인 예고편 (우리 영화 볼래?)","contents":"<em class=\"screen_out\">재생시간 : </em>01:27","link":"https://tv.kakao.com/channel/462787/cliplink/421739505?act=clip","retrieved":1629706677812,"image":"https://t1.daumcdn.net/thumb/C320x180.fjpg.q75/?fname=https%3A%2F%2Fthumb.kakaocdn.net%2Fdna%2Fkamp%2Fsource%2Frvbo0ka1c8zvjt0rmnggpsul8%2Fthumbs%2Fthumb.jpg%3Fcredential%3DTuMuFGKUIcirOSjFzOpncbomGFEIdZWK%26expires%3D33186611731%26signature%3DF7gjN4UJPDZn4b3S5t214s05e8Y%253D%26ts%3D1629702931"},{"title":"<스피릿> 메인 예고편 (우리 영화 볼래?)","contents":"<em class=\"screen_out\">재생시간 : </em>02:28","link":"https://tv.kakao.com/channel/462787/cliplink/421739342?act=clip","retrieved":1629702950067,"image":"https://t1.daumcdn.net/thumb/C320x180.fjpg.q75/?fname=http%3A%2F%2Fthumb.kakaocdn.net%2Fdna%2Fkamp%2Fsource%2Frviybuvxzh9gdar22m6jmc3qr%2Fthumbs%2Fthumb.jpg%3Fcredential%3DTuMuFGKUIcirOSjFzOpncbomGFEIdZWK%26expires%3D33186611305%26signature%3DW3SdHCE3vRfN7hy8T1Nb4xr8xVw%253D"},{"title":"<날씨의 아이> [재개봉] 4K UHD 예고편 (우리 영화 볼래?)","contents":"<em class=\"screen_out\">재생시간 : </em>00:29","link":"https://tv.kakao.com/channel/462787/cliplink/421738885?act=clip","retrieved":1629702950067,"image":"https://t1.daumcdn.net/thumb/C320x180.fjpg.q75/?fname=https%3A%2F%2Fthumb.kakaocdn.net%2Fdna%2Fkamp%2Fsource%2Frvw4e38ihggmhzdi4hwg984ck%2Fthumbs%2Fthumb.jpg%3Fcredential%3DTuMuFGKUIcirOSjFzOpncbomGFEIdZWK%26expires%3D33186686901%26signature%3Dx31SKsJiNL4UGmeu1NNN6rU9pIo%253D%26ts%3D1629778101"},{"title":"<원티드 킬러> 메인 예고편 (우리 영화 볼래?)","contents":"<em class=\"screen_out\">재생시간 : </em>01:41","link":"https://tv.kakao.com/channel/462787/cliplink/421735358?act=clip","retrieved":1629695634609,"image":"https://t1.daumcdn.net/thumb/C320x180.fjpg.q75/?fname=https%3A%2F%2Fthumb.kakaocdn.net%2Fdna%2Fkamp%2Fsource%2Frvp0x0s4kvzreppjno13wcefm%2Fthumbs%2Fthumb.jpg%3Fcredential%3DTuMuFGKUIcirOSjFzOpncbomGFEIdZWK%26expires%3D33186603117%26signature%3D33kRcVQcEB52U8slT8vgIqcJwhE%253D%26ts%3D1629694317"},{"title":"<그대 너머에> 메인 예고편 (우리 영화 볼래?)","contents":"<em class=\"screen_out\">재생시간 : </em>01:42","link":"https://tv.kakao.com/channel/462787/cliplink/421735105?act=clip","retrieved":1629695634609,"image":"https://t1.daumcdn.net/thumb/C320x180.fjpg.q75/?fname=https%3A%2F%2Fthumb.kakaocdn.net%2Fdna%2Fkamp%2Fsource%2Frvovmdkpyewwwg0cvmk1jjkal%2Fthumbs%2Fthumb.jpg%3Fcredential%3DTuMuFGKUIcirOSjFzOpncbomGFEIdZWK%26expires%3D33186602464%26signature%3DA3huRMsJZEPc1jaVrrslMld0IMQ%253D%26ts%3D1629693664"},{"title":"<더 트랩> 예고편 (우리 영화 볼래?)","contents":"<em class=\"screen_out\">재생시간 : </em>01:08","link":"https://tv.kakao.com/channel/462787/cliplink/421734925?act=clip","retrieved":1629695634609,"image":"https://t1.daumcdn.net/thumb/C320x180.fjpg.q75/?fname=https%3A%2F%2Fthumb.kakaocdn.net%2Fdna%2Fkamp%2Fsource%2Frvszn0ham6z61aoqf0nu60bew%2Fthumbs%2Fthumb.jpg%3Fcredential%3DTuMuFGKUIcirOSjFzOpncbomGFEIdZWK%26expires%3D33186602019%26signature%3DxnwoZ%252FkFwDbbjEbTZEAXk70js2E%253D%26ts%3D1629693219"},{"title":"<사운드 오브 데스> 메인 예고편 (우리 영화 볼래?)","contents":"<em class=\"screen_out\">재생시간 : </em>01:03","link":"https://tv.kakao.com/channel/462787/cliplink/421734705?act=clip","retrieved":1629695634611,"image":"https://t1.daumcdn.net/thumb/C320x180.fjpg.q75/?fname=http%3A%2F%2Fimg1.daumcdn.net%2Fkakaotv%2FKAKAOACCOUNT%2F356946556%2Fthumb%2F20210823132543"},{"title":"<카라타이: 태양의 전사> 메인 예고편 (우리 영화 볼래?)","contents":"<em class=\"screen_out\">재생시간 : </em>01:39","link":"https://tv.kakao.com/channel/462787/cliplink/421734531?act=clip","retrieved":1629692407910,"image":"https://t1.daumcdn.net/thumb/C240x140.fjpg.q75/?fname=https%3A%2F%2Fthumb.kakaocdn.net%2Fdna%2Fkamp%2Fsource%2Frvp583np7b0w6sl3alu7xckfs%2Fthumbs%2Fthumb.jpg%3Fcredential%3DTuMuFGKUIcirOSjFzOpncbomGFEIdZWK%26expires%3D33186601031%26signature%3DvL3mqSy58XoaOL%252Bbzt4rjt%252FSNTc%253D%26ts%3D1629692231"},{"title":"<첫눈이 사라졌다> 메인 예고편 (우리 영화 볼래?)","contents":"<em class=\"screen_out\">재생시간 : </em>01:50","link":"https://tv.kakao.com/channel/462787/cliplink/421734207?act=clip","retrieved":1629692407912,"image":"https://t1.daumcdn.net/thumb/C240x140.fjpg.q75/?fname=https%3A%2F%2Fthumb.kakaocdn.net%2Fdna%2Fkamp%2Fsource%2Frvyr1lyl9lawk7mjcncq4ccjx%2Fthumbs%2Fthumb.jpg%3Fcredential%3DTuMuFGKUIcirOSjFzOpncbomGFEIdZWK%26expires%3D33186600148%26signature%3DYfqoP0XpcJWc%252FxcEiqPAhuv%252BSV4%253D%26ts%3D1629691348"},{"title":"<토베 얀손> 티저 예고편 (우리 영화 볼래?)","contents":"<em class=\"screen_out\">재생시간 : </em>00:41","link":"https://tv.kakao.com/channel/462787/cliplink/421734024?act=clip","retrieved":1629692407913,"image":"https://t1.daumcdn.net/thumb/C240x140.fjpg.q75/?fname=http%3A%2F%2Fimg1.daumcdn.net%2Fkakaotv%2FKAKAOACCOUNT%2F681997725%2Fthumb%2F20210823130050"},{"title":"<시간여행: 과거에 갇힌 남자> 메인 예고편 (우리 영화 볼래?)","contents":"<em class=\"screen_out\">재생시간 : </em>01:46","link":"https://tv.kakao.com/channel/462787/cliplink/421733899?act=clip","retrieved":1629692407913,"image":"https://t1.daumcdn.net/thumb/C240x140.fjpg.q75/?fname=https%3A%2F%2Fthumb.kakaocdn.net%2Fdna%2Fkamp%2Fsource%2Frvczcr9rwcofw6ylxe79u5msr%2Fthumbs%2Fthumb.jpg%3Fcredential%3DTuMuFGKUIcirOSjFzOpncbomGFEIdZWK%26expires%3D33186599273%26signature%3Dzpi6sOR%252B51r5bbkVcwfxr%252BDppO0%253D%26ts%3D1629690473"},{"title":"<기적> 메인 예고편 (우리 영화 볼래?)","contents":"<em class=\"screen_out\">재생시간 : </em>01:38","link":"https://tv.kakao.com/channel/462787/cliplink/421733670?act=clip","retrieved":1629769980487,"image":"https://t1.daumcdn.net/thumb/C240x140.fjpg.q75/?fname=https%3A%2F%2Fthumb.kakaocdn.net%2Fdna%2Fkamp%2Fsource%2Frv95tkhafcykd0hf2s9kfeox0%2Fthumbs%2Fthumb.jpg%3Fcredential%3DTuMuFGKUIcirOSjFzOpncbomGFEIdZWK%26expires%3D33186598643%26signature%3DiOf3uAnKwndG8BF4JTBUuZXL0yI%253D%26ts%3D1629689843"},{"title":"<박강아름 결혼하다> 개봉 축하 영상 (우리 영화 볼래?)","contents":"<em class=\"screen_out\">재생시간 : </em>01:10","link":"https://tv.kakao.com/channel/462787/cliplink/421733596?act=clip","retrieved":1629692407915,"image":"https://t1.daumcdn.net/thumb/C240x140.fjpg.q75/?fname=http%3A%2F%2Fimg1.daumcdn.net%2Fkakaotv%2FKAKAOACCOUNT%2F835554265%2Fthumb%2F20210823123402"},{"title":"<영화의 거리> 메인 예고편 (우리 영화 볼래?)","contents":"<em class=\"screen_out\">재생시간 : </em>01:15","link":"https://tv.kakao.com/channel/462787/cliplink/421733503?act=clip","retrieved":1629692407916,"image":"https://t1.daumcdn.net/thumb/C240x140.fjpg.q75/?fname=https%3A%2F%2Fthumb.kakaocdn.net%2Fdna%2Fkamp%2Fsource%2Frvd1ezbvyxuzfzokg6dq7bhv8%2Fthumbs%2Fthumb.jpg%3Fcredential%3DTuMuFGKUIcirOSjFzOpncbomGFEIdZWK%26expires%3D33186598219%26signature%3DnjehhMTijU3n9PBAZmr30Qu920s%253D%26ts%3D1629689419"},{"title":"<켈리 갱> 메인 예고편 (우리 영화 볼래?)","contents":"<em class=\"screen_out\">재생시간 : </em>01:06","link":"https://tv.kakao.com/channel/462787/cliplink/421733433?act=clip","retrieved":1629692407921,"image":"https://t1.daumcdn.net/thumb/C240x140.fjpg.q75/?fname=http%3A%2F%2Fthumb.kakaocdn.net%2Fdna%2Fkamp%2Fsource%2Frv5ajdjiuai7egh75lz16moqp%2Fthumbs%2Fthumb.jpg%3Fcredential%3DTuMuFGKUIcirOSjFzOpncbomGFEIdZWK%26expires%3D33186597952%26signature%3D27scgJSIgUOr4UfVxxF%252FJT9sD%252Bw%253D"},{"title":"<여름날 우리> 허광한 스페셜 인터뷰 (우리 영화 볼래?)","contents":"<em class=\"screen_out\">재생시간 : </em>02:26","link":"https://tv.kakao.com/channel/462787/cliplink/421732091?act=clip","retrieved":1629685481077,"image":"https://t1.daumcdn.net/thumb/C240x140.fjpg.q75/?fname=http%3A%2F%2Fthumb.kakaocdn.net%2Fdna%2Fkamp%2Fsource%2Frvisuqbghobn73246w127xsf1%2Fthumbs%2Fthumb.jpg%3Fcredential%3DTuMuFGKUIcirOSjFzOpncbomGFEIdZWK%26expires%3D33186594110%26signature%3DskwRiflORo0NLpjyoK%252FB0A7AR4w%253D"},{"title":"<언더그라운드> 추천 영상 (우리 영화 볼래?)","contents":"<em class=\"screen_out\">재생시간 : </em>02:56","link":"https://tv.kakao.com/channel/462787/cliplink/421665602?act=clip","retrieved":1629450956260,"image":"https://t1.daumcdn.net/thumb/C240x140.fjpg.q75/?fname=http%3A%2F%2Fthumb.kakaocdn.net%2Fdna%2Fkamp%2Fsource%2Frvhwapbzz8srczutd7326os85%2Fthumbs%2Fthumb.jpg%3Fcredential%3DTuMuFGKUIcirOSjFzOpncbomGFEIdZWK%26expires%3D33186358550%26signature%3DLH%252BRpnbzwkSix897f4ymBP%252FAZkU%253D"},{"title":"<데미지> [재개봉] 메인 예고편 (우리 영화 볼래?)","contents":"<em class=\"screen_out\">재생시간 : </em>01:48","link":"https://tv.kakao.com/channel/462787/cliplink/421665228?act=clip","retrieved":1629692407926,"image":"https://t1.daumcdn.net/thumb/C240x140.fjpg.q75/?fname=http%3A%2F%2Fthumb.kakaocdn.net%2Fdna%2Fkamp%2Fsource%2Frv2djawklq7o3jowg07q6nsyk%2Fthumbs%2Fthumb.jpg%3Fcredential%3DTuMuFGKUIcirOSjFzOpncbomGFEIdZWK%26expires%3D33186357858%26signature%3D7TJ8N2n53jQ55YOoNHl5gPS5Ymw%253D"},{"title":"<시스터즈 워: 레드스네이크> 예고편 (우리 영화 볼래?)","contents":"<em class=\"screen_out\">재생시간 : </em>01:24","link":"https://tv.kakao.com/channel/462787/cliplink/421664993?act=clip","retrieved":1629450956263,"image":"https://t1.daumcdn.net/thumb/C240x140.fjpg.q75/?fname=http%3A%2F%2Fthumb.kakaocdn.net%2Fdna%2Fkamp%2Fsource%2Frviibh0wrfos0qa8iukw8zpgm%2Fthumbs%2Fthumb.jpg%3Fcredential%3DTuMuFGKUIcirOSjFzOpncbomGFEIdZWK%26expires%3D33186357474%26signature%3DSwPOtsfQekq72EqPxe%252F%252BovY79JQ%253D"},{"title":"<기적> 제작기 영상 (우리 영화 볼래?)","contents":"<em class=\"screen_out\">재생시간 : </em>03:34","link":"https://tv.kakao.com/channel/462787/cliplink/421660621?act=clip","retrieved":1629440345808,"image":"https://t1.daumcdn.net/thumb/C240x140.fjpg.q75/?fname=https%3A%2F%2Fthumb.kakaocdn.net%2Fdna%2Fkamp%2Fsource%2Frvhk1s9caq65rwslzt1p1ohj8%2Fthumbs%2Fthumb.jpg%3Fcredential%3DTuMuFGKUIcirOSjFzOpncbomGFEIdZWK%26expires%3D33186346962%26signature%3DEdwsP1Kacw0lcRcpWyOGKbLL9Sg%253D%26ts%3D1629438162"},{"title":"<모가디슈> 해외 배우 흥행 축하 영상 (우리 영화 볼래?)","contents":"<em class=\"screen_out\">재생시간 : </em>01:19","link":"https://tv.kakao.com/channel/462787/cliplink/421658864?act=clip","retrieved":1629436471922,"image":"https://t1.daumcdn.net/thumb/C240x140.fjpg.q75/?fname=http%3A%2F%2Fthumb.kakaocdn.net%2Fdna%2Fkamp%2Fsource%2Frvi2sd7ory20542arqwljn7fv%2Fthumbs%2Fthumb.jpg%3Fcredential%3DTuMuFGKUIcirOSjFzOpncbomGFEIdZWK%26expires%3D33186342796%26signature%3DRpTl4VKVAdfU6naGlJwmQzsFCiI%253D"},{"title":"<바쿠라우> 30초 예고편 (우리 영화 볼래?)","contents":"<em class=\"screen_out\">재생시간 : </em>00:30","link":"https://tv.kakao.com/channel/462787/cliplink/421657708?act=clip","retrieved":1629433190236,"image":"https://t1.daumcdn.net/thumb/C240x140.fjpg.q75/?fname=http%3A%2F%2Fthumb.kakaocdn.net%2Fdna%2Fkamp%2Fsource%2Frv6yh5ei2k81osxog7m78nxad%2Fthumbs%2Fthumb.jpg%3Fcredential%3DTuMuFGKUIcirOSjFzOpncbomGFEIdZWK%26expires%3D33186339584%26signature%3DuOomiHc0hajL2n94mKcahzBpF4o%253D"},{"title":"<귀문> ‘강철부대’ 4DX Screen 리액션 영상 (우리 영화 볼래?)","contents":"<em class=\"screen_out\">재생시간 : </em>01:47","link":"https://tv.kakao.com/channel/462787/cliplink/421657609?act=clip","retrieved":1629433190236,"image":"https://t1.daumcdn.net/thumb/C240x140.fjpg.q75/?fname=https%3A%2F%2Fthumb.kakaocdn.net%2Fdna%2Fkamp%2Fsource%2Frvl6jqu2ktwzej6sr1r7v3ni4%2Fthumbs%2Fthumb.jpg%3Fcredential%3DTuMuFGKUIcirOSjFzOpncbomGFEIdZWK%26expires%3D33186339326%26signature%3DjAQyQq10Ow0uVmFbAlrbKvLuGiw%253D%26ts%3D1629430526"},{"title":"<슈퍼문> 메인 예고편 (우리 영화 볼래?)","contents":"<em class=\"screen_out\">재생시간 : </em>01:24","link":"https://tv.kakao.com/channel/462787/cliplink/421657498?act=clip","retrieved":1629433190238,"image":"https://t1.daumcdn.net/thumb/C240x140.fjpg.q75/?fname=http%3A%2F%2Fthumb.kakaocdn.net%2Fdna%2Fkamp%2Fsource%2Frv6dj5d34ci96ie4kuq5vl1dn%2Fthumbs%2Fthumb.jpg%3Fcredential%3DTuMuFGKUIcirOSjFzOpncbomGFEIdZWK%26expires%3D33186339040%26signature%3DAdpm5Fwuoe%252BPKwRf15f29nxCSno%253D"},{"title":"<더 런> 메인 예고편 (우리 영화 볼래?)","contents":"<em class=\"screen_out\">재생시간 : </em>00:53","link":"https://tv.kakao.com/channel/462787/cliplink/421657369?act=clip","retrieved":1629433190245,"image":"https://t1.daumcdn.net/thumb/C240x140.fjpg.q75/?fname=https%3A%2F%2Fthumb.kakaocdn.net%2Fdna%2Fkamp%2Fsource%2Frvi025yfca9ueeuk6zu76hzk9%2Fthumbs%2Fthumb.jpg%3Fcredential%3DTuMuFGKUIcirOSjFzOpncbomGFEIdZWK%26expires%3D33186338889%26signature%3DwEbq6bMtw0Zw7txDfC2828Mk%252FR4%253D%26ts%3D1629430089"},{"title":"<아임 유어 맨> 티저 예고편 (우리 영화 볼래?)","contents":"<em class=\"screen_out\">재생시간 : </em>00:30","link":"https://tv.kakao.com/channel/462787/cliplink/421655271?act=clip","retrieved":1629426327255,"image":"https://t1.daumcdn.net/thumb/C240x140.fjpg.q75/?fname=http%3A%2F%2Fimg1.daumcdn.net%2Fkakaotv%2FKAKAOACCOUNT%2F1653394125%2Fthumb%2F20210820110108"},{"title":"<건파우더 밀크셰이크> 킬링 액션 벌스 영상 (우리 영화 볼래?)","contents":"<em class=\"screen_out\">재생시간 : </em>01:39","link":"https://tv.kakao.com/channel/462787/cliplink/421655130?act=clip","retrieved":1629426327256,"image":"https://t1.daumcdn.net/thumb/C240x140.fjpg.q75/?fname=http%3A%2F%2Fimg1.daumcdn.net%2Fkakaotv%2FKAKAOACCOUNT%2F869590127%2Fthumb%2F20210820105413"},{"title":"'니키리라고도 알려진' 메인 예고편 (네이버 영화 예고편 저장소)","contents":"1시간 전","link":"https://tv.naver.com/v/22049884","retrieved":1629861395016,"image":"https://phinf.pstatic.net/tvcast/20210825_111/cnHuE_1629859351152paUP8_JPEG/b9daaf51-054d-11ec-80a9-a0369ff95678_06.jpg?type=f194_109_blend"},{"title":"'말리그넌트' 30초 예고편 (네이버 영화 예고편 저장소)","contents":"2시간 전","link":"https://tv.naver.com/v/22049311","retrieved":1629858340106,"image":"https://phinf.pstatic.net/tvcast/20210825_10/bx8JM_1629857593558fFSdO_JPEG/bf70929f-0549-11ec-8111-505dac8c381b_02.jpg?type=f194_109_blend"},{"title":"'캔디맨' 소환영상 1탄 (네이버 영화 예고편 저장소)","contents":"2시간 전","link":"https://tv.naver.com/v/22049151","retrieved":1629858340110,"image":"https://phinf.pstatic.net/tvcast/20210825_233/IkoHR_1629857120794oeQNe_JPEG/a559c304-0548-11ec-9d7e-a0369ff952f4_01.jpg?type=f194_109_blend"},{"title":"'퇴마사' 예고편 (네이버 영화 예고편 저장소)","contents":"19시간 전","link":"https://tv.naver.com/v/22036588","retrieved":1629796578241,"image":"https://phinf.pstatic.net/tvcast/20210824_82/VPu6m_1629793777862TfuSW_JPEG/025b91f1-04b5-11ec-a9f1-505dac8c3639_03.jpg?type=f194_109_blend"},{"title":"'더 드라이버' 예고편 (네이버 영화 예고편 저장소)","contents":"19시간 전","link":"https://tv.naver.com/v/22036133","retrieved":1629796578243,"image":"https://phinf.pstatic.net/tvcast/20210824_124/d8z9K_1629793265329iSoil_JPEG/ff07c896-04b3-11ec-8678-48df379cca40_08.jpg?type=f194_109_blend"},{"title":"'용과 주근깨 공주' 티저 예고편 (네이버 영화 예고편 저장소)","contents":"20시간 전","link":"https://tv.naver.com/v/22035235","retrieved":1629793111985,"image":"https://phinf.pstatic.net/tvcast/20210824_104/T431k_1629792057879oj3n4_JPEG/3303c48f-04b1-11ec-a77c-a0369ff94ec8_04.jpg?type=f194_109_blend"},{"title":"'바람난 가족들' 예고편 (네이버 영화 예고편 저장소)","contents":"20시간 전","link":"https://tv.naver.com/v/22034484","retrieved":1629793111988,"image":"https://phinf.pstatic.net/tvcast/20210824_84/q83AV_1629790848646z6W7p_JPEG/644d7151-04ae-11ec-89ce-48df379ccacc_01.jpg?type=f194_109_blend"},{"title":"'극장판 포켓몬스터: 정글의 아이, 코코' 메인 예고편 (네이버 영화 예고편 저장소)","contents":"20시간 전","link":"https://tv.naver.com/v/22034068","retrieved":1629793111990,"image":"https://phinf.pstatic.net/tvcast/20210824_65/weWdz_1629790157045qebKP_JPEG/ba5a2b11-04ac-11ec-86ec-48df37ae3fca_10.jpg?type=f194_109_blend"},{"title":"'스쿨 아웃 포에버' 티저 예고편 (네이버 영화 예고편 저장소)","contents":"20시간 전","link":"https://tv.naver.com/v/22033764","retrieved":1629793111991,"image":"https://phinf.pstatic.net/tvcast/20210824_230/6Cn1V_1629789683301Trkfu_PNG/1629789677776.png?type=f194_109_blend"},{"title":"'극장판 마이 리틀 포니: 새로운 희망' 1차 예고편 (네이버 영화 예고편 저장소)","contents":"20시간 전","link":"https://tv.naver.com/v/22033706","retrieved":1629793111991,"image":"https://phinf.pstatic.net/tvcast/20210824_175/cEXGG_1629789598817ECtA2_PNG/1629789593768.png?type=f194_109_blend"},{"title":"'고스트 스나이퍼' 메인 예고편 (네이버 영화 예고편 저장소)","contents":"21시간 전","link":"https://tv.naver.com/v/22033687","retrieved":1629793111993,"image":"https://phinf.pstatic.net/tvcast/20210824_167/DGXZe_1629789555283VBxQY_JPEG/73dbdc8d-04ab-11ec-89ce-48df379ccacc_09.jpg?type=f194_109_blend"},{"title":"'남색대문' 엔딩 명장면 (네이버 영화 예고편 저장소)","contents":"21시간 전","link":"https://tv.naver.com/v/22032695","retrieved":1629789350282,"image":"https://phinf.pstatic.net/tvcast/20210824_272/2RUgu_1629787837458Ayc38_JPEG/50a4582a-04a7-11ec-882d-48df37ae3dc4_06.jpg?type=f194_109_blend"},{"title":"'어시스턴트' 30초 예고편 (네이버 영화 예고편 저장소)","contents":"22시간 전","link":"https://tv.naver.com/v/22031200","retrieved":1629785906853,"image":"https://phinf.pstatic.net/tvcast/20210824_149/rDXx6_1629784736438K0tIb_JPEG/3216b488-04a0-11ec-86ec-48df37ae3fca_07.jpg?type=f194_109_blend"},{"title":"'내가 날 부를 때' 30초 예고편 (네이버 영화 예고편 저장소)","contents":"1일 전","link":"https://tv.naver.com/v/22027277","retrieved":1629774979444,"image":"https://phinf.pstatic.net/tvcast/20210824_117/3IKqP_1629772992332NS8dy_JPEG/d03b159c-0484-11ec-8c9c-505dac8c37f3_07.jpg?type=f194_109_blend"},{"title":"'내가 날 부를 때' 메인 예고편 (네이버 영화 예고편 저장소)","contents":"1일 전","link":"https://tv.naver.com/v/22027176","retrieved":1629774979446,"image":"https://phinf.pstatic.net/tvcast/20210824_214/MIzA9_1629772728888QBdsC_JPEG/04dbf195-0484-11ec-af84-246e963a49a8_01.jpg?type=f194_109_blend"},{"title":"'카라타이: 태양의 전사' 메인 예고편 (네이버 영화 예고편 저장소)","contents":"1일 전","link":"https://tv.naver.com/v/22026734","retrieved":1629771862968,"image":"https://phinf.pstatic.net/tvcast/20210824_131/sazPq_16297716420860viho_JPEG/a7b8f006-0481-11ec-8678-48df379cca40_07.jpg?type=f194_109_blend"},{"title":"'시간여행: 과거에 갇힌 남자' 메인 예고편 (네이버 영화 예고편 저장소)","contents":"1일 전","link":"https://tv.naver.com/v/22026408","retrieved":1629771862969,"image":"https://phinf.pstatic.net/tvcast/20210824_40/jdYz4_1629770779943VuSRy_JPEG/78c707f5-047f-11ec-9845-505dacfbaa5c_03.jpg?type=f194_109_blend"},{"title":"'스파이더맨: 노 웨이 홈' 티저 예고편 (네이버 영화 예고편 저장소)","contents":"1일 전","link":"https://tv.naver.com/v/22026311","retrieved":1629771862972,"image":"https://phinf.pstatic.net/tvcast/20210824_41/wksN8_1629770536206HvQAe_JPEG/844223b4-047e-11ec-8111-505dac8c381b_09.jpg?type=f194_109_blend"},{"title":"'날씨의 아이'  4K UHD 예고편 (네이버 영화 예고편 저장소)","contents":"1일 전","link":"https://tv.naver.com/v/22025317","retrieved":1629769986457,"image":"https://phinf.pstatic.net/tvcast/20210824_142/hxRTL_1629767766602c5jNU_JPEG/c925b1ef-0478-11ec-8c9c-505dac8c37f3_03.jpg?type=f194_109_blend"},{"title":"'스피릿' 메인 예고편 (네이버 영화 예고편 저장소)","contents":"1일 전","link":"https://tv.naver.com/v/22015493","retrieved":1629710150960,"image":"https://phinf.pstatic.net/tvcast/20210823_116/s04Wt_1629709834339WpzO9_JPEG/a6e57607-03f1-11ec-b6bf-48df379cc9e4_01.jpg?type=f194_109_blend"},{"title":"'데미지' 메인 예고편 (네이버 영화 예고편 저장소)","contents":"1일 전","link":"https://tv.naver.com/v/22014639","retrieved":1629710150964,"image":"https://phinf.pstatic.net/tvcast/20210823_151/0tpli_1629707537574KOd8s_JPEG/4a56f27a-03ec-11ec-9b63-505dacfba98a_09.jpg?type=f194_109_blend"},{"title":"'토베 얀손' 티저 예고편 (네이버 영화 예고편 저장소)","contents":"1일 전","link":"https://tv.naver.com/v/22014334","retrieved":1629710150965,"image":"https://phinf.pstatic.net/tvcast/20210823_287/faHFx_1629706832446i8MHm_JPEG/d4b51300-03ea-11ec-8678-48df379cca40_07.jpg?type=f194_109_blend"},{"title":"'영화의 거리' 메인 예고편 (네이버 영화 예고편 저장소)","contents":"1일 전","link":"https://tv.naver.com/v/22013877","retrieved":1629706683213,"image":"https://phinf.pstatic.net/tvcast/20210823_58/WQJyc_1629706028454SJVbs_JPEG/06ff9847-03e9-11ec-a72a-246e963a464c_04.jpg?type=f194_109_blend"},{"title":"'켈리 갱' 메인 예고편 (네이버 영화 예고편 저장소)","contents":"1일 전","link":"https://tv.naver.com/v/22013533","retrieved":1629706683214,"image":"https://phinf.pstatic.net/tvcast/20210823_29/b8heW_1629705300374bsGUC_JPEG/5688fe39-03e7-11ec-82ff-505dac8c385b_03.jpg?type=f194_109_blend"},{"title":"'박강아름 결혼하다' 개봉 축하 영상 (네이버 영화 예고편 저장소)","contents":"1일 전","link":"https://tv.naver.com/v/22013236","retrieved":1629706683215,"image":"https://phinf.pstatic.net/tvcast/20210823_144/l6YNm_1629704661105sg5el_JPEG/dc6abedc-03e5-11ec-a509-a0369ff968b0_02.jpg?type=f194_109_blend"},{"title":"'여름날 우리' 허광한 스페셜 인터뷰 (네이버 영화 예고편 저장소)","contents":"1일 전","link":"https://tv.naver.com/v/22013036","retrieved":1629706683217,"image":"https://phinf.pstatic.net/tvcast/20210823_83/y44za_1629704218720RtOp1_JPEG/b55dc199-03e4-11ec-a8ac-505dac8c35ff_01.jpg?type=f194_109_blend"},{"title":"'언더그라운드' 추천 영상 (네이버 영화 예고편 저장소)","contents":"1일 전","link":"https://tv.naver.com/v/22012772","retrieved":1629706683220,"image":"https://phinf.pstatic.net/tvcast/20210823_63/5GkkY_1629703410536EFTB3_JPEG/b97d6e81-03e2-11ec-86ec-48df37ae3fca_01.jpg?type=f194_109_blend"},{"title":"'기적' 메인 예고편 (네이버 영화 예고편 저장소)","contents":"1일 전","link":"https://tv.naver.com/v/22010222","retrieved":1629769986475,"image":"https://phinf.pstatic.net/tvcast/20210823_155/UF548_1629697135337pY5DM_JPEG/22b30382-03d4-11ec-a77c-a0369ff94ec8_06.jpg?type=f194_109_blend"},{"title":"'싱크홀' THANK YOU ALL 무비토크 FULL 영상 (네이버 영화 예고편 저장소)","contents":"2일 전","link":"https://tv.naver.com/v/22006685","retrieved":1629685486356,"image":"https://phinf.pstatic.net/tvcast/20210823_126/Whdrb_1629685269931rIRGv_JPEG/98beeb5a-03b7-11ec-8c9c-505dac8c37f3_06.jpg?type=f194_109_blend"},{"title":"'기적' 제작기 (네이버 영화 예고편 저장소)","contents":"4일 전","link":"https://tv.naver.com/v/21975486","retrieved":1629450962444,"image":"https://phinf.pstatic.net/tvcast/20210820_85/n1qjd_1629449741568zhFDW_JPEG/310bfec1-0194-11ec-b6bf-48df379cc9e4_03.jpg?type=f194_109_blend"},{"title":"<인질>,<언더그라운드>,<박강아름 결혼하다>,<팜 스프링스>등 씨네21 20자평 (씨네21 ─ 20자평)","contents":"<span class=\"ell\">씨네21</span>","link":"https://post.naver.com/viewer/postView.naver?volumeNo=32166684&memberNo=15205863&navigationType=push","retrieved":1629004862869,"image":"https://post-phinf.pstatic.net/MjAyMTA4MTNfMTEx/MDAxNjI4ODQyNDEyMjU0.hFrBYxSQoQibdwF1i_4MIbl1jN0AK1uIE8bJLX3C8zEg.mlOtw-jwosmx8oiika3umDluuIP4wOL-eznL3GSLMdMg.JPEG/Iqh9x0NpWiRhuRtkQ70fJ7DdMShk.jpg?type=fb500_500"},{"title":"<싱크홀> <암살자들> <더 수어사이드 스쿼드> 등 씨네21 20자평 (씨네21 ─ 20자평)","contents":"<span class=\"ell\">씨네21</span>","link":"https://post.naver.com/viewer/postView.naver?volumeNo=32117037&memberNo=15205863&navigationType=push","retrieved":1629004862870,"image":"https://post-phinf.pstatic.net/MjAyMTA4MDZfNzIg/MDAxNjI4MjA3ODcxOTMy.zAVN6a_wSVLgv2NIgaZll-9O3zL9I_BbFvUf6llqLfIg.BJMn80QRI5sbyvHtaJ7v0odcM7-mU-s7jmMCC8QF-1Qg.JPEG/I1q8rN6BvnyrEB6Ri2pq3GPAo9O0.jpg?type=fb500_500"},{"title":"<정글 크루즈>,<잘리카투>,<그린나이트> 등 씨네21 20자평 (씨네21 ─ 20자평)","contents":"<span class=\"ell\">씨네21</span>","link":"https://post.naver.com/viewer/postView.naver?volumeNo=32075394&memberNo=15205863&navigationType=push","retrieved":1629004862902,"image":"https://post-phinf.pstatic.net/MjAyMTA3MzBfMjYz/MDAxNjI3NjI0MDQwNDEy.OTUdo-IQB3qdjugjrrMvzejATQEAC2hoLkEI49mEsp4g.WKzOvTijpcoGeN-4t0tCxdiEZnBMQM1fKJFzLG3IlLAg.JPEG/IpV5-NDuYe5k3WHN-23ZSnVDz3cM.jpg?type=fb500_500"},{"title":"<모가디슈>,<방법:재차의>,<갈매기> 등 씨네21 전문가 20자평 (씨네21 ─ 20자평)","contents":"<span class=\"ell\">씨네21</span>","link":"https://post.naver.com/viewer/postView.naver?volumeNo=32069045&memberNo=15205863&navigationType=push","retrieved":1629004862903,"image":"https://post-phinf.pstatic.net/MjAyMTA3MzBfMTI5/MDAxNjI3NjI0MTAzMTY2.vRlXikLHsmFlNqVXcyRwhBvcD5AxyagBjveU4-rkHZsg.ro9uW05slqjuatj7jAIyeyUrLE4qSG06O12FedgYL5Ug.JPEG/IwE7EJ0-rHXsZ0P2P_Q2z60Wi3CE.jpg?type=fb500_500"},{"title":"<피닉스>, <숏버스 이별행>, <워스>, <아이스 로드> 등 씨네21 20자평 (씨네21 ─ 20자평)","contents":"<span class=\"ell\">씨네21</span>","link":"https://post.naver.com/viewer/postView.naver?volumeNo=32013527&memberNo=15205863&navigationType=push","retrieved":1629004862903,"image":"https://post-phinf.pstatic.net/MjAyMTA3MzBfMjc3/MDAxNjI3NjI0MTI1MTI5.qtvYJhXkQygppHfvz_Y2gGfil_20HgVA-onOxIid0k4g.wrsqCRJkMy75dEwlncUqvlIPpmVtNrMYPogzw7iLUN4g.JPEG/IYyu17NpPKU3LLvr3ieE53oMnRk4.jpg?type=fb500_500"},{"title":"<랑종>,<오필리아>,<죽어도 좋은 경험: 천사여 악마가 되라> 등 씨네21 20자평 (씨네21 ─ 20자평)","contents":"<span class=\"ell\">씨네21</span>","link":"https://post.naver.com/viewer/postView.naver?volumeNo=31934622&memberNo=15205863&navigationType=push","retrieved":1629004862903,"image":"https://post-phinf.pstatic.net/MjAyMTA3MDlfMTY3/MDAxNjI1ODA3MTY2NDU1.4dtMvCuczWgmU68vG_2EmQ03-M74q3WMiwUYzurtNwQg.3cTyJTeqSITvfrwKIKKXCDYgohnjsiZ-OdohG9zzdkcg.JPEG/I4v2GM5FUR9FWVIzAycqD6MWzdI8.jpg?type=fb500_500"},{"title":"<블랙 위도우> <트림 투 그리스> <미션 임파서블 : 루벤> 등 씨네21 20자평 (씨네21 ─ 20자평)","contents":"<span class=\"ell\">씨네21</span>","link":"https://post.naver.com/viewer/postView.naver?volumeNo=31889069&memberNo=15205863&navigationType=push","retrieved":1629004862903,"image":"https://post-phinf.pstatic.net/MjAyMTA3MDJfMjM3/MDAxNjI1MjA3NjA4NjU0.Ha0Bz78pkUjDA79Ap92fzej9RtAJHQpNB5W33kONMxMg.7ehRRo3s8fS1F71U5UsleKR8OZZH8Y805YAHthfeMgcg.JPEG/IsCJa29blc6xsoUwoPQ0_mUZPeQE.jpg?type=fb500_500"},{"title":"<웬디>,<아사다 가족>,<인더 하이츠> 등 씨네21 전문가 20자평 (씨네21 ─ 20자평)","contents":"<span class=\"ell\">씨네21</span>","link":"https://post.naver.com/viewer/postView.naver?volumeNo=31841642&memberNo=15205863&navigationType=push","retrieved":1629004862903,"image":"https://post-phinf.pstatic.net/MjAyMTA2MjVfMTM1/MDAxNjI0NjA4NzI1NDYx.Jehl0xkMvDRvwRNfqG0BUn3ZwtUX0SC6jG35KeA3jwAg.-0CLCIDBLaOSR0PhKls9-g2lvqr5WfKPlQ3E35Vxydog.JPEG/IDMrtuijOb8dm84COkg1HBIcGEOQ.jpg?type=fb500_500"},{"title":"<발신제한>,<메이드인루프탑>,<킬러의 보디가드2> 등 씨네21 20자평 (씨네21 ─ 20자평)","contents":"<span class=\"ell\">씨네21</span>","link":"https://post.naver.com/viewer/postView.naver?volumeNo=31803453&memberNo=15205863&navigationType=push","retrieved":1629004862903,"image":"https://post-phinf.pstatic.net/MjAyMTA2MjFfMjkg/MDAxNjI0MjQ5NTk1ODAx.COj1_EYVCJTeUU6giSvrsC98D9BdQPkmxDYCM5Mk1Wwg.dnsJrdxZPMT77yrIVUkAtJk2NyQpLjuEtjZ9CCePOBog.JPEG/IqdFZkGYGx_ptvv88gZCn5WoN2pY.jpg?type=fb500_500"},{"title":"<여고괴담 여섯번째 이야기 : 모교>,<클라이밍>,<그레타 툰베리>등 씨네21 20자평 (씨네21 ─ 20자평)","contents":"<span class=\"ell\">씨네21</span>","link":"https://post.naver.com/viewer/postView.naver?volumeNo=31720809&memberNo=15205863&navigationType=push","retrieved":1629004862903,"image":"https://post-phinf.pstatic.net/MjAyMTA2MTFfMTM1/MDAxNjIzMzkyMjM0Mjgx.NbL56pbn264jkFg4ae611PhMBXcXrRgbs0KmkXmn9DUg.eJLOg60UgooInykPvFmKcvwn9eBvCXFZxcWmwbBL4vkg.JPEG/IP9hIq2Q7ljMbBnPOeCZ-BLwgkRc.jpg?type=fb500_500"},{"title":"<컨저링3>,<라이더스 오브 저스티스>,<화이트 온 화이트> 등 씨네21 20자평 (씨네21 ─ 20자평)","contents":"<span class=\"ell\">씨네21</span>","link":"https://post.naver.com/viewer/postView.naver?volumeNo=31660490&memberNo=15205863&navigationType=push","retrieved":1629004862903,"image":"https://post-phinf.pstatic.net/MjAyMTA2MDRfMTA4/MDAxNjIyNzcxMzQ5ODM2.VJYJitsUz_YUR4s-p-znW97o3g7T5TXC6FRwPUVSeEQg.Z8bSqyxwo5bMJ_NLuMi0gPgOuBm1nIkxw0uSMO9O2OIg.JPEG/IaSnl9lKMzTuW8KSO31GJq7WgLCk.jpg?type=fb500_500"},{"title":"<크루엘라>,<#위왓치유>,<낫아웃> 등 씨네21 20자평 (씨네21 ─ 20자평)","contents":"<span class=\"ell\">씨네21</span>","link":"https://post.naver.com/viewer/postView.naver?volumeNo=31627009&memberNo=15205863&navigationType=push","retrieved":1629004862903,"image":"https://post-phinf.pstatic.net/MjAyMTA1MzFfMTUz/MDAxNjIyNDUyMDMyNTIy.JqZ7oTXeZYPZ7Av76yxNBBL465-eMROtdlYKLOojtKcg.sdKHb7z8C9KP9uVYsbKctzMtI8TVpU4ywuneTRJ6o1og.JPEG/IFh-fzXk0a4xJgwqzh64EDPAUzjk.jpg?type=fb500_500"},{"title":"<분노의 질주: 더 얼티메이트><파이프라인> 등 7편 ㅣ<씨네21> 1307호 전문가 별점 (씨네21 ─ 20자평)","contents":"<span class=\"ell\">씨네21</span>","link":"https://post.naver.com/viewer/postView.naver?volumeNo=31548898&memberNo=15205863&navigationType=push","retrieved":1629004862903,"image":"https://post-phinf.pstatic.net/MjAyMTA1MjFfNTcg/MDAxNjIxNTczMDQ1NDkz.UaodnZtE1AmT9fuGDSteA_Nq1SqYb7tE2732aJO5ES4g.MFUqtN74uSG3Rz_R3HzIyomLTdI_U9_pRDRPtRux7d8g.JPEG/IdRUUzcH_dq6caP0DaJD_O164Afk.jpg?type=fb500_500"},{"title":"<혼자 사는 사람들><쿠오바디스, 아이다> 등 10편 ㅣ<씨네21> 1306호 전문가 별점 (씨네21 ─ 20자평)","contents":"<span class=\"ell\">씨네21</span>","link":"https://post.naver.com/viewer/postView.naver?volumeNo=31496676&memberNo=15205863&navigationType=push","retrieved":1629004862904,"image":"https://post-phinf.pstatic.net/MjAyMTA1MTRfNzcg/MDAxNjIwOTY5MDQ3NTIx.ElvW4Xd0gjPUa6dUVYSvChBA1cNfP_Mj4oolMtfCOYwg.JZ2SV2zWe5ZlVEKGROwLqM0n52cg96gq5Ea54FpQ4Y8g.JPEG/IIHdrjGSGZ9Ei0YES7-L2hANTdEg.jpg?type=fb500_500"},{"title":"<내가 죽기를 바라는 자들> 등 7편 ㅣ<씨네21> 1305호 전문가 별점 (씨네21 ─ 20자평)","contents":"<span class=\"ell\">씨네21</span>","link":"https://post.naver.com/viewer/postView.naver?volumeNo=31461892&memberNo=15205863&navigationType=push","retrieved":1629004862904,"image":"https://post-phinf.pstatic.net/MjAyMTA1MTBfMjA1/MDAxNjIwNjM2MjkwMjE0.ZyTsl-9ERy40XlMZGyzXujFoYSuweBsFI3Ze3YbzRPAg.kX443SnPK65tUXFYnbDlLtzPSNz4yaGUAOB9TIkTGgsg.JPEG/IyZDVDswbTNjAntzsQKxwJXBeRm0.jpg?type=fb500_500"},{"title":"<극장판 콩순이><아이들은 즐겁다> 등 7편 ㅣ<씨네21> 1304호 전문가 별점 (씨네21 ─ 20자평)","contents":"<span class=\"ell\">씨네21</span>","link":"https://post.naver.com/viewer/postView.naver?volumeNo=31417460&memberNo=15205863&navigationType=push","retrieved":1629004862909,"image":"https://post-phinf.pstatic.net/MjAyMTA1MDRfODYg/MDAxNjIwMTA4NDYwNTU1.5zJvVifxD9SwqPmTQK5o2MxfqfhIuv04kQWcRdhEYNIg.-ybo6gBY1S1d-UtuTysjuzKU-uCxL6Cd2tYSIBndVnEg.JPEG/IKT_x63A-upscIzskdPIdFwdhIBc.jpg?type=fb500_500"},{"title":"<비와 당신의 이야기> 등 6편 ㅣ<씨네21> 1303호 전문가 별점 (씨네21 ─ 20자평)","contents":"<span class=\"ell\">씨네21</span>","link":"https://post.naver.com/viewer/postView.naver?volumeNo=31334706&memberNo=15205863&navigationType=push","retrieved":1629004862909,"image":"https://post-phinf.pstatic.net/MjAyMTA0MjNfMTUg/MDAxNjE5MTU5NjExMTYw.HwlkYrmoYfXtQWykDJE9Ar5X9VOc1Jgj0vBV494S3ysg.XJ5--JvcfOzcJYvABtKMPVzsLXK_GvK3xicjQBbOqVsg.JPEG/IM0tn2wUOSTh-9NW4flFoPRbZyHA.jpg?type=fb500_500"},{"title":"<서복> <유다 그리고 블랙 메시아> 등 8편 ㅣ<씨네21> 1302호 전문가 별점 (씨네21 ─ 20자평)","contents":"<span class=\"ell\">씨네21</span>","link":"https://post.naver.com/viewer/postView.naver?volumeNo=31258147&memberNo=15205863&navigationType=push","retrieved":1629004862909,"image":"https://post-phinf.pstatic.net/MjAyMTA0MTZfMTA5/MDAxNjE4NTYyMDQzMDM1.N5c6IoA-ljGtBho_6LXGV01saZw7Guvr7ykSVT8U05gg.-ZcfKsDyeVVBdA4frb-FewS93Kz8Yi5orTdhPv7L31Yg.JPEG/IVfsyEDhuaM-bl1ptTl-NqIraos0.jpg?type=fb500_500"},{"title":"<노매드랜드> <낙원의 밤> 등 9편 ㅣ<씨네21> 1301호 전문가 별점 (씨네21 ─ 20자평)","contents":"<span class=\"ell\">씨네21</span>","link":"https://post.naver.com/viewer/postView.naver?volumeNo=31184363&memberNo=15205863&navigationType=push","retrieved":1629004862910,"image":"https://post-phinf.pstatic.net/MjAyMTA0MDlfMTY5/MDAxNjE3OTQ3NDIzMDA3.RL1kCQgoSUcA0GP_2wOLiPbFXek-KN4lgCjmXaemapMg.EkpJW8fa8BezG-r8pcy3S4I0Z_4ed8KCgFFyTC4OW4Yg.JPEG/IhoDOy2IvM2tcIhZbF3udML5N2tM.jpg?type=fb500_500"},{"title":"<더 파더><노바디> 등 14편 ㅣ<씨네21> 1300호 전문가 별점 (씨네21 ─ 20자평)","contents":"<span class=\"ell\">씨네21</span>","link":"https://post.naver.com/viewer/postView.naver?volumeNo=31184324&memberNo=15205863&navigationType=push","retrieved":1629004862915,"image":"https://post-phinf.pstatic.net/MjAyMTA0MDlfODAg/MDAxNjE3OTQ3ODczMzc1.80LVSzc7F-zwFBiVVMznjj6pNOJwYQ17Q0S_TTBO2rgg.tSBv1qGYICXpdkF87pX9s1zIC_qJvojtMpSljyjWUz0g.JPEG/IvRYwUVoSY8eBEU4BoDrS80xOex8.jpg?type=fb500_500"},{"title":"비스포크 썸머 무비 <너를 위해 문을 열어놓을게>의 이옥섭 감독을 만나다 (씨네21 ─ 국내뉴스)","contents":"<span class=\"ell\">씨네21</span>","link":"https://post.naver.com/viewer/postView.naver?volumeNo=31802303&memberNo=15205863&navigationType=push","retrieved":1629004867563,"image":"https://post-phinf.pstatic.net/MjAyMTA2MjFfNjQg/MDAxNjI0MjQxNzI1MjEz.yQ2tPDA3F4zoXtxt4BIHvBEzFXbx4a38OZy5QT3KYKIg.hs3VOiFatKTwFYF2gxVt5QYojdSeVXUP8bT-m3h_vx4g.JPEG/ILq0MGOs2KNrqJWZsoAbJtnIwMiA.jpg?type=fb500_500"},{"title":"<씨네21>·인스타페이, 콘텐츠 협력 제휴 체결 (씨네21 ─ 국내뉴스)","contents":"<span class=\"ell\">씨네21</span>","link":"https://post.naver.com/viewer/postView.naver?volumeNo=30654213&memberNo=15205863&navigationType=push","retrieved":1629004867566,"image":"https://post-phinf.pstatic.net/MjAyMTAyMDVfMTAy/MDAxNjEyNTEwNDU2MDQx.hJjN9i-AkD1czjxAB5ovd_VEYVmBEU_nCN5XN6JX_rAg.5InmdHEk6q4LmDIOrtP0DjwEA6FK0htrJn9gXqHn_d0g.JPEG/IaS6EC2RJLhCqva9U8EvQkcO6Eyc.jpg?type=fb500_500"},{"title":"<미나리>의 배우 윤여정과 <기생충> 봉준호 감독의 만남 (씨네21 ─ 국내뉴스)","contents":"<span class=\"ell\">씨네21</span>","link":"https://post.naver.com/viewer/postView.naver?volumeNo=30652405&memberNo=15205863&navigationType=push","retrieved":1629004867566,"image":"https://post-phinf.pstatic.net/MjAyMTAyMDVfODQg/MDAxNjEyNTAwNDczNzg5.pNiuGEai9C7w0NEjaogvUJm15wwLenBdB-9UhmZYEOIg.RuUowvw-bsi4Hvb0WwyXbYleOP2v2KZrtXma9cnGGLEg.JPEG/I4cDFRCBGl78snju7BQlP2KsTBdQ.jpg?type=fb500_500"},{"title":"천만 영화 <부산행>, <변호인>, 쿠팡플레이에서 본다 (씨네21 ─ 국내뉴스)","contents":"<span class=\"ell\">씨네21</span>","link":"https://post.naver.com/viewer/postView.naver?volumeNo=30489705&memberNo=15205863&navigationType=push","retrieved":1629004867576,"image":"https://post-phinf.pstatic.net/MjAyMTAxMTVfMjU4/MDAxNjEwNjk2NTU0MTA1.EZOAuSBVq9gtu7TeEilVDhOmhYfaCQGyyfMUyHi3_GIg.N6iW4iYuIW2blMY8sC9tpRvaM7FQ6M5CuV-wMIGU_ygg.PNG/I8lN7i9wB2Fdajra8c7GkohE01pc.jpg?type=fb500_500"},{"title":"배우 류준열, 어린이 후원 프로그램 독려 “후원하며 나도 함께 성장” (씨네21 ─ 국내뉴스)","contents":"<span class=\"ell\">씨네21</span>","link":"https://post.naver.com/viewer/postView.naver?volumeNo=30484872&memberNo=15205863&navigationType=push","retrieved":1629004867576,"image":"https://post-phinf.pstatic.net/MjAyMTAxMTRfMjc1/MDAxNjEwNTg4MTAyNjYz.FhJoirRfd16l9_7_HumdaGUkbDAPTB18lm7JOXxjwzMg.V4UyQ_yQFPxHyaS25SQpfVtoHgBcRLjzKOad6Kf8EeQg.JPEG/IzaFVeUzkxR-J7pQIuJ--nNGl3XM.jpg?type=fb500_500"},{"title":"경성 스파이들의 암투 다룬 <유령> 촬영 시작, 설경구·이하늬·박소담·박해수·김동희 출연 (씨네21 ─ 국내뉴스)","contents":"<span class=\"ell\">씨네21</span>","link":"https://post.naver.com/viewer/postView.naver?volumeNo=30417141&memberNo=15205863&navigationType=push","retrieved":1629004867578,"image":"https://post-phinf.pstatic.net/MjAyMTAxMDdfMTk0/MDAxNjA5OTgzNjU5NDA1.tdh817xJdcW9soHeH4Ttv7UcA3PUH4Kkymq6U8u1UUog.aMvuPUlOkUNHd9J_UIPMDw9Y-muz1ttpjsOM-iKVZE0g.JPEG/I1nN97YbXHKPyfkULnnpxvlYmtXA.jpg?type=fb500_500"},{"title":"넷플릭스, <인간수업> 진한새 작가의 신작 <글리치> 제작 확정 (씨네21 ─ 국내뉴스)","contents":"<span class=\"ell\">씨네21</span>","link":"https://post.naver.com/viewer/postView.naver?volumeNo=30350688&memberNo=15205863&navigationType=push","retrieved":1629004867579,"image":"https://post-phinf.pstatic.net/MjAyMDEyMzBfMTQz/MDAxNjA5MjkxNzcyNjM5.dgW0vwljeFmhl4sUpxPgb6_pa3bUCoL8nL7bs-DomNYg.lxy8KxKaVaR7A3upasoPY9Zs15nC1WZI5sj2dkOlE8Ag.JPEG/Ik4yr-oMkIE9J5Eqt6Jtsw2EgEms.jpg?type=fb500_500"},{"title":"박지윤·장도연·재재·비비·최예나, 티빙의 첫 오리지널 콘텐츠 <여고추리반>으로 뭉친다 (씨네21 ─ 국내뉴스)","contents":"<span class=\"ell\">씨네21</span>","link":"https://post.naver.com/viewer/postView.naver?volumeNo=30249629&memberNo=15205863&navigationType=push","retrieved":1629004867582,"image":"https://post-phinf.pstatic.net/MjAyMDEyMTdfMTUw/MDAxNjA4MTg0NjA5MTU1.zrkgKbGkk_gDzY8e7ACByDQdo8Z-IOzMDZ7eV2Q9Pz0g.G7X82FAMbJr-bGpFpd0flBy7VKpoIvR6qpjmQpAsTX4g.JPEG/IR3oYqm2u2aIVd6aUl49kjqyLmTY.jpg?type=fb500_500"},{"title":"마블 슈퍼히어로 영화 출연한 마동석의 차기작은 <압구정 리포트> (씨네21 ─ 국내뉴스)","contents":"<span class=\"ell\">씨네21</span>","link":"https://post.naver.com/viewer/postView.naver?volumeNo=30105402&memberNo=15205863&navigationType=push","retrieved":1629004867582,"image":"https://post-phinf.pstatic.net/MjAyMDExMzBfMjY1/MDAxNjA2NzAyODE4OTkz.iLcBVpmBpoFUprfTPq-ea31_sfskq3ma4QR2mX1_i8Yg.q2x0Wncp2aZem1PthCajws-i4ucjeACd146f20DL1TIg.JPEG/IR5tUeUhoBSdMvb_JoEbuUG-P4jE.jpg?type=fb500_500"},{"title":"미국 ‘흙수저’들의 삶 다룬 영화 <힐빌리의 노래> 기자간담회 (씨네21 ─ 국내뉴스)","contents":"<span class=\"ell\">씨네21</span>","link":"https://post.naver.com/viewer/postView.naver?volumeNo=30087975&memberNo=15205863&navigationType=push","retrieved":1629004867584,"image":"https://post-phinf.pstatic.net/MjAyMDExMjdfMjI4/MDAxNjA2NDU4MjEyMjAw.g8yGD68Vtltjd2mCCx9eNnplDgKzBms30g0Lug1dI0Eg.mxn9l0W9CO9YnpKy6QXXJ6YunfLe_7vltjc2trDufm0g.JPEG/IrvHkvq6zJDb97fg03Z0uIMJtBy8.jpg?type=fb500_500"},{"title":"송강호, 김민희가 21세기 최고 배우로 선정된 이유 (씨네21 ─ 국내뉴스)","contents":"<span class=\"ell\">씨네21</span>","link":"https://post.naver.com/viewer/postView.naver?volumeNo=30086480&memberNo=15205863&navigationType=push","retrieved":1629004867586,"image":"https://post-phinf.pstatic.net/MjAyMDExMjdfMTEw/MDAxNjA2NDYxMzYxMzU4.UDQSIPX9jgvYs7WCoBQTMan0B9Zti3J43w0peF5Vu_Yg.JMSS9d5FFGHM9RJtyl0c9e2ecSoklxy-nk_M_UFEtW8g.JPEG/IR1shxZy3tGXX9lIZQcDoi3HJWjc.jpg?type=fb500_500"},{"title":"캐치온, SINCE 1995 특급 영화 구독 시대를 열다 (씨네21 ─ 국내뉴스)","contents":"<span class=\"ell\">씨네21</span>","link":"https://post.naver.com/viewer/postView.naver?volumeNo=30063990&memberNo=15205863&navigationType=push","retrieved":1629004867589,"image":"https://post-phinf.pstatic.net/MjAyMDExMjVfMjY1/MDAxNjA2MjgyMTE1MTEz.EIBsTvZQj1DtNTVxiHtjGlepO_m1urrByFbfFJsOrfMg.hf_az6QU4GIBbkQLNIKrparXIkqcFo2sCVHEjP-ot1Ug.JPEG/IC02Zmn0uyortDPAZrv0peoPmtn0.jpg?type=fb500_500"},{"title":"박신혜x전종서 <콜> 첫 반응... \"<추격자> <곡성> 생각나\" (씨네21 ─ 국내뉴스)","contents":"<span class=\"ell\">씨네21</span>","link":"https://post.naver.com/viewer/postView.naver?volumeNo=30062142&memberNo=15205863&navigationType=push","retrieved":1629004867590,"image":"https://post-phinf.pstatic.net/MjAyMDExMjVfMTQ4/MDAxNjA2MjcyMTQzNzk5.JBhM2_577IpDY7MwuHvAh0jgsR9u7XzAPOc2bKAYisYg.6mZSTgnxCpqYDhDf7vgDLY8Gh60akqdnmLU9Ad0XVNcg.JPEG/IZ6ZGopW9GRY1wL40zJmArT4bHWY.jpg?type=fb500_500"},{"title":"넷플릭스 영화 <맹크> 국내 첫 반응 (씨네21 ─ 국내뉴스)","contents":"<span class=\"ell\">씨네21</span>","link":"https://post.naver.com/viewer/postView.naver?volumeNo=30061978&memberNo=15205863&navigationType=push","retrieved":1629004867591,"image":"https://post-phinf.pstatic.net/MjAyMDExMjVfMTEx/MDAxNjA2MjcwNzg5MTA3.qGr102549XvoedFmxBo4-CI8HT5kNndck49jrIY19K4g.MhvOcrgZT_zxvMgSKhwa26FBC-Y2tEG0FuuIQVbA6Zog.JPEG/IFtVAMAHtx1DmBSac5aH1YAmT1Yo.jpg?type=fb500_500"},{"title":"수수료 없는 독립예술영화 전용관 통합예매 사이트 ‘인디앤아트’ 오픈 (씨네21 ─ 국내뉴스)","contents":"<span class=\"ell\">씨네21</span>","link":"https://post.naver.com/viewer/postView.naver?volumeNo=28782437&memberNo=15205863&navigationType=push","retrieved":1629004867592,"image":"https://post-phinf.pstatic.net/MjAyMDA3MTNfMjkz/MDAxNTk0NjIwOTI2Mzk2.-jC9LTBu3HxGbfS0Gxz7etxZRfEiLcXDK2X-rPDi28sg.eHN_gejXBGOHJ9udvPgCFxGK3fObR4waesqH0Yyd5hAg.JPEG/IbDh4lkiJ9oefxOVW28vvb63QNRo.jpg?type=fb500_500"},{"title":"<기생충> 아카데미 주요 4개 부문 수상 (씨네21 ─ 국내뉴스)","contents":"<span class=\"ell\">씨네21</span>","link":"https://post.naver.com/viewer/postView.naver?volumeNo=27467447&memberNo=15205863&navigationType=push","retrieved":1629004867594,"image":"https://post-phinf.pstatic.net/MjAyMDAyMTBfMjU2/MDAxNTgxMzI0Mjg1Mjkz._UPBvz07gYFqzP_muuQk7hNC-iVdq7l9NM7OsncWYSog.ow3mQAwt6-mJHscjgq91zQNYwsefU7pwL5OBSzN2UKMg.JPEG/IRgYA1VolByz1_JfhRwgmusZ1VUs.jpg?type=fb500_500"},{"title":"총상금 1,300만원의 주인공은 바로 당신! (씨네21 ─ 국내뉴스)","contents":"<span class=\"ell\">씨네21</span>","link":"https://post.naver.com/viewer/postView.naver?volumeNo=27038080&memberNo=15205863&navigationType=push","retrieved":1629004867595,"image":"https://post-phinf.pstatic.net/MjAxOTEyMDlfMTM2/MDAxNTc1ODY5NTE2MzMz.N3d2o7O0G0K9r1waLkUVseoV-NIOj5APBBe3B-OwXxQg.4OrlLCEotCr6ZeVLBK_6-KuWQgvh90EoRAIEwfoScA4g.JPEG/IbHhEVsu5uSmi9bIqys14P7YTzK4.jpg?type=fb500_500"},{"title":"생생한 현장감이 스토리텔링으로! CJ문화재단 ‘병원이라는 무대, 의사라는 캐릭터’ 특강 (씨네21 ─ 국내뉴스)","contents":"<span class=\"ell\">씨네21</span>","link":"https://post.naver.com/viewer/postView.naver?volumeNo=24033716&memberNo=15205863&navigationType=push","retrieved":1629004867596,"image":"https://post-phinf.pstatic.net/MjAxOTA4MjZfMTg3/MDAxNTY2Nzc4NDMwMDgw.bNJhzIujnn-62_6EmPy_G2y1SGWFauq4_nbpx5f2Ea0g.RbO_dYeB8FFRWX2Vhj_MBOQAGgSoU1fzTDTnIzMwxhog.JPEG/IOzMmxkMdyTNSDduyv_D7sA_tH9Y.jpg?type=fb500_500"},{"title":"제15회 제천국제음악영화제 오늘 8일 개막 (씨네21 ─ 국내뉴스)","contents":"<span class=\"ell\">씨네21</span>","link":"https://post.naver.com/viewer/postView.naver?volumeNo=23303883&memberNo=15205863&navigationType=push","retrieved":1629004867598,"image":"https://post-phinf.pstatic.net/MjAxOTA4MDhfMjEz/MDAxNTY1MjMxMzIyMDA2.ASS6QQ5NQhiw3btCn2wey8hE_3chuBV1jva0rvhjIGIg.L2t8jXw-fE61cVSmcz0zZSt6mpLwVmRAba3GAeK_NdIg.JPEG/Iq0WdHvS2i7UkHJMQVEAHJNT8_1Y.jpg?type=fb500_500"},{"title":"<토이 스토리>의 영원한 버즈, 원로 성우 박일 별세 (씨네21 ─ 국내뉴스)","contents":"<span class=\"ell\">씨네21</span>","link":"https://post.naver.com/viewer/postView.naver?volumeNo=23075860&memberNo=15205863&navigationType=push","retrieved":1629004867598,"image":"https://post-phinf.pstatic.net/MjAxOTA4MDFfNzYg/MDAxNTY0NjI3NzEyNzQw.i86rUyd_mBFYJhg2LuGNlvvhUEW_x2QfmggmVOImH0Yg.AwFx6oGglz4qT5lmOfRfJNtx1GBHoF0wjnHCAigYrjIg.JPEG/Ib9BvFS2jYtol1CTXbQf4eGZKZhs.jpg?type=fb500_500"}]}