{"title":"다음영화 뉴스 ─ 인기","url":"https://movie.daum.net/contents/news?type=popular","favicon":"https://movie.daum.net/contents/favicon.ico","elements":[{"title":"안젤리나 졸리X마동석 '이터널스', 가슴 웅장해지는 마블 뉴 히어로 군단","contents":"[마이데일리 = 김나라 기자] 마블 '어벤져스' 시리즈의 전설을 이어갈 영화 '이터널스'가 티저 포스터와 메인 예고편을 전격 공개했다. '이터널스'는 19일, 티저 포스터와 예고편을 오픈하며 기대감을 끌어올렸다. 티저 포스터 속 떠오르는 태양을 뒤로하고 10명의 '이터널스' 실루엣이 시선을 이끈다. 오랜 세월 인류에게 그 모습을 드러내지 않았던 '이터널","link":"https://movie.v.daum.net/v/20210820102247618","retrieved":1629433172334,"image":"https://img1.daumcdn.net/thumb/S732x228/?fname=https%3A%2F%2Ft1.daumcdn.net%2Fnews%2F202108%2F20%2Fmydaily%2F20210820102248060nyhv.jpg"},{"title":"벼랑 끝 영화계 \"韓 영화 산업 붕괴 중..국고 직접 지원을\" 호소","contents":"[서울경제] 영화계가 20일 코로나 19로 인한 영화 산업 피해의 심각성을 강조하면서 정부에 직접적인 국고 지원을 호소하고 나섰다. 현재 극장 관객 수는 코로나 19 이전 대비 70% 이상 줄어들었고, 당장 크게 회복될 기미도 보이지 않고 있다. 이에 한국영화프로듀서조합, 영화마케팅사협회, 한국영화감독조합 이사회, 한국영화미술감독조합, 한국영화녹음감독협","link":"https://movie.v.daum.net/v/20210820162013117","retrieved":1629447440665,"image":"https://img1.daumcdn.net/thumb/S732x228/?fname=https%3A%2F%2Ft1.daumcdn.net%2Fnews%2F202108%2F20%2Fseouleconomy%2F20210820162016684jdqf.jpg"},{"title":"마약·폭력, 톰 크루즈와 라이벌이었던 배우의 몰락","contents":"[양형석 기자] 메이저리그 최고의 강타자 중 한 명인 마이크 트라웃(LA 에인절스)은 현재 오른쪽 종아리 부상으로 개점 휴업 중이다. 하지만 트라웃은 마이너리그로 내려가거나 다음 시즌 팀에서 쫓겨날 걱정은 전혀 하지 않는다. 지난 2019년 3월 에인절스와 12년4억2650만 달러 계약을 맺은 트라웃은 만38세가 되는 오는 2030년까지 연 3700만 달러","link":"https://movie.v.daum.net/v/20210820100900126","retrieved":1629424461072,"image":"https://img1.daumcdn.net/thumb/S384x240/?fname=https%3A%2F%2Ft1.daumcdn.net%2Fnews%2F202108%2F20%2Fohmynews%2F20210820100901487uzsz.jpg"},{"title":"'블랙 위도우' '모가디슈' 개봉..7월 극장 관객수 전년 대비 24.2%↑","contents":"[스타뉴스 전형화 기자] '블랙 위도우' '모가디슈' 등 대작 영화들이 개봉한 덕분에 사회적 거리두기 격상에도 불구하고 7월 극장 전체 매출액과 관객수는 전년에 비해 증가했다. 20일 영진위 한국영화산업결산 자료에 따르면 7월 극장 전체 매출액은 683억 원으로 전년 동월 대비 44.7%(211억 원 ↑) 증가했고, 7월 전체 관객 수는 698만 명으로 전","link":"https://movie.v.daum.net/v/20210820153624813","retrieved":1629450936701,"image":"https://img1.daumcdn.net/thumb/S384x240/?fname=https%3A%2F%2Ft1.daumcdn.net%2Fnews%2F202108%2F20%2Fstarnews%2F20210820153627248mmrt.jpg"},{"title":"[단독] 조진웅·김희애·류혜영, '데드맨' 캐스팅..'믿보배' 조합 기대","contents":"(엑스포츠뉴스 김현정 기자) 배우 조진웅, 김희애, 류혜영이 영화 '데드맨'으로 뭉칠지 주목된다. 20일 엑스포츠뉴스 취재 결과 영화 '데드맨'에 조진웅, 김희애, 류혜영이 출연을 검토하고 있다.&nbsp; '데드맨'은 웨이브 오리지널로 선보일 예정이며 극장 개봉도 추진하고 있는 것으로 알려졌다.&nbsp;팔레트픽처스가 제작, 하준원 감독이 메가폰을 잡으며 11월에 촬영을","link":"https://movie.v.daum.net/v/20210820110007128","retrieved":1629436453051,"image":"https://img1.daumcdn.net/thumb/S384x240/?fname=https%3A%2F%2Ft1.daumcdn.net%2Fnews%2F202108%2F20%2Fxportsnews%2F20210820110008631fzhy.jpg"},{"title":"지하세계에서 펼쳐지는 소외된 노동의 풍경화","contents":"[김상목 기자] 지하철은 한국의 대도시 권역에서는 버스와 함께 시민의 발로 기능하는 대표적 교통수단이다. 특히 버스에 비해 일정 규모 이상, 소위 메트로폴리스 급 이상의 광역도시권에서 볼 수 있는 특성 때문에 단순한 교통수단을 넘어 도시정책의 핵심적인 요소로 인정받는 영역이기도 하다. 지하철 관련 공약은 광역지자체 선거에서 늘 최우선 과제로 자리매김하고 있","link":"https://movie.v.daum.net/v/20210820143900966","retrieved":1629447440672,"image":"https://img1.daumcdn.net/thumb/S384x240/?fname=https%3A%2F%2Ft1.daumcdn.net%2Fnews%2F202108%2F20%2Fohmynews%2F20210820143901656shlm.jpg"},{"title":"'경쟁률 1000:1' 뚫은 김재범 \"악역인데 경사였죠\"[인터뷰]","contents":"‘인질’에서 납치범 리더 최기완 역을 연기한 김재범(사진=NEW)[이데일리 스타in 박미애 기자] 충무로가 주목해야 할 ‘뉴페이스’가 탄생했다. 박스오피스 1위를 달리는 영화 ‘인질’의 김재범이다. 연기도 좋지만, 1000대 1의 경쟁률을 뚫고 캐스팅된 사실로도 주목받고 있다. 김재범은 최근 ‘인질’로 진행한 인터뷰에서 “경쟁률이 그렇게 높은 줄은 나중에","link":"https://movie.v.daum.net/v/20210821142708955","retrieved":1629526719575,"image":"https://img1.daumcdn.net/thumb/S384x240/?fname=https%3A%2F%2Ft1.daumcdn.net%2Fnews%2F202108%2F21%2FEdaily%2F20210821142710849psln.jpg"},{"title":"휴 잭맨 '레미니센스', 신화와 고전 누아르 영화의 결합","contents":"[마이데일리 = 곽명동 기자]8월 25일 개봉하는 영화 '레미니센스'의 리사 조이 감독이 이번 영화에 신화와 고전 누아르 영화를 조화시켰다고 밝혀 눈길을 끈다. '레미니센스'는 가까운 미래, 사라진 사랑을 찾아나선 한 남자가 기억을 통한 과거로의 여행에 얽힌 음모와 진실을 마주하며 벌어지는 위험한 추적을 그린다. 영화의 제목인 레미니센스(reminisce","link":"https://movie.v.daum.net/v/20210820091957277","retrieved":1629447440669,"image":"https://img1.daumcdn.net/thumb/S384x240/?fname=https%3A%2F%2Ft1.daumcdn.net%2Fnews%2F202108%2F20%2Fmydaily%2F20210820091957173zwcd.jpg"},{"title":"'동성애는 틀렸다'는 믿음에서 시작된 비극","contents":"[김형욱 기자] &nbsp;        ▲ &nbsp;넷플릭스 오리지널 다큐멘터리 &lt;프레이 어웨이&gt; 포스터.    ⓒ 넷플릭스  &nbsp;지난 2013년 6월, 미국을 넘어 전 세계 최대 전환 치료 단체 '엑소더스 인터내셔널'(이하, '엑소더스')이 문을 닫았다. 이 단체는 녹록지 않은 역사와 전통 그리고 힘을 자랑했는데, 1976년에 시작되어 미국과 캐나다 등 북미에 250개","link":"https://movie.v.daum.net/v/20210821125401949","retrieved":1629519566825,"image":"https://img1.daumcdn.net/thumb/S384x240/?fname=https%3A%2F%2Ft1.daumcdn.net%2Fnews%2F202108%2F21%2Fohmynews%2F20210821125402200bigh.jpg"},{"title":"\"가족 관객의 압도적 선택\"..'싱크홀', 세대별 관전 포인트 공개","contents":"[마이데일리 = 김나라 기자] 영화 '싱크홀'이 10대부터 50대까지 전 세대를 사로잡은 연령대별 관전 포인트를 공개했다. '싱크홀'(감독 김지훈)은 개봉 2주 차에도 폭발적인 입소문 흥행을 이어가고 있다. 특히 지난 주말 이틀 연속으로 2021년 한국 영화 일일 최다 관객수 기록을 세우며 확실한 주말 강자임을 입증한 바. 이번 주말에도 전 세대 관객들의","link":"https://movie.v.daum.net/v/20210820090848916","retrieved":1629465706607,"image":"https://img1.daumcdn.net/thumb/S384x240/?fname=https%3A%2F%2Ft1.daumcdn.net%2Fnews%2F202108%2F20%2Fmydaily%2F20210820090848278rkyv.jpg"},{"title":"전설의 공포게임을 영화로 '화이트데이: 부서진 결계' 론칭 예고편 공개","contents":"[서울경제] ‘화이트데이: 부서진 결계’가 9월 개봉을 앞두고 론칭 예고편을 공개했다. ‘화이트데이: 부서진 결계’는 늦은 밤 학교에서 일어나는 기이한 현상을 일으키는 악령으로부터 친구들을 구하기 위한 사투를 그린 공포 판타지 영화. 올해로 발매 20주년을 맞은 국산 PC 패키지 공포 게임의 전설 ‘화이트데이: 학교라는 이름의 미궁’을 바탕으로 퇴마를","link":"https://movie.v.daum.net/v/20210820091930263","retrieved":1629501312843,"image":"https://img1.daumcdn.net/thumb/S384x240/?fname=https%3A%2F%2Ft1.daumcdn.net%2Fnews%2F202108%2F20%2Fseouleconomy%2F20210820091936462ojde.jpg"},{"title":"'보이스' 보이스피싱의 A to Z","contents":"[티브이데일리 최하나 기자] 수많은 실제 사례와 다양한 전문가의 자문 등 철저한 사전조사를 바탕으로 탄생한 영화 '보이스'의 프로덕션 비하인드를 공개한다. 영화 '보이스'(감독 김선 김곡·제작 수필름)는 보이스피싱 조직의 덫에 걸려 모든 것을 잃게 된 서준(변요한)이 빼앗긴 돈을 되찾기 위해 중국에 있는 본거지에 잠입, 보이스피싱 설계자 곽프로(김무열)를","link":"https://movie.v.daum.net/v/20210820100522914","retrieved":1629506752283,"image":"https://img1.daumcdn.net/thumb/S384x240/?fname=https%3A%2F%2Ft1.daumcdn.net%2Fnews%2F202108%2F20%2Ftvdaily%2F20210820100523260xwku.jpg"},{"title":"[SC초점] \"秋극장 살리는 마블\"..9월 '샹치'X11월 '이터널스' 출격에 '마블민국' 들썩","contents":"[스포츠조선 조지영 기자] 올해 가을 극장은 마블로 시작해 마블로 끝난다. 가을 극장의 포문은 9월 액션 영화 '샹치와 텐 링즈의 전설'(데스틴 다니엘 크리튼 감독)이, 가을의 마지막에는 배우 마동석의 첫 마블 진출작인 액션 영화 '이터널스'(클로이 자오 감독)가 연달아 가을 극장에 출사표를 던졌다. 먼저 내달 1일 전 세계 최초 국내 개봉하","link":"https://movie.v.daum.net/v/20210820112749232","retrieved":1629551993880,"image":"https://img1.daumcdn.net/thumb/S384x240/?fname=https%3A%2F%2Ft1.daumcdn.net%2Fnews%2F202108%2F20%2FSpoChosun%2F20210820112750087lcvz.jpg"},{"title":"[SC현장] \"아픈 트라우마 떠올라\"..'최선의 삶' 방민아→한성민, 최선의 날것이 만든 문제작 (종합)","contents":"[스포츠조선 조지영 기자] 올해 가장 솔직하고 과감한, 최선의 날것이 담긴 문제작이 가을 극장을 찾았다. 더 나아지기 위해서 기꺼이 더 나빠졌던 소녀들의 이상했고 무서웠고 좋아했던 그 시절의 드라마를 담은 휴먼 영화 '최선의 삶'(이우정 감독, 마일스톤컴퍼니 제작). 20일 오후 서울 용산구 이촌동 CGV 용산아이파크몰에서 진행된 '최선의","link":"https://movie.v.daum.net/v/20210820162538288","retrieved":1629515802294,"image":"https://img1.daumcdn.net/thumb/S384x240/?fname=https%3A%2F%2Ft1.daumcdn.net%2Fnews%2F202108%2F20%2FSpoChosun%2F20210820162539019qldl.jpg"},{"title":"아센디오, 블록버스터 영화 '하이브'에 자이언트스텝 전격 합류","contents":"종합 콘텐츠 기업 아센디오(각자대표 신동철·강재현)는 블록버스터 영화 ‘하이브’ 제작과 관련, 영화의 VFX를 포함한 시각 및 특수효과 기술에 대해 리얼타임 콘텐츠 솔루션 기업 자이언트스텝과 업무협약을 체결했다고 20일 밝혔다. 향후 자이언트스텝은 하이브에 대한 시각효과(Visual Effects/VFX)를 위해 VFX 프리 프로덕션, On-Set 수","link":"https://movie.v.daum.net/v/20210820112905271","retrieved":1629551993888,"image":"https://img1.daumcdn.net/thumb/S384x240/?fname=https%3A%2F%2Ft1.daumcdn.net%2Fnews%2F202108%2F20%2FSpoHankook%2F20210820112906216hqhk.jpg"},{"title":"'실: 인연의 시작' 10월 개봉..스다 마사키·고마츠 나나 세 번째 호흡","contents":"스다 마사키와 고마츠 나나가 주연을 맡은 영화 '실: 인연의 시작'이 10월 개봉을 확정했다.㈜디스테이션는 20일 '실: 인연의 시작' 개봉 소식과 함께 포스터를 공개했다. 이 영화는 일본 가수 나카지마 미유키의 대표곡 ‘糸’(실)을 모티브로 제작됐다.'실: 인연의 시작'은 열두 살에 만나 서로의 첫사랑이 된 렌과 아오이가 18년의 세월 동안 만남과 헤어짐","link":"https://movie.v.daum.net/v/20210820095618476","retrieved":1629555220955,"image":"https://img1.daumcdn.net/thumb/S384x240/?fname=https%3A%2F%2Ft1.daumcdn.net%2Fnews%2F202108%2F20%2Fdailian%2F20210820095624996rlig.jpg"},{"title":"가족의 탄생이 이렇게 어렵습니다","contents":"[김상목 기자] ▲ &nbsp;&lt;박강아름 결혼하다&gt; 포스터    ⓒ 영화사 진진  &nbsp;1_&lt;가장 무도회&gt;에서 &lt;결혼하다&gt;로의 전환&nbsp;전작 &lt;박강아름의 가장 무도회&gt;(2015)에서 지독한 외모 콤플렉스에 시달리던 박강아름 감독은 자신과 자신의 신체를 직접 실험대상으로 활용해 한국 사회가 여성에게 요구하는 '여성성'에 대해 관찰하는 작업을 시도했다. '모태솔","link":"https://movie.v.daum.net/v/20210820101203255","retrieved":1629522793625,"image":"https://img1.daumcdn.net/thumb/S384x240/?fname=https%3A%2F%2Ft1.daumcdn.net%2Fnews%2F202108%2F20%2Fohmynews%2F20210820101206741tlst.jpg"},{"title":"영화 '습도 다소 높음', '찬실이는 복도많지'→'좋좋소' 잇는 하이퍼리얼리즘 코미디","contents":"(엑스포츠뉴스 이창규 기자)&nbsp;더 이상의 판타지는 없다. 관찰 예능이 많은 이들을 즐겁게 했듯 영화와 드라마도 현실 고증이 대세다. 먼저 장기 흥행으로 의미있는 스코어를 기록한 '찬실이는 복도 많지'는 영화 프로듀서였지만 지금은 일이 똑 끊겨 먹고 살길이 막막한 ‘찬실’이에게 닥쳐오는 일들을 유쾌하게 그려낸 작품이다. 많은 영화인들은 물론, 팍팍했던 삶에","link":"https://movie.v.daum.net/v/20210820094512120","retrieved":1629540993068,"image":"https://img1.daumcdn.net/thumb/S384x240/?fname=https%3A%2F%2Ft1.daumcdn.net%2Fnews%2F202108%2F20%2Fxportsnews%2F20210820094513365cfqa.jpg"},{"title":"류경수 \"'인질'서 날아다닌 황정민, 나도 저렇게 될 수 있을까\" [인터뷰 종합]","contents":"(엑스포츠뉴스 김유진 기자) 배우 류경수가 '인질'로 함께 호흡을 맞춘 선배 배우 황정민을 향한 남다른 마음을 전하며 앞으로도 꾸준히 연기에 매진하겠다는 의지를 전했다. 류경수는 20일 오전 온라인으로 진행된 영화 '인질'(감독 필감성) 인터뷰에서 영화와 함께 다양한 이야기를 전했다. '인질'은 어느 날 새벽, 증거도 목격자도 없이 납치된 배우 황정민을","link":"https://movie.v.daum.net/v/20210820145003300","retrieved":1629551993885,"image":"https://img1.daumcdn.net/thumb/S384x240/?fname=https%3A%2F%2Ft1.daumcdn.net%2Fnews%2F202108%2F20%2Fxportsnews%2F20210820145006224mmit.jpg"},{"title":"여름 극장가 끌고 가는 외유내강 [★날선무비]","contents":"[스타뉴스 김미화 기자] /사진='모가디슈', '인질' 포스터영화 제작사 외유내강이 여름 극장가를 이끌고 있다. 코로나 19로 인한 사회적 거리두기 4단계 조치가 지속되고 힘든 시기임에도, 극장가 최고 성수기인 여름 시장에 용기 있게 두 편의 영화를 선보였다. 영화 '모가디슈'가 앞서서 끌었고, '인질'이 뒤에서 밀고 있다. 지난달 개봉한 영화 '모가디슈'","link":"https://movie.v.daum.net/v/20210821133001301","retrieved":1629573135973,"image":"https://img1.daumcdn.net/thumb/S384x240/?fname=https%3A%2F%2Ft1.daumcdn.net%2Fnews%2F202108%2F21%2Fstarnews%2F20210821133002668badi.jpg"}]}