{"title":"네이버TV연예 ─ 영화","url":"https://entertain.naver.com/movie","favicon":"https://entertain.naver.com/favicon.ico","elements":[{"title":"[공식]김혜수X유연석, 제42회 청룡영화상 진행 맡는다…4년 연속 공동 MC","contents":"[스포츠조선 이승미 기자]배우 김혜수와 유연석이 올해 청룡영화상에서도 빛나는 호흡을 맞춘다. 김혜수와 유연석이 오는 11월 26일 오후 8시 30분 여의도 KBS홀에서 개최되는 제42회 청룡영화상 시상식 MC로 나선","link":"https://entertain.naver.com/movie/now/read?oid=076&aid=0003800882","retrieved":1636586178811},{"title":"영화 '부활' 구수환 감독, 도산인상 사회통합상 수상","contents":"2021년 도산인상 사회통합상과 행정안전부 장관 표창수여자로 구수환 사단법인 이태석 재단 이사장이 선정됐다. 구수환 이사장은 11월 9일 몬드리안 서울 이태원에서 개최된 제32회 '도산의 밤' 및 2021년 '도산인","link":"https://entertain.naver.com/movie/now/read?oid=108&aid=0003003746","retrieved":1636586178811},{"title":"김혜수·유연석, 4년 연속 청룡영화상 MC [공식]","contents":"[마이데일리 = 양유진 기자] 배우 김혜수와 유연석이 오는 26일 오후 8시 30분 여의도 KBS홀에서 개최되는 제42회 청룡영화상 시상식 MC로 나서 올 한 해 한국영화의 성과를 되새긴다. 김혜수는 1993년 제1","link":"https://entertain.naver.com/movie/now/read?oid=117&aid=0003554485","retrieved":1636586178811},{"title":"김종국은 달린다, 디즈니+ '런닝맨: 뛰는 놈 위에 노는 놈'","contents":"12일(금) 공식 런칭하는 디즈니플러스(디즈니+)를 통해 '런닝맨' 스핀오프를 만난다. SBS의 장수 예능 프로그램이자 한류 예능의 선두주자로 자리매김한 &lt;런닝맨&gt;의 첫 번째 공식 스핀오프인 디즈니+ 오리지널 &lt;런닝","link":"https://entertain.naver.com/movie/now/read?oid=438&aid=0000040574","retrieved":1636586178811},{"title":"김혜수=28년, 유연석=4년..청룡영화상 MC 확정 '26일 개최' [공식입장]","contents":"[OSEN=박소영 기자] 배우 김혜수와 유연석이 오는 11월 26일(금) 오후 8시 30분 여의도 KBS홀에서 개최되는 제42회 청룡영화상 시상식 MC로 나서 올 한 해 한국영화의 성과를 되새긴다. 배우 김혜수는 1","link":"https://entertain.naver.com/movie/now/read?oid=109&aid=0004508380","retrieved":1636586178811},{"title":"김혜수·유연석, 4년 연속 ‘청룡영화상’ 공동 MC 확정 (공식)","contents":"배우 김혜수와 유연석이 오는 26일 오후 8시 30분 여의도 KBS홀에서 개최되는 제42회 청룡영화상 시상식 MC로 나서 올 한 해 한국영화의 성과를 되새긴다. 배우 김혜수는 1993년 제14회 청룡영화상 시상식부터","link":"https://entertain.naver.com/movie/now/read?oid=410&aid=0000830354","retrieved":1636586178811},{"title":"위드 코로나 첫 한국영화 ‘강릉’ 전체 2위로 출발[박스오피스]","contents":"[뉴스엔 배효주 기자] '강릉'이 한국영화 박스오피스 1위를 차지했다. 11월 11일 영화진흥위원회 통합전산망 집계에 따르면 10일 개봉한 유오성, 장혁의 범죄 액션 누아르 '강릉'이 개봉 첫날 3만2,859명을 모","link":"https://entertain.naver.com/movie/now/read?oid=609&aid=0000509768","retrieved":1636586178818},{"title":"'1984 최동원', 오늘(11일) 개봉..미공개 영상→조진웅 내레이션 관람포인트 셋","contents":"[헤럴드POP=천윤혜기자]1984년 가을 한국시리즈 7차전 4승 1패의 주인공, 대한민국 부산의 심장 무쇠팔 최동원의 인생 경기를 담은 최초의 다큐멘터리 영화 '1984 최동원'이 뜨거운 관심 속 드디어 오늘 개봉하","link":"https://entertain.naver.com/movie/now/read?oid=112&aid=0003497058","retrieved":1636586178818},{"title":"‘청룡영화상’ 김혜수X유연석, 4년 연속 공동 MC 확정(공식)","contents":"[뉴스엔 이민지 기자] 배우 김혜수, 유연석이 4년 연속 청룡영화상 MC로 호흡을 맞춘다. 배우 김혜수와 유연석이 오는 11월 26일 오후 8시 30분 여의도 KBS홀에서 개최되는 제42회 청룡영화상 시상식 MC로","link":"https://entertain.naver.com/movie/now/read?oid=609&aid=0000509767","retrieved":1636586178818},{"title":"[공식] 김혜수X유연석, 4년 연속 '청룡영화상' 공동 MC 확정","contents":"[텐아시아=차혜영 기자] 배우 김혜수와 유연석이 오는 11월 26일(금) 오후 8시 30분 여의도 KBS홀에서 개최되는 제42회 청룡영화상 시상식 MC로 나서 올 한 해 한국영화의 성과를 되새긴다. 배우 김혜수는 1","link":"https://entertain.naver.com/movie/now/read?oid=312&aid=0000510788","retrieved":1636586178818},{"title":"김혜수·유연석 4년 연속 청룡영화상 공동 MC…26일 개최","contents":"(서울=뉴스1) 윤효정 기자 = 배우 김혜수와 유연석이 청룡영화상 진행자로 다시 만난다. 김혜수와 유연석은 오는 26일 열리는 제42회 청룡영화상 시상식 MC로 나서 올 한 해 한국영화의 성과를 되새긴다. 김혜수는","link":"https://entertain.naver.com/movie/now/read?oid=421&aid=0005716046","retrieved":1636586178818},{"title":"20년 전 '오아시스' 커플 설경구 문소리, '영평상' 주연상 수상","contents":"'자산어보' '모가디슈' 4관왕 20년 전 이창동 감독 영화 '오아시스'(2002)에서 진한 여운을 남긴 배우 설경구와 문소리가 20년 후 영화 시상식에서 나란히 주연상을 수상해 눈길을 끈다. 10일 오후 서울 중구","link":"https://entertain.naver.com/movie/now/read?oid=629&aid=0000115495","retrieved":1636586178828},{"title":"덱스터, 버추얼 프로덕션 스튜디오 ‘D1’ 런칭","contents":"시각특수효과(VFX) 및 콘텐츠 전문기업 (주)덱스터스튜디오(대표 김욱·강종익)의 버추얼 프로덕션 스튜디오가 베일을 벗었다. 덱스터스튜디오는 경기도 파주에 제1호 버추얼 프로덕션 스튜디오 ‘D1’(디원)을 런칭했다고 밝","link":"https://entertain.naver.com/movie/now/read?oid=438&aid=0000040567","retrieved":1636586178828},{"title":"'강릉', 동시기 개봉작 박스오피스 1위..위드 코로나 시기 첫 韓 영화 자존심[공식]","contents":"[헤럴드POP=천윤혜기자]유오성x장혁의 범죄 액션 누아르 '강릉'이 개봉 첫날 동시기 개봉작 박스오피스 1위에 오르며 흥행 신호탄을 쏘아 올렸다. 위드 코로나 시행 첫 한국 영화 '강릉'이 거센 입소문 열풍을 이어가","link":"https://entertain.naver.com/movie/now/read?oid=112&aid=0003497047","retrieved":1636586178831},{"title":"‘자산어보’·‘모가디슈’…영평상 각 4관왕","contents":"이준익 감독의 ‘자산어보’와 류승완 감독의 ‘모가디슈’가 영평상에서 각각 4관왕에 올랐다. 10일 서울 중구 통일로 KG타워 하모니홀에서 진행된 ‘제41회 영화평론가협회상’(영평상) 시상식에서 ‘자산어부’는 작품상의","link":"https://entertain.naver.com/movie/now/read?oid=021&aid=0002492035","retrieved":1636586178831},{"title":"유오성·장혁 주연 ‘강릉’, 박스오피스 2위로 출발","contents":"배우 유오성·장혁이 주연을 맡은 영화 ‘강릉’이 박스오피스 2위로 출발했다. 영화관입장권통합전산망에 따르면 10일 개봉한 ‘강릉’은 전국 관객 3만2790명을 모았다. 1위 자리는 8만9347명을 모은 ‘이터널스’가","link":"https://entertain.naver.com/movie/now/read?oid=021&aid=0002492034","retrieved":1636586178831},{"title":"[TEN인터뷰] '닥터 브레인' 김지운 감독 \"첫 드라마, 엔딩 떡밥 만들기가 관건\"","contents":"[텐아시아=김지원 기자] \"처음 이 작품을 제안 받았을 때는 영화로 만들어도 되지 않을까 싶었어요. 코로나 이전이었고, OTT가 부흥하기 전이었죠. 그러다가 이 이야기를 풍요롭고 깊게 접근하면 더 의미 있지 않을까","link":"https://entertain.naver.com/movie/now/read?oid=312&aid=0000510767","retrieved":1636582562044},{"title":"문소리 \"(설)경구 오빠, 못다 한 멜로 합시다\" 러브콜…'영평상' 초토화시킨 수상 소감 [MD픽]","contents":"[마이데일리 = 김나라 기자] 배우 설경구와 문소리가 나란히 '영평상' 남녀 주연상을 수상한 가운데, 이들의 남다른 소감 또한 이목을 끌었다. 10일 오후 서울 중구 순화동 KG타워에선 '제41회 영평상'(한국영화평","link":"https://entertain.naver.com/movie/now/read?oid=117&aid=0003554448","retrieved":1636582562044},{"title":"TV시네마 '사이렌' 기이한 공간 파헤치는 '속물 변호사'","contents":"기사내용 요약 KBS 12일 SF 미스테리 스릴러극 방송 [서울=뉴시스]고다연 인턴 기자 = TV 시네마 '사이렌'이 관전 포인트를 공개했다. 12일 방송 예정인 UHD KBS 드라마 스페셜 2021-TV시네마 '사","link":"https://entertain.naver.com/movie/now/read?oid=003&aid=0010825312","retrieved":1636582562059},{"title":"[동정] 오세훈 서울시장, 영화 '탄생' 제작 발표회 참석","contents":"▲ 오세훈 서울시장은 11일 오후 3시 세종문화회관 세종S씨어터에서 열리는 영화 '탄생' 제작 발표회에 참석한다. '탄생'은 한국인 최초의 천주교 사제인 김대건 신부의 일대기를 그린 영화로, 내년 개봉할 예정이다.","link":"https://entertain.naver.com/movie/now/read?oid=001&aid=0012784650","retrieved":1636582562059},{"title":"韓 영화의 저력…리메이크작, 중화권 극장가 접수 [TF확대경]","contents":"한국 영화·합작 영화 대신 리메이크작 줄줄이 개봉…흥행 릴레이 코로나19 팬데믹으로 전 세계 극장가의 침체가 이어진 가운데 2021년 중화권 극장가에서 한국 영화를 원작으로 한 리메이크 작품들의 선전이 눈에 띈다.","link":"https://entertain.naver.com/movie/now/read?oid=629&aid=0000115491","retrieved":1636575388705},{"title":"영화 ‘태일이’ 관람한 김재연 대선후보 “지금 시대 전태일들의 ‘전국민노동법’ 만들겠다”","contents":"[스포츠경향] 진보당 김재연 대선 후보가 지난 9일 광화문 씨네큐브에서 배달노동자들과 함께 전태일 열사의 생애를 담은 영화 ‘태일이’를 관람했다고 전했다. 김 후보는 영화 관람에 앞서 배달노동자들을 만나“‘근로기준법","link":"https://entertain.naver.com/movie/now/read?oid=144&aid=0000773552","retrieved":1636561455564},{"title":"[인터뷰]류승룡 \"모두 치유받고 관계 속에 성장하기를\"②","contents":"\"원제는 '입술은 안돼요'…놀랐지만 바꾸길 잘해\" 류승룡은 조은지 감독의 영화 '장르만 로맨스'에 합류한 배경을 '오직 시나리오만 보고 선택했다'고 답했다. '장르만 로맨스'는 20년 차 베테랑 배우 조은지의 첫 장","link":"https://entertain.naver.com/movie/now/read?oid=629&aid=0000115488","retrieved":1636557408293},{"title":"[인터뷰]류승룡 \"난이도? 사극보다 현대극이 훨씬 어렵죠\"①","contents":"영화 '장르만 로맨스'로 스크린 컴백…'짠내 코미디 귀환' 배우 류승룡이 현대극으로 돌아왔다. 특유의 짠내 가득한 코믹 연기는 물론 배우 고유의 아우라도 가감없이 뿜어냈다. 류승룡이라는 배우를 충무로에 각인시킨 '내","link":"https://entertain.naver.com/movie/now/read?oid=629&aid=0000115481","retrieved":1636557408294},{"title":"설경구·문소리, 제41회 영평상 남녀주연상…'자산어보' 최우수작품상 [종합]","contents":"(엑스포츠뉴스 김유진 기자) 배우 설경구와 문소리가 영평상 남녀주연상의 주인공이 됐다. 최우수작품상은 '자산어보'(감독 이준익)가 차지했다. 10일 서울 중구 통일로 KG타워 하모니홀에서 배우 조한철과 이다슬 프리랜","link":"https://entertain.naver.com/movie/now/read?oid=311&aid=0001371877","retrieved":1636550521192}]}