{"title":"네이버TV연예 ─ 영화","url":"https://entertain.naver.com/movie","favicon":"https://entertain.naver.com/favicon.ico","elements":[{"title":"‘DC 슈퍼펫’ 북미 박스 1위..여름대전 복명되나","contents":"8월 국내 극장가에 상륙하는 ‘DC 슈퍼펫’이 북미에서 먼저 개봉한 가운데 현지 박스오피스를 휩쓸며 흥행 신호탄을 쏘아올렸다. 1일 박스오피스 모조에 따르면 지난 29일 북미에서 개봉한 ‘DC 슈퍼펫’은 개봉 첫 주","link":"https://entertain.naver.com/movie/now/read?oid=009&aid=0004998886","retrieved":1659335530940},{"title":"'한산' 개봉 첫 주말 1위…누적관객 227만명","contents":"이순신 장군의 한산해전을 그린 영화 '한산: 용의 출현'이 개봉 첫 주말 박스오피스 1위를 기록했습니다. 영화진흥위원회에 따르면 '한산'은 지난 주말 사흘 동안 관객 163만2천여 명을 동원해 박스오피스 정상에 올랐","link":"https://entertain.naver.com/movie/now/read?oid=422&aid=0000553727","retrieved":1659335530947},{"title":"윌 스미스, '오스카 폭행' 사과영상 공개 \"용납될 수 없는 행동\"","contents":"윌 스미스(사진=윌 스미스 인스타그램) 할리우드 배우 윌 스미스가 오스카 시상식에서 물의를 일으킨 것에 대해 사과했다. 스미스는 지난달 29일(현지시각) 자신의 인스타그램에 게재한 6분가량의 영상에 “록 당신에게 사","link":"https://entertain.naver.com/movie/now/read?oid=018&aid=0005281471","retrieved":1659335530949},{"title":"김동하 장편소설 '한산: 태동하는 반격' 오디오북으로","contents":"영화 '한산:용의 출현'의 흥행속 김동하 작가의 장편 소설 '한산: 태동하는 반격'이 윌라 오디오북으로 출시됐다. 소설은 이순신 장군의 한산대첩을 하나의 거대한 전투로 향하는 시점으로 묘사한 작품이다. 윌라는 영화","link":"https://entertain.naver.com/movie/now/read?oid=003&aid=0011338736","retrieved":1659335530950},{"title":"어린 딸 두고 도망친 엄마, 대체 왜 그랬을까","contents":"영화 &lt;로스트 도터&gt; ▲ 영화 &lt;로스트 도터&gt; 스틸 ⓒ 그린나래미디어(주) 대학에서 비교문학 교수인 레다(올리비아 콜맨)는 휴가 겸 일을 하러 한적한 그리스에 왔다. 젠틀한 30년 지기 관리인 라일(에드 해리스)과","link":"https://entertain.naver.com/movie/now/read?oid=047&aid=0002361645","retrieved":1659335530950},{"title":"[사진]방민아, '서울국제여성영화제 빛내는 미소'","contents":"1일 오후 서울 상암동 스탠포드호텔에서 ’24회 서울국제여성영화제’ 공식 기자회견이 열렸다. 홍보대사로 위촉된 배우 방민아가 포토타임을 하고 있다. 2022.08.01","link":"https://entertain.naver.com/movie/now/read?oid=109&aid=0004669639","retrieved":1659335530954},{"title":"[사진]서울국제여성영화제 홍보대사로 위촉된 방민아, '미소 가득'","contents":"1일 오후 서울 상암동 스탠포드호텔에서 ’24회 서울국제여성영화제’ 공식 기자회견이 열렸다. 배우 방민아가 박광수 집행위원장에게 위촉장을 전달받고 있다. 2022.08.01","link":"https://entertain.naver.com/movie/now/read?oid=109&aid=0004669638","retrieved":1659335530954},{"title":"[사진]서울국제여성영화제 홍보대사 방민아, '블랙으로 우아하게'","contents":"1일 오후 서울 상암동 스탠포드호텔에서 ’24회 서울국제여성영화제’ 공식 기자회견이 열렸다. 홍보대사로 위촉된 배우 방민아가 무대에 오르고 있다. 2022.08.01","link":"https://entertain.naver.com/movie/now/read?oid=109&aid=0004669637","retrieved":1659335530956},{"title":"[사진]방민아, '우아한 발걸음'","contents":"1일 오후 서울 상암동 스탠포드호텔에서 ’24회 서울국제여성영화제’ 공식 기자회견이 열렸다. 홍보대사로 위촉된 배우 방민아가 무대에 오르고 있다. 2022.08.01","link":"https://entertain.naver.com/movie/now/read?oid=109&aid=0004669635","retrieved":1659335530956},{"title":"[사진]방민아, '우아함 가득한 서울국제여성영화제 홍보대사'","contents":"1일 오후 서울 상암동 스탠포드호텔에서 ’24회 서울국제여성영화제’ 공식 기자회견이 열렸다. 홍보대사로 위촉된 배우 방민아가 포토타임을 하고 있다. 2022.08.01","link":"https://entertain.naver.com/movie/now/read?oid=109&aid=0004669634","retrieved":1659335530958},{"title":"[사진]24회 서울국제여성영화제 홍보대사로 위촉된 배우 방민아","contents":"1일 오후 서울 상암동 스탠포드호텔에서 ’24회 서울국제여성영화제’ 공식 기자회견이 열렸다. 홍보대사로 위촉된 배우 방민아 박광수 집행위원장과 포토타임을 하고 있다. 2022.08.01","link":"https://entertain.naver.com/movie/now/read?oid=109&aid=0004669633","retrieved":1659335530958},{"title":"[사진]방민아, '서울국제여성영화제의 미소'","contents":"1일 오후 서울 상암동 스탠포드호텔에서 ’24회 서울국제여성영화제’ 공식 기자회견이 열렸다. 홍보대사로 위촉된 배우 방민아가 인사말을 전하며 미소짓고 있다. 2022.08.01","link":"https://entertain.naver.com/movie/now/read?oid=109&aid=0004669632","retrieved":1659335530961},{"title":"[사진]방민아, '우아한 서울국제여성영화제 홍보대사'","contents":"1일 오후 서울 상암동 스탠포드호텔에서 ’24회 서울국제여성영화제’ 공식 기자회견이 열렸다. 홍보대사로 위촉된 배우 방민아가 포토타임을 하고 있다. 2022.08.01","link":"https://entertain.naver.com/movie/now/read?oid=109&aid=0004669630","retrieved":1659335530964},{"title":"[사진]방민아, '24회 서울국제여성영화제의 얼굴'","contents":"1일 오후 서울 상암동 스탠포드호텔에서 ’24회 서울국제여성영화제’ 공식 기자회견이 열렸다. 홍보대사로 위촉된 배우 방민아가 포토타임을 하고 있다. 2022.08.01","link":"https://entertain.naver.com/movie/now/read?oid=109&aid=0004669627","retrieved":1659335530965},{"title":"한한령 막히니 한국산 원작 재미보는 중국…리메이크 이어 웹툰 원작 영화까지","contents":"한한령 이후 국내 영화나 드라마의 중국 진출이 꽉 막혔으나 오히려 중국은 한국 콘텐츠를 활용해 대박을 터뜨리고 있는 것으로 나타났다. 한국 영화나 드라마를 리메이크 해서 흥행에 성공한 데 이어 한국 웹툰을 원작으로","link":"https://entertain.naver.com/movie/now/read?oid=011&aid=0004082589","retrieved":1659335530967},{"title":"'한산' 개봉 5일째 관객수 200만 돌파","contents":"박해일·변요한 주연의 '한산: 용의 출현'의 배급사 롯데엔터테인먼트 자료에 따르면 개봉 닷새째인 지난 31일 누적 관객수 200만 명을 돌파했다. 사진은 1일 서울 한 영화관에서 티켓을 구매하는 시민의 모습. 202","link":"https://entertain.naver.com/movie/now/read?oid=001&aid=0013347603","retrieved":1659335530970},{"title":"'한산' 개봉 5일째 관객수 200만 돌파","contents":"박해일·변요한 주연의 '한산: 용의 출현'의 배급사 롯데엔터테인먼트 자료에 따르면 개봉 닷새째인 지난 31일 누적 관객수 200만 명을 돌파했다. 사진은 1일 서울 한 영화관의 영화 시간표. 2022.8.1","link":"https://entertain.naver.com/movie/now/read?oid=001&aid=0013347602","retrieved":1659335530973},{"title":"'한산' 개봉 5일째 관객수 200만 돌파","contents":"박해일·변요한 주연의 '한산: 용의 출현'의 배급사 롯데엔터테인먼트 자료에 따르면 개봉 닷새째인 지난 31일 누적 관객수 200만 명을 돌파했다. 사진은 1일 서울 한 영화관에서 티켓을 구매하는 시민의 모습. 202","link":"https://entertain.naver.com/movie/now/read?oid=001&aid=0013347601","retrieved":1659335530974},{"title":"'한산' 개봉 5일째 관객수 200만 돌파","contents":"박해일·변요한 주연의 '한산: 용의 출현'의 배급사 롯데엔터테인먼트 자료에 따르면 개봉 닷새째인 지난 31일 누적 관객수 200만 명을 돌파했다. 사진은 1일 서울 한 영화관의 영화 시간표. 2022.8.1","link":"https://entertain.naver.com/movie/now/read?oid=001&aid=0013347600","retrieved":1659335530977},{"title":"'한산' 개봉 5일 만에 관객수 200만 돌파","contents":"박해일·변요한 주연의 '한산: 용의 출현'의 배급사 롯데엔터테인먼트 자료에 따르면 개봉 닷새째인 지난 31일 누적 관객수 200만 명을 돌파했다. 사진은 1일 서울 한 영화관의 영화 홍보 영상. 2022.8.1","link":"https://entertain.naver.com/movie/now/read?oid=001&aid=0013347599","retrieved":1659335530977},{"title":"'한산' 개봉 5일째 관객수 200만 돌파","contents":"박해일·변요한 주연의 '한산: 용의 출현'의 배급사 롯데엔터테인먼트 자료에 따르면 개봉 닷새째인 지난 31일 누적 관객수 200만 명을 돌파했다. 사진은 1일 서울 한 영화관의 영화 홍보물. 2022.8.1","link":"https://entertain.naver.com/movie/now/read?oid=001&aid=0013347598","retrieved":1659335530980},{"title":"'한산' 개봉 5일째 관객수 200만 돌파","contents":"박해일·변요한 주연의 '한산: 용의 출현'의 배급사 롯데엔터테인먼트 자료에 따르면 개봉 닷새째인 지난 31일 누적 관객수 200만 명을 돌파했다. 사진은 1일 서울 한 영화관의 영화 홍보 영상. 2022.8.1","link":"https://entertain.naver.com/movie/now/read?oid=001&aid=0013347597","retrieved":1659335530986},{"title":"'한산' 개봉 5일 만에 관객수 200만 돌파","contents":"박해일·변요한 주연의 '한산: 용의 출현'의 배급사 롯데엔터테인먼트 자료에 따르면 개봉 닷새째인 지난 31일 누적 관객수 200만 명을 돌파했다. 사진은 1일 서울 한 영화관의 영화 홍보 영상. 2022.8.1","link":"https://entertain.naver.com/movie/now/read?oid=001&aid=0013347596","retrieved":1659335530986},{"title":"[사진]환한 미소로 초대하는 '24회 서울국제여셩영화제'","contents":"1일 오후 서울 상암동 스탠포드호텔에서 ’24회 서울국제여성영화제’ 공식 기자회견이 열렸다. 김은실 이사장, 변재란 조직위원장, 박광수 집행위원장, 황미요조 프로그래머, 김현민 프로그래머와 홍보대사로 위촉된 배우 방","link":"https://entertain.naver.com/movie/now/read?oid=109&aid=0004669626","retrieved":1659335531019},{"title":"[TEN 포토] 방민아 '점점 더 말라가는 몸매'","contents":"그룹 걸스데이 출신 배우 방민아가 1일 오후 서울 마포구 상암동 스탠포드호텔 서울에서 열린 제 24회 서울국제여성영화제 공식 기자회견에 참석해 포즈를 취하고 있다. 조준원 기자","link":"https://entertain.naver.com/movie/now/read?oid=312&aid=0000561523","retrieved":1659335531019}]}